Workbook

Sheet 高科对内
A1: 销售员 | B1: 付款方式 | C1: 运费 | D1: 单位名称 | E1: 合同号 | F1: 合同有效期 | G1: 产品规格 | H1: 合同量 | I1: 销售单价 | J1: 销售金额 | K1: 实际出库 | L1: 未发量 | M1: 到款金额 | N1: 余款 | O1: 应收款 | P1: 出厂价 | Q1: 指导价 | R1: 合同总金额￥ | S1: 包装 | T1: 托盘 | U1: 缠绕膜 | V1: 扎带 | W1: 卡扣 | X1: 吨袋 | Y1: 绑带
A2: 毛晓翔 | B2: 本周35%预付，下周付款45%，本月底之前付清全款。 | C2: 自提 | D2: 浙江五合进出口有限公司 | E2: CHDN-20260312-106 | F2: 46174 | G2: CH301 | H2: 806.4 | I2: 15600 | J2: =H2*I2 -> 12579840 | K2: =680.96+125.44 -> 806.4 | L2: =H2-K2 -> 0 | M2: =高科收款!D6+高科收款!D10+高科收款!D17 -> 12579840 | N2: =J2-M2 -> 0 | O2: =K2*I2-M2 -> 0 | P2: 15305 | R2: =P2*H2 -> 12341952 | S2: 560kg/包，吨袋包装。 | T2: 720 | V2: 23 | W2: 2880 | X2: 1440
A3: 毛晓翔 | B3: 款到发货 | C3: 自提 | D3: 上海穗广贸易有限公司 | E3: CHDN-20260313-111 | F3: 46125 | G3: CH520 | H3: 18 | I3: 16100 | J3: =H3*I3 -> 289800 | K3: 18 | L3: =H3-K3 -> 0 | M3: =高科收款!D9 -> 289800 | N3: =J3-M3 -> 0 | O3: =K3*I3-M3 -> 0 | P3: 16100 | Q3: 16100 | R3: =P3*H3 -> 289800 | S3: 15kg/包散装，1*40HQ.
A4: 张晓敏 | B4: 100%预付 | C4: 送到 | D4: 浙江五合进出口有限公司 | E4: CHDN-20260319-133 | F4: 46131 | G4: CH332 | H4: 10 | I4: 16000 | J4: =H4*I4 -> 160000 | K4: =高科出库!E28 -> 10 | L4: =H4-K4 -> 0 | M4: =高科收款!D11 -> 160000 | N4: =J4-M4 -> 0 | O4: =K4*I4-M4 -> 0 | P4: 15860 | Q4: 15600 | R4: =P4*H4 -> 158600 | S4: 小包散装
A5: 毛晓翔 | B5: 款到发货 | C5: 自提 | D5: 苏州名创新材料有限公司 | E5: CHDN-20260323-160 | F5: 46111 | G5: CH510 | H5: 6 | I5: 17300 | J5: =H5*I5 -> 103800 | K5: 6 | L5: =H5-K5 -> 0 | M5: 103800 | N5: =J5-M5 -> 0 | O5: =K5*I5-M5 -> 0 | P5: 17300 | Q5: 17250 | R5: =P5*H5 -> 103800 | S5: 15kg/包散装
A6: 毛晓翔 | B6: 款到发货 | C6: 自提 | D6: 苏州名创新材料有限公司 | E6: CHDN-20260323-160 | F6: 46111 | G6: CH506 | H6: 6 | I6: 17500 | J6: =H6*I6 -> 105000 | K6: 6 | L6: =H6-K6 -> 0 | M6: 105000 | N6: =J6-M6 -> 0 | O6: =K6*I6-M6 -> 0 | P6: 17500 | Q6: 17250 | R6: =P6*H6 -> 105000 | S6: 15kg/包散装
A7: 毛晓翔 | B7: 100%预付 | C7: 送到 | D7: 昆山九子莲汽车隔音材料有限公司 | E7: CHDN-20260324-177 | F7: 46111 | G7: CH520 | H7: 11.04 | I7: 18100 | J7: =H7*I7 -> 199824 | K7: 11.04 | L7: =H7-K7 -> 0 | M7: =高科收款!D13 -> 199824 | N7: =J7-M7 -> 0 | O7: =K7*I7-M7 -> 0 | P7: 17945 | Q7: 17100 | R7: =P7*H7 -> 198112.8 | S7: 15kg/包散装
A8: 毛晓翔 | B8: 20%定金2026年4月10日之前付款，分批发货到7月底，发货前对应数量付全款，定金最后一批发货抵扣。 | C8: 自提 | D8: 浙江五合进出口有限公司 | E8: CHDN-20260325-180 | F8: 46249 | G8: CH332 | H8: 1708.8 | I8: 16489 | J8: =H8*I8 -> 28176403 | K8: =1401.6+153.6+153.6 -> 1708.8 | L8: =H8-K8 -> 0 | M8: =高科收款!D20+高科收款!D34+高科收款!D35+高科收款!D51+高科收款!D64+高科收款!D74+高科收款!D77+高科收款!D113+高科收款!D114+高科收款!D126 -> 28176403 | N8: =J8-M8 -> 0 | O8: =K8*I8-M8 -> 0 | P8: 16000 | Q8: 16000 | R8: =P8*H8 -> 27340800 | S8: 600kg/包，吨袋包装，其中一半带托盘，19.2吨/柜 | T8: =1248+176 -> 1424 | V8: =39+5.5 -> 44.5 | W8: =4992+704 -> 5696 | X8: =2496+352 -> 2848
A9: 张晓敏 | B9: 100%预付 | C9: 送到 | D9: 浙江五合进出口有限公司 | E9: CHDN-20260401-201 | F9: 46143 | G9: CH332 | H9: 43.28 | I9: 18200 | J9: =H9*I9 -> 787696 | K9: 43.28 | L9: =H9-K9 -> 0 | M9: =873600-(48-H9)*I9 -> 787696 | N9: =J9-M9 -> 0 | O9: =K9*I9-M9 -> 0 | P9: 17735 | Q9: 17600 | R9: =P9*H9 -> 767570.8 | S9: 240kg/包，吨袋包装 | X9: 200(小尺寸）
A10: 毛晓翔 | B10: 20%定金，提货前全款。 | C10: 自提 | D10: 宁波方觉科技有限公司 | E10: CHDN-20260408-214 | F10: 46142 | G10: CH520 | H10: 187.5 | I10: 21000 | J10: =H10*I10 -> 3937500 | K10: 187.5 | L10: =H10-K10 -> 0 | M10: =高科收款!D19+高科收款!D22+高科收款!D29 -> 3937500 | N10: =J10-M10 -> 0 | O10: =K10*I10-M10 -> 0 | P10: 21000 | Q10: 20500 | R10: =P10*H10 -> 3937500 | S10: 15kg/包散装
A11: 张晓敏 | B11: 100%预付 | C11: 自提 | D11: 浙江五合进出口有限公司 | E11: CHDN-20260511-234 | F11: 46184 | G11: CH301 | H11: 38 | I11: 14800 | J11: =H11*I11 -> 562400 | K11: 38 | L11: =H11-K11 -> 0 | M11: 562400 | N11: =J11-M11 -> 0 | O11: =K11*I11-M11 -> 0 | P11: 14800 | R11: =P11*H11 -> 562400 | S11: 20kg/包散装
A12: 张晓敏 | B12: 100%预付 | C12: 自提 | D12: 宁波澜塑新材料有限公司 | E12: CHDN-20260513-237 | F12: 46172 | G12: CH301 | H12: 4 | I12: 14600 | J12: =H12*I12 -> 58400 | K12: 4 | L12: =H12-K12 -> 0 | M12: 58400 | N12: =J12-M12 -> 0 | O12: =K12*I12-M12 -> 0 | P12: 14600 | R12: =P12*H12 -> 58400 | S12: 小包散货包装
A13: 张晓敏 | B13: 100%预付 | C13: 自提 | D13: 宁波澜塑新材料有限公司 | E13: CHDN-20260513-237 | F13: 46172 | G13: CH608 | H13: 2.5 | I13: 16600 | J13: =H13*I13 -> 41500 | K13: 2.5 | L13: =H13-K13 -> 0 | M13: 41500 | N13: =J13-M13 -> 0 | O13: =K13*I13-M13 -> 0 | P13: 16600 | R13: =P13*H13 -> 41500 | S13: 小包散货包装
A14: 毛晓翔 | B14: 全款承兑支付。 | C14: 自提 | D14: 金华穗广 | E14: CHDN-20260517-243 | F14: 46203 | G14: CH332 | H14: 100 | I14: 15850 | J14: =H14*I14 -> 1585000 | K14: =53.76+41.36+4.88 -> 100 | L14: =H14-K14 -> 0 | M14: =高科收款!D38 -> 1585000 | N14: =J14-M14 -> 0 | O14: =K14*I14-M14 -> 0 | P14: 15635 | Q14: 15500 | R14: =P14*H14 -> 1563500 | S14: 20kg小包带托盘 | T14: 320 | U14: 25 | V14: 10 | W14: 1280
A15: 张晓敏 | B15: 100%全款预付 | C15: 送到 | D15: 浙江五合进出口有限公司 | E15: CHDN-20260601-273 | F15: 46204 | G15: CH332 | H15: 24.2 | I15: 15200 | J15: =H15*I15 -> 367840 | K15: 24.2 | L15: =H15-K15 -> 0 | M15: =高科收款!D31+高科收款!D45-6688 -> 367840 | N15: =J15-M15 -> 0 | O15: =K15*I15-M15 -> 0 | P15: 14725 | Q15: 14500 | R15: =P15*H15 -> 356345 | S15: 220kg/包，吨袋包装 | X15: 112
A16: 毛晓翔 | B16: 全款承兑支付 | C16: 自提 | D16: 金华穗广 | E16: CHDN-20260601-274 | F16: 46234 | G16: CH332 | H16: 100 | I16: 14820 | J16: =H16*I16 -> 1482000 | K16: 100 | L16: =H16-K16 -> 0 | M16: =高科收款!D47 -> 1482000 | N16: =J16-M16 -> 0 | O16: =K16*I16-M16 -> 0 | P16: 14605 | Q16: 14500 | R16: =P16*H16 -> 1460500 | S16: 20kg小包带托盘 | T16: 320 | U16: 25 | V16: 10 | W16: 1280
A17: 毛晓翔 | B17: 款到发货 | C17: 自提 | D17: 苏州名创新材料有限公司 | E17: CHDN-20260610-293 | F17: 46188 | G17: CH506 | H17: 5.01 | I17: 16300 | J17: =H17*I17 -> 81663 | K17: =5.01 -> 5.01 | L17: =H17-K17 -> 0 | M17: 81663 | N17: =J17-M17 -> 0 | O17: =K17*I17-M17 -> 0 | P17: 16300 | Q17: 16250 | R17: =P17*H17 -> 81663 | S17: 15kg/包散装
A18: 毛晓翔 | B18: 全款预付 | C18: 自提 | D18: 宁海赤欣电器有限公司 | E18: CHDN-20260612-301 | F18: 46215 | G18: CH301 | H18: 17.92 | I18: 13400 | J18: =H18*I18 -> 240128 | K18: 17.92 | L18: =H18-K18 -> 0 | M18: =高科收款!D61 -> 240128 | N18: =J18-M18 -> 0 | O18: =K18*I18-M18 -> 0 | P18: 13163 | Q18: 13000 | R18: =P18*H18 -> 235880.96 | S18: 20kg小包带托盘 | T18: 32 | U18: 4 | V18: 1 | W18: 128
A19: 毛晓翔 | B19: 全款预付 | C19: 自提 | D19: 浙江五合进出口有限公司 | E19: CHDN-20260615-304 | F19: 46218 | G19: CH520 | H19: 1.5 | I19: 15850 | J19: =H19*I19 -> 23775 | K19: 1.5 | L19: =H19-K19 -> 0 | M19: =高科收款!D60 -> 23775 | N19: =J19-M19 -> 0 | O19: =K19*I19-M19 -> 0 | P19: 15500 | Q19: 15400 | R19: =P19*H19 -> 23250 | S19: 打3托，其中2托40包 ，1 托15包 | T19: 3
A20: 张晓敏 | B20: 全款预付 | C20: 自提 | D20: 陕西杰艾恩特贸易有限公司 | E20: CHDN-20260616-305 | F20: 46219 | G20: CH301 | H20: 7 | I20: 13000 | J20: =H20*I20 -> 91000 | K20: 7 | L20: =H20-K20 -> 0 | M20: =高科收款!D63 -> 91000 | N20: =J20-M20 -> 0 | O20: =K20*I20-M20 -> 0 | P20: 13000 | Q20: 13000 | R20: =P20*H20 -> 91000 | S20: 20kg 散货包装
A21: 张晓敏 | B21: 全款预付 | C21: 自提 | D21: 浙江五合进出口有限公司 | E21: CHDN-20260629-344 | F21: 46235 | G21: CH332 | H21: 266.24 | I21: 12200 | J21: =H21*I21 -> 3248128 | K21: =61.44+61.44+61.44+40.96+40.96 -> 266.24 | L21: =H21-K21 -> 0 | M21: =741440+高科收款!D68+高科收款!D69+6688 -> 3248128 | N21: =J21-M21 -> 0 | O21: =K21*I21-M21 -> 0 | P21: 12008 | Q21: 11800 | R21: =P21*H21 -> 3197009.9 | S21: 20kg小包带托盘 | T21: 416 | U21: 26 | V21: 13 | W21: 1664
A22: 毛晓翔 | B22: 款到发货 | C22: 自提 | D22: 苏州名创新材料有限公司 | E22: CHDN-20260706-361 | F22: 46223 | G22: CH506 | H22: 5.01 | I22: 13000 | J22: =H22*I22 -> 65130 | K22: 5.01 | L22: =H22-K22 -> 0 | M22: 65130 | N22: =J22-M22 -> 0 | O22: =K22*I22-M22 -> 0 | P22: 13000 | Q22: 12750 | R22: =P22*H22 -> 65130 | S22: 15kg/包散装
A23: 毛晓翔 | B23: 款到发货 | C23: 自提 | D23: 苏州名创新材料有限公司 | E23: CHDN-20260706-361 | F23: 46223 | G23: CH510 | H23: 5.01 | I23: 13000 | J23: =H23*I23 -> 65130 | K23: 5.01 | L23: =H23-K23 -> 0 | M23: 65130 | N23: =J23-M23 -> 0 | O23: =K23*I23-M23 -> 0 | P23: 13000 | Q23: 12750 | R23: =P23*H23 -> 65130 | S23: 15kg/包散装
A24: 张晓敏 | B24: 款到发货 | C24: 送到 | D24: 临沂天佑地毯有限公司 | E24: CHDN-20260707-366 | F24: 46223 | G24: CH520 | H24: 3 | I24: 13100 | J24: =H24*I24 -> 39300 | K24: =2.865+0.135 -> 3 | L24: =H24-K24 -> 0 | M24: =高科收款!D70 -> 39300 | N24: =J24-M24 -> 0 | O24: =K24*I24-M24 -> 0 | P24: 12720 | Q24: 12600 | R24: =P24*H24 -> 38160 | S24: 15kg/包散装
A25: 张晓敏 | B25: 款到发货 | C25: 送到 | D25: 浙江五合进出口有限公司 | E25: CHDN-20260708-371 | F25: 46265 | G25: CH332 | H25: 89.32 | I25: 12000 | J25: =H25*I25 -> 1071840 | K25: =50.6+25.52+13.2 -> 89.32 | L25: =H25-K25 -> 0 | M25: =高科收款!D75+高科收款!D76 -> 1071840 | N25: =J25-M25 -> 0 | O25: =K25*I25-M25 -> 0 | P25: 11500 | Q25: 11300 | R25: =P25*H25 -> 1027180 | S25: 220kg/包，吨袋包装
A26: 毛晓翔 | B26: 款到发货 | C26: 自提 | D26: 青岛玖盈化工有限公司 | E26: CHDN-20260709-382 | F26: 46223 | G26: CH520 | H26: 0.06 | I26: 15000 | J26: =H26*I26 -> 900 | K26: 0.06 | L26: =H26-K26 -> 0 | M26: =高科收款!D78 -> 900 | N26: =J26-M26 -> 0 | O26: =K26*I26-M26 -> 0 | P26: 15000 | Q26: 12600 | R26: =P26*H26 -> 900 | S26: 15kg/包散装
A27: 毛晓翔 | B27: 100%预付 | C27: 自提 | D27: 金华穗广 | E27: CHDN-20260713-398 | F27: 46233 | G27: CH301 | H27: 153.6 | I27: 12355 | J27: =H27*I27 -> 1897728 | K27: =38.4+57.6+57.6 -> 153.6 | L27: =H27-K27 -> 0 | M27: =高科收款!D80+高科收款!D82 -> 1897728 | N27: =J27-M27 -> 0 | O27: =K27*I27-M27 -> 0 | P27: 12111 | Q27: 12100 | R27: =P27*H27 -> 1860249.6 | S27: 600公斤吨袋 | T27: 128 | V27: 8 | W27: 512 | X27: 256
A28: 张晓敏 | B28: 款到发货 | C28: 自提 | D28: 浙江五合进出口有限公司 | E28: CHDN-20260714-403 | F28: 46265 | G28: CH332 | H28: 389.12 | I28: 12200 | J28: =H28*I28 -> 4747264 | K28: =41+61.5+61.5+61.5+163.62 -> 389.12 | L28: =H28-K28 -> 0 | M28: =高科收款!D79+高科收款!D88+高科收款!D92+1765568 -> 4747264 | N28: =J28-M28 -> 0 | O28: =K28*I28-M28 -> 0 | P28: 12010 | Q28: 12000 | R28: =P28*H28 -> 4673331.2 | S28: 20kg小包带托盘 | T28: =32*20 -> 640 | U28: =2*20 -> 40 | V28: =1*20 -> 20 | W28: =128*20 -> 2560
A29: 张晓敏 | B29: 款到发货 | C29: 自提 | D29: 浙江五合进出口有限公司 | E29: CHDN-20260714-403 | F29: 46265 | G29: CH301 | H29: 19.2 | I29: 12210 | J29: =H29*I29 -> 234432 | K29: 19.2 | L29: =H29-K29 -> 0 | M29: =高科收款!D93-1765568 -> 234432 | N29: =J29-M29 -> 0 | O29: =K29*I29-M29 -> 0 | P29: 12008 | Q29: 12000 | R29: =P29*H29 -> 230553.6 | S29: 20kg小包带托盘
A30: 毛晓翔 | B30: 款到发货 | C30: 自提 | D30: 杭州塑合新材料有限公司 | E30: CHDN-20260717-429 | F30: 46225 | G30: CH301 | H30: 0.3 | I30: 14000 | J30: =H30*I30 -> 4200 | K30: 0.3 | L30: =H30-K30 -> 0 | M30: =高科收款!D87 -> 4200 | N30: =J30-M30 -> 0 | O30: =K30*I30-M30 -> 0 | P30: 14000 | Q30: 13000 | R30: =P30*H30 -> 4200 | S30: 20kg 散货包装
A31: 毛晓翔 | B31: 款到发货 | C31: 自提 | D31: 苏州名创新材料有限公司 | E31: CHDN-20260722-450 | F31: 46233 | G31: CH510 | H31: 6 | I31: 14500 | J31: =H31*I31 -> 87000 | K31: 6 | L31: =H31-K31 -> 0 | M31: 87000 | N31: =J31-M31 -> 0 | O31: =K31*I31-M31 -> 0 | P31: 14500 | Q31: 14250 | R31: =P31*H31 -> 87000 | S31: 15kg/包散装
A32: 毛晓翔 | B32: 款到发货 | C32: 自提 | D32: 金华烯谷新材料有限公司 | E32: CHDN-20260723-458 | F32: 46244 | G32: CH608 | H32: 25 | I32: 13700 | J32: =H32*I32 -> 342500 | K32: 25 | L32: =H32-K32 -> 0 | M32: =高科收款!D91 -> 342500 | N32: =J32-M32 -> 0 | O32: =K32*I32-M32 -> 0 | P32: 13700 | R32: =P32*H32 -> 342500
A33: 张晓敏 | B33: 款到发货 | C33: 送到 | D33: 浙江五合进出口有限公司 | E33: CHDN-20260723-460 | F33: 46265 | G33: CH332 | H33: 70.84 | I33: 13600 | J33: =H33*I33 -> 963424 | K33: =26.4+26.4 -> 52.8 | L33: =H33-K33 -> 18.04 | M33: =高科收款!D110 -> 963424 | N33: =J33-M33 -> 0 | O33: =K33*I33-M33 -> -245344 | P33: 13110 | Q33: 13100 | R33: =P33*H33 -> 928712.4 | S33: 220kg/包；需324个小尺寸吨袋，单价46元/个
A34: 毛晓翔 | B34: 款到发货 | C34: 自提 | D34: 金华穗广 | E34: CHDN-20260724-461 | F34: 46249 | G34: CH301 | H34: 19.2 | I34: 13350 | J34: =H34*I34 -> 256320 | K34: 19.2 | L34: =H34-K34 -> 0 | M34: =高科收款!D111 -> 256320 | N34: =J34-M34 -> 0 | O34: =K34*I34-M34 -> 0 | P34: 13110 | R34: =P34*H34 -> 251712 | S34: 20kg小包带托盘 | T34: 32 | U34: 2 | V34: 1 | W34: 64
A35: 毛晓翔 | B35: 款到发货 | C35: 自提 | D35: 无锡市中捷诚化工有限公司 | E35: CHDN-20260728-472 | F35: 46253 | G35: CH608 | H35: 27 | I35: 14000 | J35: =H35*I35 -> 378000 | K35: 27 | L35: =H35-K35 -> 0 | M35: =高科收款!D100 -> 378000 | N35: =J35-M35 -> 0 | O35: =K35*I35-M35 -> 0 | P35: 14000 | Q35: 13700 | R35: =P35*H35 -> 378000
A36: 张晓敏 | B36: 款到发货 | C36: 送到 | D36: 浙江五合进出口有限公司 | E36: CHDN-20260731-479 | F36: 46265 | G36: CH332 | H36: 0.38 | I36: 12800 | J36: =H36*I36 -> 4864 | K36: 0.38 | L36: =H36-K36 -> 0 | M36: =高科收款!D94 -> 4864 | N36: =J36-M36 -> 0 | O36: =K36*I36-M36 -> 0 | P36: 12800 | Q36: 12600 | R36: =P36*H36 -> 4864 | S36: 20kg/包，散货
A37: 毛晓翔 | B37: 款到发货 | C37: 自提 | D37: 金华穗广 | E37: CHDN-20260805-492 | F37: 46264 | G37: CH332 | H37: 34 | I37: 12100 | J37: =H37*I37 -> 411400 | K37: 34 | L37: =H37-K37 -> 0 | M37: =513300-101900 -> 411400 | N37: =J37-M37 -> 0 | O37: =K37*I37-M37 -> 0 | P37: 12100 | R37: =P37*H37 -> 411400
A38: 毛晓翔 | B38: 款到发货 | C38: 自提 | D38: 金华穗广 | E38: CHDN-20260805-492 | F38: 46264 | G38: CH520 | H38: 6 | I38: 13800 | J38: =H38*I38 -> 82800 | K38: 6 | L38: =H38-K38 -> 0 | M38: 101900 | N38: =J38-M38 -> -19100 | O38: =K38*I38-M38 -> -19100 | P38: 13800 | R38: =P38*H38 -> 82800
A39: 毛晓翔 | B39: 款到发货 | C39: 自提 | D39: 苏州名创新材料有限公司 | E39: CHDN-20260810-515 | F39: 46254 | G39: CH510 | H39: 6 | I39: 14800 | J39: =H39*I39 -> 88800 | K39: 6 | L39: =H39-K39 -> 0 | M39: 88800 | N39: =J39-M39 -> 0 | O39: =K39*I39-M39 -> 0 | P39: 14800 | Q39: 14350 | R39: =P39*H39 -> 88800 | S39: 15kg/包散装
A40: 毛晓翔 | B40: 款到发货 | C40: 自提 | D40: 苏州名创新材料有限公司 | E40: CHDN-20260810-515 | F40: 46254 | G40: CH506 | H40: 4.5 | I40: 14800 | J40: =H40*I40 -> 66600 | K40: 4.5 | L40: =H40-K40 -> 0 | M40: 66600 | N40: =J40-M40 -> 0 | O40: =K40*I40-M40 -> 0 | P40: 14800 | Q40: 14350 | R40: =P40*H40 -> 66600 | S40: 15kg/包散装
A41: 张晓敏 | B41: 100%预付 | C41: 自提 | D41: 宁波澜塑新材料有限公司 | E41: CHDN-20260812-522 | F41: 46246 | G41: CH301 | H41: 8.5 | I41: 12400 | J41: =H41*I41 -> 105400 | K41: 8.5 | L41: =H41-K41 -> 0 | M41: =高科收款!D112 -> 105400 | N41: =J41-M41 -> 0 | O41: =K41*I41-M41 -> 0 | P41: 12400 | Q41: 12300 | R41: =P41*H41 -> 105400 | S41: 20kg 散货包装
A42: 毛晓翔 | B42: 款到发货 | C42: 自提 | D42: 上海穗广贸易有限公司 | E42: CHDN-20260812-523 | F42: 46295 | G42: CH520 | H42: 81.6 | I42: 14350 | J42: =H42*I42 -> 1170960 | K42: 81.6 | L42: =H42-K42 -> 0 | M42: =1412880-241920 -> 1170960 | N42: =J42-M42 -> 0 | O42: =K42*I42-M42 -> 0 | P42: 14110 | Q42: 14100 | R42: =P42*H42 -> 1151376 | S42: 15kg/包，托盘包装 | T42: 160 | U42: 10 | V42: 5 | W42: 640
A43: 毛晓翔 | B43: 款到发货 | C43: 自提 | D43: 上海穗广贸易有限公司 | E43: CHDN-20260812-523 | F43: 46295 | G43: CH332 | H43: 19.2 | I43: 12600 | J43: =H43*I43 -> 241920 | K43: 19.2 | L43: =H43-K43 -> 0 | M43: 241920 | N43: =J43-M43 -> 0 | O43: =K43*I43-M43 -> 0 | P43: 12355 | Q43: 12300 | R43: =P43*H43 -> 237216 | S43: 600公斤一包（一托2包） | T43: 16 | V43: 1 | W43: 64 | X43: 32
A44: 张晓敏 | B44: 款到发货 | C44: 自提 | D44: 浙江五合进出口有限公司 | E44: CHDN-20260818-542 | F44: 46295 | G44: CH332 | H44: 230.4 | I44: 13150 | J44: =H44*I44 -> 3029760 | K44: 230.4 | L44: =H44-K44 -> 0 | M44: =高科收款!D115 -> 3029760 | N44: =J44-M44 -> 0 | O44: =K44*I44-M44 -> 0 | P44: 12905 | Q44: 12800 | R44: =P44*H44 -> 2973312 | S44: 2吨袋 装1个托盘 | T44: =16*12 -> 192 | V44: =1*12 -> 12 | W44: =128*12 -> 1536
A45: 毛晓翔 | B45: 款到发货 | C45: 自提 | D45: 金华烯谷新材料有限公司 | E45: CHDN-20260828-582 | F45: 46285 | G45: CH332 | H45: 17.92 | I45: 13500 | J45: =H45*I45 -> 241920 | K45: 17.92 | L45: =H45-K45 -> 0 | M45: 241920 | N45: =J45-M45 -> 0 | O45: =K45*I45-M45 -> 0 | P45: 13260 | Q45: 13200 | R45: =P45*H45 -> 237619.2 | S45: 20kg小包带托盘 | T45: 32 | U45: 2 | V45: 1 | W45: 64
A46: 毛晓翔 | B46: 款到发货 | C46: 自提 | D46: 金华烯谷新材料有限公司 | E46: CHDN-20260828-582 | F46: 46285 | G46: CH520 | H46: 5.01 | I46: 15200 | J46: =H46*I46 -> 76152 | K46: 5.01 | L46: =H46-K46 -> 0 | M46: 76152 | N46: =J46-M46 -> 0 | O46: =K46*I46-M46 -> 0 | P46: 15200 | Q46: 15200 | R46: =P46*H46 -> 76152 | S46: 15kg/包散装
A47: 毛晓翔 | B47: 款到发货 | C47: 自提 | D47: 苏州名创新材料有限公司 | E47: CHDN-20260902-600 | F47: 46275 | G47: CH506 | H47: 6 | I47: 16500 | J47: =H47*I47 -> 99000 | K47: 6 | L47: =H47-K47 -> 0 | M47: 99000 | N47: =J47-M47 -> 0 | O47: =K47*I47-M47 -> 0 | P47: 16500 | Q47: 15550 | R47: =P47*H47 -> 99000 | S47: 15kg/包散装
A48: 毛晓翔 | B48: 款到发货 | C48: 自提 | D48: 苏州名创新材料有限公司 | E48: CHDN-20260902-600 | F48: 46275 | G48: CH510 | H48: 3 | I48: 16500 | J48: =H48*I48 -> 49500 | K48: 3 | L48: =H48-K48 -> 0 | M48: 49500 | N48: =J48-M48 -> 0 | O48: =K48*I48-M48 -> 0 | P48: 16500 | Q48: 15550 | R48: =P48*H48 -> 49500 | S48: 15kg/包散装
A49: 毛晓翔 | B49: 款到发货 | C49: 自提 | D49: 金华烯谷新材料有限公司 | E49: CHDN-20260904-611 | F49: 46295 | G49: CH332 | H49: 250 | I49: 14000 | J49: =H49*I49 -> 3500000 | K49: =64+64+122 -> 250 | L49: =H49-K49 -> 0 | M49: =高科收款!D122+高科收款!D125 -> 3500000 | N49: =J49-M49 -> 0 | O49: =K49*I49-M49 -> 0 | P49: 14000 | R49: =P49*H49 -> 3500000
A50: 毛晓翔 | B50: 款到发货 | C50: 自提 | D50: 上海穗广贸易有限公司 | E50: CHDN-20260904-612 | F50: 46295 | G50: CH520 | H50: 65.28 | I50: 16540 | J50: =H50*I50 -> 1079731.2 | K50: 0 | L50: =H50-K50 -> 65.28 | M50: =高科收款!D127-420268.8 -> 1079731.2 | N50: =J50-M50 -> 0 | O50: =K50*I50-M50 -> -1079731.2 | P50: 16300 | R50: =P50*H50 -> 1064064 | S50: 15kg/包，托盘包装
A51: 毛晓翔 | B51: 款到发货 | C51: 自提 | D51: 上海穗广贸易有限公司 | E51: CHDN-20260904-612 | F51: 46295 | G51: CH332 | H51: 249.6 | I51: 14310 | J51: =H51*I51 -> 3571776 | K51: 204.8 | L51: =H51-K51 -> 44.8 | M51: =420268.8+高科收款!D145 -> 2420268.8 | N51: =J51-M51 -> 1151507.2 | O51: =K51*I51-M51 -> 510419.2 | P51: 14100 | R51: =P51*H51 -> 3519360 | S51: 20kg/包，托盘包装
A52: 张晓敏 | B52: 100%预付 | C52: 自提 | D52: 浙江五合进出口有限公司 | E52: CHDN-20260904-613 | F52: 46305 | G52: CH332 | H52: 153.6 | I52: 14250 | J52: =H52*I52 -> 2188800 | K52: 153.6 | L52: =H52-K52 -> 0 | M52: =高科收款!D135 -> 2188800 | N52: =J52-M52 -> 0 | O52: =K52*I52-M52 -> 0 | P52: 14005 | R52: =P52*H52 -> 2151168 | T52: =8*16 -> 128 | V52: =8*1 -> 8 | W52: =8*128 -> 1024 | X52: =8*32 -> 256
A53: 毛晓翔 | B53: 款到发货 | C53: 自提 | D53: 苏州名创新材料有限公司 | E53: CHDN-20260909-630 | F53: 46285 | G53: CH506 | H53: 6 | I53: 17300 | J53: =H53*I53 -> 103800 | K53: 6 | L53: =H53-K53 -> 0 | M53: 103800 | N53: =J53-M53 -> 0 | O53: =K53*I53-M53 -> 0 | P53: 17300 | R53: =P53*H53 -> 103800 | S53: 15kg/包散装
A54: 毛晓翔 | B54: 款到发货 | C54: 自提 | D54: 苏州名创新材料有限公司 | E54: CHDN-20260909-630 | F54: 46285 | G54: CH510 | H54: 4.5 | I54: 17300 | J54: =H54*I54 -> 77850 | K54: 4.5 | L54: =H54-K54 -> 0 | M54: 77850 | N54: =J54-M54 -> 0 | O54: =K54*I54-M54 -> 0 | P54: 17300 | R54: =P54*H54 -> 77850 | S54: 15kg/包散装
A55: 毛晓翔 | B55: 款到发货 | C55: 自提 | D55: 金华烯谷新材料有限公司 | E55: CHDN-20260910-633 | F55: 46295 | G55: CH601 | H55: 12 | I55: 14600 | J55: =H55*I55 -> 175200 | K55: 12 | L55: =H55-K55 -> 0 | M55: =高科收款!D140 -> 175200 | N55: =J55-M55 -> 0 | O55: =K55*I55-M55 -> 0 | P55: 14600 | R55: =P55*H55 -> 175200 | S55: 15kg/包散装
A56: 毛晓翔 | B56: 款到发货 | C56: 自提 | D56: 苏州名创新材料有限公司 | E56: CHDN-20260914-641 | F56: 46285 | G56: CH506 | H56: 6 | I56: 17300 | J56: =H56*I56 -> 103800 | K56: 6 | L56: =H56-K56 -> 0 | M56: =高科收款!D129 -> 103800 | N56: =J56-M56 -> 0 | O56: =K56*I56-M56 -> 0 | P56: 17300 | R56: =P56*H56 -> 103800 | S56: 15kg/包散装
A57: 毛晓翔 | B57: 款到发货 | C57: 自提 | D57: 苏州名创新材料有限公司 | E57: CHDN-20260921-664 | F57: 46295 | G57: CH506 | H57: 6 | I57: 17300 | J57: =H57*I57 -> 103800 | K57: 6 | L57: =H57-K57 -> 0 | M57: =高科收款!D134 -> 103800 | N57: =J57-M57 -> 0 | O57: =K57*I57-M57 -> 0 | P57: 17300 | R57: =P57*H57 -> 103800 | S57: 15kg/包散装
A58: 毛晓翔 | B58: 款到发货 | C58: 送到 | D58: 昆山九子莲汽车隔音材料有限公司 | E58: CHDN-20260922-666 | F58: 46295 | G58: CH520 | H58: 4.05 | I58: 17500 | J58: =H58*I58 -> 70875 | K58: 4.05 | L58: =H58-K58 -> 0 | M58: =高科收款!D136 -> 70875 | N58: =J58-M58 -> 0 | O58: =K58*I58-M58 -> 0 | P58: 17100 | Q58: 16800 | R58: =P58*H58 -> 69255 | S58: 15kg/包散装
A59: 毛晓翔 | B59: 款到发货 | C59: 自提 | D59: 苏州名创新材料有限公司 | E59: CHDN-20260928-671 | F59: 46305 | G59: CH506 | H59: 6 | I59: 17300 | J59: =H59*I59 -> 103800 | K59: 6 | L59: =H59-K59 -> 0 | M59: 103800 | N59: =J59-M59 -> 0 | O59: =K59*I59-M59 -> 0 | P59: 17300 | Q59: 16650 | R59: =P59*H59 -> 103800 | S59: 15kg/包散装
A60: 毛晓翔 | B60: 款到发货 | C60: 自提 | D60: 上海穗广贸易有限公司 | E60: CHDN-20260928-674 | F60: 46310 | G60: CH301 | H60: 19.2 | I60: 14050 | J60: =H60*I60 -> 269760 | K60: 0 | L60: =H60-K60 -> 19.2 | M60: =高科收款!D137 -> 269760 | N60: =J60-M60 -> 0 | O60: =K60*I60-M60 -> -269760 | P60: 13845 | Q60: 13800 | R60: =P60*H60 -> 265824 | S60: 20公斤小包打托
A61: 毛晓翔 | B61: 款到发货 | C61: 自提 | D61: 金华烯谷新材料有限公司 | E61: CHDN-20260928-675 | F61: 46305 | G61: CH520 | H61: 15 | I61: 16800 | J61: =H61*I61 -> 252000 | K61: 15 | L61: =H61-K61 -> 0 | M61: 252000 | N61: =J61-M61 -> 0 | O61: =K61*I61-M61 -> 0 | P61: 16800 | R61: =P61*H61 -> 252000 | S61: 15公斤小包散装
A62: 毛晓翔 | B62: 款到发货 | C62: 自提 | D62: 金华烯谷新材料有限公司 | E62: CHDN-20260928-675 | F62: 46305 | G62: CH510 | H62: 3.75 | I62: 16950 | J62: =H62*I62 -> 63562.5 | K62: 3.75 | L62: =H62-K62 -> 0 | M62: 63562.5 | N62: =J62-M62 -> 0 | O62: =K62*I62-M62 -> 0 | P62: 16950 | R62: =P62*H62 -> 63562.5 | S62: 15公斤小包散装
A63: 毛晓翔 | B63: 款到发货 | C63: 自提 | D63: 苏州名创新材料有限公司 | E63: CHDN-20261009-701 | F63: 46310 | G63: CH506 | H63: 4.5 | I63: 17600 | J63: =H63*I63 -> 79200 | K63: 4.5 | L63: =H63-K63 -> 0 | M63: =高科收款!D144 -> 79200 | N63: =J63-M63 -> 0 | O63: =K63*I63-M63 -> 0 | P63: 17600 | Q63: 16950 | R63: =P63*H63 -> 79200 | S63: 15公斤小包散装
A64: 毛晓翔 | B64: 款到发货 | C64: 自提 | D64: 金华烯谷新材料有限公司 | E64: CHDN-20261010-708 | F64: 46326 | G64: CH332 | H64: 50 | I64: 13800 | J64: =H64*I64 -> 690000 | K64: 0 | L64: =H64-K64 -> 50 | M64: =高科收款!D154 -> 300000 | N64: =J64-M64 -> 390000 | O64: =K64*I64-M64 -> -300000 | P64: 13800 | Q64: 13800 | R64: =P64*H64 -> 690000 | S64: 20kg 散货包装
A65: 毛晓翔 | B65: 款到发货 | C65: 自提 | D65: 金华烯谷新材料有限公司 | E65: CHDN-20261010-708 | F65: 46326 | G65: CH332 | H65: 76.8 | I65: 14100 | J65: =H65*I65 -> 1082880 | K65: 0 | L65: =H65-K65 -> 76.8 | M65: 0 | N65: =J65-M65 -> 1082880 | O65: =K65*I65-M65 -> 0 | P65: 13840 | Q65: 13800 | R65: =P65*H65 -> 1062912 | S65: 吨袋 | T65: 64 | U65: 1 | V65: 4 | W65: 256 | X65: 128
A66: 毛晓翔 | B66: 款到发货 | C66: 自提 | D66: 上海穗广贸易有限公司 | E66: CHDN-20261010-709 | F66: 46325 | G66: CH301 | H66: 16.2 | I66: 14100 | J66: =H66*I66 -> 228420 | K66: 0 | L66: =H66-K66 -> 16.2 | M66: 0 | N66: =J66-M66 -> 228420 | O66: =K66*I66-M66 -> 0 | P66: 13895 | Q66: 13800 | R66: =P66*H66 -> 225099 | S66: 20公斤小包打托 | T66: 32 | U66: 2 | V66: 1 | W66: 64
A67: 毛晓翔 | B67: 款到发货 | C67: 自提 | D67: 上海穗广贸易有限公司 | E67: CHDN-20261010-709 | F67: 46325 | G67: CH332 | H67: 3 | I67: 14100 | J67: =H67*I67 -> 42300 | K67: 0 | L67: =H67-K67 -> 3 | M67: 0 | N67: =J67-M67 -> 42300 | O67: =K67*I67-M67 -> 0 | P67: 13895 | Q67: 13800 | R67: =P67*H67 -> 41685 | S67: 20公斤小包打托
A68: 毛晓翔 | B68: 款到发货 | C68: 自提 | D68: 苏州名创新材料有限公司 | E68: CHDN-20261014-730 | F68: 46311 | G68: CH506 | H68: 4.5 | I68: 17600 | J68: =H68*I68 -> 79200 | K68: 4.5 | L68: =H68-K68 -> 0 | M68: =高科收款!D146 -> 79200 | N68: =J68-M68 -> 0 | O68: =K68*I68-M68 -> 0 | P68: 17600 | Q68: 16950 | R68: =P68*H68 -> 79200 | S68: 15公斤小包散装
A69: 毛晓翔 | B69: 款到发货 | C69: 自提 | D69: 苏州名创新材料有限公司 | E69: CHDN-20261019-746 | F69: 46315 | G69: CH506 | H69: 6 | I69: 17600 | J69: =H69*I69 -> 105600 | K69: 6 | L69: =H69-K69 -> 0 | M69: =高科收款!D152 -> 105600 | N69: =J69-M69 -> 0 | O69: =K69*I69-M69 -> 0 | P69: 17600 | Q69: 16450 | R69: =P69*H69 -> 105600 | S69: 15公斤小包散装
A70: 毛晓翔 | B70: 款到发货 | C70: 自提 | D70: 金华烯谷新材料有限公司 | E70: CHDN-20261019-747 | F70: 46325 | G70: CH601 | H70: 12 | I70: 15100 | J70: =H70*I70 -> 181200 | K70: 0 | L70: =H70-K70 -> 12 | M70: =高科收款!D153 -> 181200 | N70: =J70-M70 -> 0 | O70: =K70*I70-M70 -> -181200 | P70: 15100 | Q70: 15100 | R70: =P70*H70 -> 181200 | S70: 20kg 散货包装
A71: 毛晓翔 | B71: 款到发货 | C71: 自提 | D71: 上海穗广贸易有限公司 | E71: CHDN-20261019-748 | F71: 46325 | G71: CH520 | H71: 30.66 | I71: 16300 | J71: =H71*I71 -> 499758 | K71: 0 | L71: =H71-K71 -> 30.66 | M71: 0 | N71: =J71-M71 -> 499758 | O71: =K71*I71-M71 -> 0 | P71: 16300 | Q71: 16300 | R71: =P71*H71 -> 499758 | S71: 15公斤小包散装
A72: 毛晓翔 | B72: 款到发货 | C72: 自提 | D72: 苏州名创新材料有限公司 | E72: CHDN-20261021-769 | F72: 46325 | G72: CH506 | H72: 4.5 | I72: 17600 | J72: =H72*I72 -> 79200 | K72: 4.5 | L72: =H72-K72 -> 0 | M72: 79200 | N72: =J72-M72 -> 0 | O72: =K72*I72-M72 -> 0 | P72: 17600 | Q72: 16450 | R72: =P72*H72 -> 79200 | S72: 15公斤小包散装
A73: 毛晓翔 | B73: 款到发货 | C73: 自提 | D73: 苏州名创新材料有限公司 | E73: CHDN-20261021-769 | F73: 46325 | G73: CH510 | H73: 6 | I73: 17600 | J73: =H73*I73 -> 105600 | K73: 6 | L73: =H73-K73 -> 0 | M73: 105600 | N73: =J73-M73 -> 0 | O73: =K73*I73-M73 -> 0 | P73: 17600 | Q73: 16450 | R73: =P73*H73 -> 105600 | S73: 15公斤小包散装

Sheet 高科对外
A1: 销售员 | B1: 付款方式 | C1: 单位名称 | D1: 合同号 | E1: 合同有效期 | F1: 产品规格 | G1: 合同量 | H1: 销售单价 | I1: 销售金额 | J1: 实际出库 | K1: 未发量 | L1: 到款金额 | M1: 余款 | N1: 应收款 | O1: 佣金 | P1: 佣金总金额 | Q1: 审批汇率 | R1: 出厂价 | S1: 指导价 | T1: 合同总金额￥ | U1: 包装 | V1: 运输条款 | W1: 目的港 | X1: 审批海运费 | Y1: 审批保费 | Z1: 审批内陆费 | AA1: 实际海运费 | AB1: 托盘数量 | AC1: 缠绕膜 | AD1: 扎带 | AE1: 卡扣 | AF1: 吨袋 | AG1: 绑带 | AH1: 备注 | AI1: 开票
A2: 杨玉赏 | B2: 50/50TT | C2: INABATA SINGAPORE (PTE.) LTD. | D2: CHDW-20260408-017 | E2: 46172 | F2: CH520 | G2: 75 | H2: 2860 | I2: =G2*H2 -> 214500 | J2: 0 | K2: =G2-J2 -> 75 | L2: 0 | M2: =I2-L2 -> 214500 | N2: =J2*H2-L2 -> 0 | O2: 0 | P2: =P20 -> 0 | Q2: 6.86 | R2: 20530 | S2: 20500 | T2: =R2*G2 -> 1539750 | U2: 15KG小包散装 | V2: CIF | W2: IZMIR | X2: =4*3400 -> 13600 | Y2: =4*50 -> 200 | Z2: =4*4000 -> 16000
A3: 杨玉赏 | B3: 50/50TT | C3: INABATA SINGAPORE (PTE.) LTD. | D3: CHDW-20260409-018 | E3: 46178 | F3: CH520 | G3: 56.25 | H3: 2880 | I3: =G3*H3 -> 162000 | J3: 0 | K3: =G3-J3 -> 56.25 | L3: 0 | M3: =I3-L3 -> 162000 | N3: =J3*H3-L3 -> 0 | O3: 0 | P3: =P2 -> 0 | Q3: 6.81 | R3: 20506 | S3: 20500 | T3: =R3*G3 -> 1153462.5 | U3: 15KG小包散装 | V3: CIF | W3: IZMIR | X3: =3*3400 -> 10200 | Y3: =3*50 -> 150 | Z3: =3*4500 -> 13500
A4: 张晓敏 | B4: 30/80TT | C4: EMAAR SQUARE GENERAL TRADING & CONT.CO | D4: CHDW-20260105-001 | E4: 46058 | F4: CH332 | G4: 19.2 | H4: 1720 | I4: =G4*H4 -> 33024 | J4: 19.2 | K4: =G4-J4 -> 0 | L4: =高科收款!D2+高科收款!D5 -> 32984 | M4: =I4-L4 -> 40 | N4: =J4*H4-L4 -> 40 | O4: 0 | P4: =O4*G4 -> 0 | Q4: 6.95 | R4: 12007 | S4: 11400 | T4: =R4*G4 -> 230534.4 | U4: 20kg带托盘 | V4: CIF | W4: 科威特Shuwaikh港 | X4: 2600 | Y4: 38 | Z4: 4500 | AB4: 32 | AC4: 4 | AD4: 1 | AE4: 130 | AH4: 0.8吨不执行
A5: 毛晓翔 | B5: 20/80TT | C5: LSMCHEM GLOBAL PTE. LTD. | D5: CHDW-20260108-002 | E5: 46063 | F5: CH301 | G5: 492.72 | H5: 1485 | I5: =G5*H5 -> 731689.2 | J5: =316.8+57.6+高科出库!E16+高科出库!E57+高科出库!E58+54.88 -> 492.72 | K5: =G5-J5 -> 0 | L5: =高科收款!D3+高科收款!D4 -> 741286 | M5: =I5-L5 -> -9596.8 | N5: =J5*H5-L5 -> -9596.8 | O5: 0 | P5: =O5*G5 -> 0 | Q5: 6.982 | R5: 11440 | S5: 11400 | T5: =R5*G5 -> 5636716.8 | U5: 600kg带托盘 | V5: EXW | W5: FACTORY | X5: 0 | Y5: 0 | Z5: 0 | AA5: 0 | AB5: 416 | AD5: 13 | AE5: 1664 | AF5: 832
A6: 张晓敏 | B6: 20/80TT | C6: RIYING INTERNATIONAL TRADING COMPANY LIMITED | D6: CHDW-20260113-003 | E6: 46091 | F6: CH301 | G6: 19.2 | H6: 1540 | I6: =G6*H6 -> 29568 | J6: =高科出库!E17 -> 19.2 | K6: =G6-J6 -> 0 | L6: =23960.99+5607.01 -> 29568 | M6: =I6-L6 -> 0 | N6: =J6*H6-L6 -> 0 | O6: 0 | P6: =O6*G6 -> 0 | Q6: 6.96 | R6: 11731 | S6: 11650 | T6: =R6*G6 -> 225235.2 | U6: 600kg带托盘 | V6: EXW | W6: FACTORY | X6: 0 | Y6: 0 | Z6: 0 | AA6: 0 | AB6: 32 | AD6: 1 | AE6: 128 | AF6: 32 | AH6: 18.75吨不执行
A7: 张晓敏 | B7: 30/70TT | C7: RIYING INTERNATIONAL TRADING COMPANY LIMITED | D7: CHDW-20260116-004 | E7: 46092 | F7: CH520 | G7: 37.5 | H7: 1700 | I7: =G7*H7 -> 63750 | J7: 37.5 | K7: =G7-J7 -> 0 | L7: =50936.99-5607.01+18420.02 -> 63750 | M7: =I7-L7 -> 0 | N7: =J7*H7-L7 -> 0 | O7: 0 | P7: =O7*G7 -> 0 | Q7: 6.95 | R7: 13345 | S7: 13200 | T7: =R7*G7 -> 500437.5 | U7: 15kg散装 | V7: EXW | W7: FACTORY | X7: 0 | Y7: 0 | Z7: 0 | AA7: 0
A8: 张晓敏 | B8: 30/70TT | C8: Garant-PP LTD | D8: CHDW-20260305-005 | E8: 46122 | F8: CH301 | G8: 71.68 | H8: 1732 | I8: =G8*H8 -> 124149.76 | J8: 71.68 | K8: =G8-J8 -> 0 | L8: =高科收款!D7 -> 79273.83 | M8: =I8-L8 -> 44875.93 | N8: =J8*H8-L8 -> 44875.93 | O8: 0 | P8: =O8*G8 -> 0 | Q8: 6.9 | R8: 13644 | T8: =R8*G8 -> 978001.92 | U8: 600kg吨袋 托盘包装 | V8: CIF | W8: 保加利亚Burgas | X8: =3700*4 -> 14800 | Y8: =42.4*4 -> 169.6 | Z8: =4000*4 -> 16000 | AB8: 160 | AC8: 4 | AD8: 7 | AE8: 896 | AF8: 128
A9: 张晓敏 | B9: 30/70TT | C9: Garant-PP LTD | D9: CHDW-20260305-005 | E9: 46122 | F9: CH301 | G9: =35.84+17.92 -> 53.76 | H9: 1732 | I9: =G9*H9 -> 93112.32 | J9: =35.84+17.92 -> 53.76 | K9: =G9-J9 -> 0 | L9: =高科收款!D40 -> 169922.68 | M9: =I9-L9 -> -76810.36 | N9: =J9*H9-L9 -> -76810.36 | O9: 0 | P9: =O9*G9 -> 0 | Q9: 6.9 | R9: 13695 | T9: =R9*G9 -> 736243.2 | U9: 20kg/包 托盘包装 | V9: CIF | W9: 保加利亚Burgas | X9: =3700*3 -> 11100 | Y9: =42.4*3 -> 127.2 | Z9: =4000*3 -> 12000
A10: 张晓敏 | B10: 50/50TT | C10: RIYING INTERNATIONAL TRADING COMPANY LIMITED | D10: CHDW-20260305-006 | E10: 46122 | F10: CH301 | G10: 53.76 | H10: 1770 | I10: =G10*H10 -> 95155.2 | J10: 53.76 | K10: =G10-J10 -> 0 | L10: =44990.21-18420.02+高科收款!D62 -> 94999.17 | M10: =I10-L10 -> 156.03 | N10: =J10*H10-L10 -> 156.03 | O10: 0 | P10: =O10*G10 -> 0 | Q10: 6.9 | R10: 13420 | T10: =R10*G10 -> 721459.2 | U10: 600kg 吨袋托盘包装 | V10: EXW | W10: FACTORY | X10: 0 | Y10: 0 | Z10: 0 | AA10: 0 | AB10: 96 | AD10: 3 | AE10: 384 | AF10: 96
A11: 杨玉赏 | B11: 100TT | C11: INABATA SINGAPORE (PTE.) LTD. | D11: CHDW-20260306-007 | E11: 46132 | F11: CH520 | G11: 130.56 | H11: 2290 | I11: =G11*H11 -> 298982.4 | J11: 130.56 | K11: =G11-J11 -> 0 | L11: =高科收款!D25 -> 298982.4 | M11: =I11-L11 -> 0 | N11: =J11*H11-L11 -> 0 | O11: 0 | P11: =O11*G11 -> 0 | Q11: 6.9 | R11: 15354 | S11: 15350 | T11: =R11*G11 -> 2004618.2 | U11: 15KG小包托盘 | V11: CIF | W11: GEBZE | X11: =4000*8 -> 32000 | Y11: =30*8 -> 240 | Z11: =4000*8 -> 32000 | AB11: 256 | AC11: 32 | AD11: 8 | AE11: 1040
A12: 杨玉赏 | B12: 100TT | C12: INABATA SINGAPORE (PTE.) LTD. | D12: CHDW-20260312-008 | E12: 46124 | F12: CH520 | G12: 48.96 | H12: 2405 | I12: =G12*H12 -> 117748.8 | J12: 48.96 | K12: =G12-J12 -> 0 | L12: =高科收款!D26 -> 117748.8 | M12: =I12-L12 -> 0 | N12: =J12*H12-L12 -> 0 | O12: 0 | P12: =O12*G12 -> 0 | Q12: 6.87 | R12: 16178 | S12: 16100 | T12: =R12*G12 -> 792074.88 | U12: 15KG小包托盘 | V12: CIF | W12: GEBZE | X12: =4000*3 -> 12000 | Y12: =30*3 -> 90 | Z12: =4000*3 -> 12000 | AB12: 96 | AC12: 12 | AD12: 3 | AE12: 390
A13: 张晓敏 | B13: 30/70TT | C13: CHINA UNICHEM HOLDINGS PTE LTD | D13: CHDW-20260316-009 | E13: 46122 | F13: CH520 | G13: 56.25 | H13: 2115 | I13: =G13*H13 -> 118968.75 | J13: 56.25 | K13: =G13-J13 -> 0 | L13: =高科收款!D8+83253 -> 118919 | M13: =I13-L13 -> 49.75 | N13: =J13*H13-L13 -> 49.75 | O13: 0 | P13: =O13*G13 -> 0 | Q13: 6.89 | R13: 16226 | T13: =R13*G13 -> 912712.5 | U13: 15KG小包散装 | V13: FOB | W13: NINGBO | X13: 0 | Y13: 0 | Z13: 5000 | AA13: 0
A14: 杨玉赏 | B14: 100TT | C14: INABATA SINGAPORE (PTE.) LTD. | D14: CHDW-20260318-010 | E14: 46143 | F14: CH520 | G14: 75 | H14: 2390 | I14: =G14*H14 -> 179250 | J14: =37.5+37.5 -> 75 | K14: =G14-J14 -> 0 | L14: =高科收款!D32 -> 179250 | M14: =I14-L14 -> 0 | N14: =J14*H14-L14 -> 0 | O14: 0 | P14: =O14*G14 -> 0 | Q14: 6.87 | R14: 16550 | S14: 16400 | T14: =R14*G14 -> 1241250 | U14: 15KG小包散装 | V14: CIF | W14: IZMIR | X14: =4200*4 -> 16800 | Y14: =50*4 -> 200 | Z14: =4000*4 -> 16000
A15: 陈诺 | B15: 100TT | C15: Rare International Corp. | D15: CHDW-20260320-011 | E15: 46132 | F15: CH265 | G15: 34.2 | H15: 1860 | I15: =G15*H15 -> 63612 | J15: 34.2 | K15: =G15-J15 -> 0 | L15: =高科收款!D14 -> 63612 | M15: =I15-L15 -> 0 | N15: =J15*H15-L15 -> 0 | O15: 0 | P15: =O15*G15 -> 0 | Q15: 6.87 | R15: 14024 | S15: 13700 | T15: =R15*G15 -> 479620.8 | U15: 30KG小包散装 | V15: CIF | W15: Ho Chi Minh | X15: =300*2 -> 600 | Y15: =35*2 -> 70 | Z15: =4500*2 -> 9000
A16: 陈诺 | B16: 100TT | C16: Rare International Corp. | D16: CHDW-20260323-012 | E16: 46135 | F16: CH265 | G16: 17.1 | H16: 1930 | I16: =G16*H16 -> 33003 | J16: 17.1 | K16: =G16-J16 -> 0 | L16: =高科收款!D15 -> 33003 | M16: =I16-L16 -> 0 | N16: =J16*H16-L16 -> 0 | O16: 0 | P16: =O16*G16 -> 0 | Q16: 6.87 | R16: 14000 | S16: 13700 | T16: =R16*G16 -> 239400 | U16: 30KG小包散装 | V16: CIF | W16: CHITTAGONG | X16: 1550 | Y16: 35 | Z16: 4500
A17: 陶莹 | B17: 100TT | C17: WWRC Korea Co.,Ltd | D17: CHDW-20260326-013 | E17: 46138 | F17: CH301 | G17: 35.84 | H17: 2160 | I17: =G17*H17 -> 77414.4 | J17: 35.84 | K17: =G17-J17 -> 0 | L17: 77414.4 | M17: =I17-L17 -> 0 | N17: =J17*H17-L17 -> 0 | O17: 0 | P17: =O17*G17 -> 0 | Q17: 6.89 | R17: 16167 | S17: 16100 | T17: =R17*G17 -> 579425.28 | U17: 560kg/吨包带托盘 | V17: CIF | W17: BUSAN | X17: 0 | Y17: =43*2 -> 86 | Z17: =4000*2 -> 8000 | AB17: 96 | AD17: 3 | AE17: 390 | AF17: 96 | AG17: 3
A18: 毛晓翔 | B18: 100TT | C18: PALMETTO ADHESIVES COMPANY | D18: CHDW-20260330-014 | E18: 46142 | F18: CH520 | G18: 1.68 | H18: 2780 | I18: =G18*H18 -> 4670.4 | J18: 1.68 | K18: =G18-J18 -> 0 | L18: 4670.4 | M18: =I18-L18 -> 0 | N18: =J18*H18-L18 -> 0 | O18: 0 | P18: =O18*G18 -> 0 | Q18: 6.85 | R18: 17750 | S18: 17100 | T18: =R18*G18 -> 29820 | U18: 15KG小包托盘 | V18: CIF | W18: Charleston | X18: 500 | Y18: 10 | Z18: 2000 | AB18: 4
A19: 杨玉赏 | B19: 50/50TT | C19: INABATA SINGAPORE (PTE.) LTD. | D19: CHDW-20260402-015 | E19: 46175 | F19: CH520 | G19: 97.92 | H19: 3015 | I19: =G19*H19 -> 295228.8 | J19: 97.92 | K19: =G19-J19 -> 0 | L19: =高科收款!D21+高科收款!D33 -> 295228.8 | M19: =I19-L19 -> 0 | N19: =J19*H19-L19 -> 0 | O19: 0 | P19: =O19*G19 -> 0 | Q19: 6.86 | R19: 21110 | S19: 20000 | T19: =R19*G19 -> 2067091.2 | U19: 15KG小包托盘 | V19: CIF | W19: GEBZE | X19: =6*3500 -> 21000 | Y19: =6*50 -> 300 | Z19: =4000*6 -> 24000 | AB19: 192 | AC19: 24 | AD19: 6 | AE19: 780
A20: 杨玉赏 | B20: 30/70TT | C20: SOPREMA LTDA | D20: CHDW-20260407-016 | E20: 46149 | F20: CH301 | G20: 19 | H20: 2585 | I20: =G20*H20 -> 49115 | J20: 19 | K20: =G20-J20 -> 0 | L20: =高科收款!D28+高科收款!D48 -> 49115 | M20: =I20-L20 -> 0 | N20: =J20*H20-L20 -> 0 | O20: 0 | P20: =P19 -> 0 | Q20: 6.87 | R20: 18294 | S20: 18000 | T20: =R20*G20 -> 347586 | U20: 20kg/包散装 | V20: CIF | W20: SANTOS | X20: 3700 | Y20: 50 | Z20: 4000
A21: 杨玉赏 | B21: 50/50TT | C21: INABATA SINGAPORE (PTE.) LTD. | D21: CHDW-20260414-019 | E21: 46203 | F21: CH520 | G21: 37.5 | H21: 2925 | I21: =G21*H21 -> 109687.5 | J21: 37.5 | K21: =G21-J21 -> 0 | L21: =高科收款!D27+高科收款!D43 -> 109687.5 | M21: =I21-L21 -> 0 | N21: =J21*H21-L21 -> 0 | O21: 0 | P21: =P3 -> 0 | Q21: 6.81 | R21: 20811 | S21: 20600 | T21: =R21*G21 -> 780412.5 | U21: 15KG小包散装
A22: 陈诺 | B22: 100TT | C22: Rare International Corp. | D22: CHDW-20260414-020 | E22: 46156 | F22: CH406 | G22: 9.6 | H22: 2535 | I22: =G22*H22 -> 24336 | J22: 9.6 | K22: =G22-J22 -> 0 | L22: =高科收款!D23 -> 24336 | M22: =I22-L22 -> 0 | N22: =J22*H22-L22 -> 0 | O22: 0 | P22: =P21 -> 0 | Q22: 6.8 | R22: 18370 | S22: 18000 | T22: =R22*G22 -> 176352 | U22: 20kg/包托盘 | V22: CIF | W22: TAICHUNG | X22: 525 | Y22: 27 | Z22: 4000
A23: 杨玉赏 | B23: 100TT | C23: SOPREMA LTDA | D23: CHDW-20260420-021 | E23: 46203 | F23: CH301 | G23: 19 | H23: 2620 | I23: =G23*H23 -> 49780 | J23: 19 | K23: =G23-J23 -> 0 | L23: =高科收款!D65 -> 49780 | M23: =I23-L23 -> 0 | N23: =J23*H23-L23 -> 0 | O23: 0 | P23: =P22 -> 0 | Q23: 6.8 | R23: 18324 | S23: 18000 | T23: =R23*G23 -> 348156 | U23: 20kg/包散装 | V23: CIF | W23: SANTOS | X23: 2400 | Y23: 50 | Z23: 4000
A24: 杨玉赏 | B24: 100TT | C24: INABATA SINGAPORE (PTE.) LTD. | D24: CHDW-20260509-022 | E24: 46188 | F24: CH520 | G24: 65.28 | H24: 2760 | I24: =G24*H24 -> 180172.8 | J24: =32.64+32.64 -> 65.28 | K24: =G24-J24 -> 0 | L24: =高科收款!D50 -> 180172.8 | M24: =I24-L24 -> 0 | N24: =J24*H24-L24 -> 0 | O24: 0 | P24: =P23 -> 0 | Q24: 6.79 | R24: 18299 | S24: 18000 | T24: =R24*G24 -> 1194558.7 | U24: 15KG小包托盘 | V24: CIF | W24: GEBZE | X24: =4900*3 -> 14700 | Y24: =60*3 -> 180 | Z24: =4500*3 -> 13500
A25: 毛晓翔 | B25: 100TT | C25: DONGJU M&TCORPORATION | D25: CHDW-20260519-023 | E25: 46192 | F25: CH406 | G25: 44.8 | H25: 2100 | I25: =G25*H25 -> 94080 | J25: 44.8 | K25: =G25-J25 -> 0 | L25: =高科收款!D41 -> 94060 | M25: =I25-L25 -> 20 | N25: =J25*H25-L25 -> 20 | O25: 0 | P25: =P24 -> 0 | Q25: 6.79 | R25: 15638 | S25: 14500 | T25: =R25*G25 -> 700582.4 | U25: 25kg小包托盘 | V25: CIF | W25: BUSAN | X25: =250*2 -> 500 | Y25: =52*2 -> 104 | Z25: =4500*2 -> 9000
A26: 毛晓翔 | B26: 20/80TT | C26: LSMCHEM GLOBAL PTE. LTD. | D26: CHDW-20260519-024 | E26: 46203 | F26: CH301 | G26: 111.36 | H26: 1890 | I26: =G26*H26 -> 210470.4 | J26: =92.16+19.2 -> 111.36 | K26: =G26-J26 -> 0 | L26: =高科收款!D53+高科收款!D44+162544.24-25745.48 -> 210470.4 | M26: =I26-L26 -> 0 | N26: =J26*H26-L26 -> 0 | O26: 0 | P26: =P25 -> 0 | Q26: 6.79 | R26: 14215 | S26: 14000 | T26: =R26*G26 -> 1582982.4 | U26: 560kg吨袋 | V26: EXW | W26: FACTORY | X26: 0 | Y26: 0 | Z26: 0 | AB26: 288 | AC26: 24 | AD26: 12 | AE26: 1536 | AF26: 88
A27: 毛晓翔 | B27: 20/80TT | C27: LSMCHEM GLOBAL PTE. LTD. | D27: CHDW-20260519-024 | E27: 46203 | F27: CH301 | G27: 19.2 | H27: 1890 | I27: =G27*H27 -> 36288 | J27: 19.2 | K27: =G27-J27 -> 0 | L27: =高科收款!D81-162544.24 -> 36288 | M27: =I27-L27 -> 0 | N27: =J27*H27-L27 -> 0 | O27: 0 | P27: =P26 -> 0 | Q27: 6.79 | R27: 14290 | S27: 14000 | T27: =R27*G27 -> 274368 | U27: 20kg小包带托盘 | V27: EXW | W27: FACTORY | X27: 0 | Y27: 0 | Z27: 0
A28: 毛晓翔 | B28: 20/80TT | C28: LSMCHEM GLOBAL PTE. LTD. | D28: CHDW-20260519-024 | E28: 46203 | F28: CH302 | G28: 96 | H28: 2050 | I28: =G28*H28 -> 196800 | J28: =38.4+38.4+19.2 -> 96 | K28: =G28-J28 -> 0 | L28: =高科收款!D39+25745.48+高科收款!D96 -> 196707 | M28: =I28-L28 -> 93 | N28: =J28*H28-L28 -> 93 | O28: 0 | P28: =P27 -> 0 | Q28: 6.79 | R28: 15519 | S28: 15500 | T28: =R28*G28 -> 1489824 | U28: 20kg小包带托盘 | V28: EXW | W28: FACTORY | X28: 0 | Y28: 0 | Z28: 0
A29: 陶莹 | B29: 100TT | C29: W CHEM KOREA | D29: CHDW-20260528-025 | E29: 46201 | F29: CH301 | G29: 17.92 | H29: 1880 | I29: =G29*H29 -> 33689.6 | J29: 17.92 | K29: =G29-J29 -> 0 | L29: =高科收款!D49 -> 33671.6 | M29: =I29-L29 -> 18 | N29: =J29*H29-L29 -> 18 | O29: 0 | P29: =P28 -> 0 | Q29: 6.77 | R29: 13700 | S29: 13500 | T29: =R29*G29 -> 245504 | U29: 560kg吨袋 | V29: CIF | W29: BUSAN | X29: 0 | Y29: 200 | Z29: 37 | AB29: 32 | AD29: 1 | AE29: 130 | AF29: 32 | AG29: 60
A30: 杨玉赏 | B30: 100TT | C30: SOPREMA LTDA | D30: CHDW-20260603-026 | E30: 46206 | F30: CH301 | G30: 19 | H30: 2620 | I30: =G30*H30 -> 49780 | J30: 19 | K30: =G30-J30 -> 0 | L30: =高科收款!D99 -> 49780 | M30: =I30-L30 -> 0 | N30: =J30*H30-L30 -> 0 | O30: 0 | P30: =P29 -> 0 | Q30: 6.75 | R30: 16589 | S30: 13000 | T30: =R30*G30 -> 315191 | U30: 20kg/包散装 | V30: CIF | W30: SANTOS | X30: 7600 | Y30: 60 | Z30: 5500
A31: 毛晓翔 | B31: 30/70TT | C31: PALMETTO ADHESIVES COMPANY | D31: CHDW-20260604-027 | E31: 46182 | F31: CH520 | G31: 15.36 | H31: 2765 | I31: =G31*H31 -> 42470.4 | J31: 15.36 | K31: =G31-J31 -> 0 | L31: =高科收款!D54+高科收款!D103 -> 42428.4 | M31: =I31-L31 -> 42 | N31: =J31*H31-L31 -> 42 | O31: 0 | P31: =P30 -> 0 | Q31: 6.75 | R31: 17150 | S31: 15500 | T31: =R31*G31 -> 263424 | U31: 15kg小包带托盘 | V31: CIF | W31: Charleston | X31: 6700 | Y31: 47 | Z31: 5000 | AB31: 32 | AC31: 2 | AD31: 1 | AE31: 64
A32: 陶莹 | B32: 100TT | C32: De Monchy International B.V | D32: CHDW-20260605-028 | E32: 46208 | F32: CH302 | G32: 1.2 | H32: 2060 | I32: =G32*H32 -> 2472 | J32: 1.2 | K32: =G32-J32 -> 0 | L32: =高科收款!D52 -> 2464 | M32: =I32-L32 -> 8 | N32: =J32*H32-L32 -> 8 | O32: 0 | P32: =P31 -> 0 | Q32: 6.7646 | R32: 14640 | S32: 14600 | T32: =R32*G32 -> 17568 | U32: 600kg带托盘 | V32: FOB | W32: NINGBO | X32: 0 | Y32: 0 | Z32: 1000 | AB32: 2 | AF32: 2
A33: 杨玉赏 | B33: 100TT | C33: INABATA SINGAPORE (PTE.) LTD. | D33: CHDW-20260608-029 | E33: 46211 | F33: CH301 | G33: 17.92 | H33: 1870 | I33: =G33*H33 -> 33510.4 | J33: 17.92 | K33: =G33-J33 -> 0 | L33: 33510.4 | M33: =I33-L33 -> 0 | N33: =J33*H33-L33 -> 0 | O33: 0 | P33: =P32 -> 0 | Q33: 6.77 | R33: 13266 | S33: 13000 | T33: =R33*G33 -> 237726.72 | U33: 20kg/包托盘 | V33: CIF | W33: SINGAPORE | X33: =1050 -> 1050 | Y33: =40 -> 40 | Z33: =5500 -> 5500 | AB33: 32 | AC33: 4 | AD33: 1 | AE33: 128
A34: 杨玉赏 | B34: 100TT | C34: INABATA SINGAPORE (PTE.) LTD. | D34: CHDW-20260608-030 | E34: 46211 | F34: CH520 | G34: 97.92 | H34: 2560 | I34: =G34*H34 -> 250675.2 | J34: =32.64+32.64+32.64 -> 97.92 | K34: =G34-J34 -> 0 | L34: 250675.2 | M34: =I34-L34 -> 0 | N34: =J34*H34-L34 -> 0 | O34: 0 | P34: =P33 -> 0 | Q34: 6.77 | R34: 15766 | S34: 15500 | T34: =R34*G34 -> 1543806.7 | U34: 15KG小包托盘 | V34: CIF | W34: GEBZE | X34: =6*6800 -> 40800 | Y34: =6*50 -> 300 | Z34: =6*5500 -> 33000 | AB34: 192 | AC34: 12 | AD34: 6 | AE34: 384
A35: 毛晓翔 | B35: 20/80TT | C35: LSMCHEM GLOBAL PTE. LTD. | D35: CHDW-20260608-031 | E35: 46234 | F35: CH301 | G35: 168 | H35: 1740 | I35: =G35*H35 -> 292320 | J35: =72+38.4+57.6 -> 168 | K35: =G35-J35 -> 0 | L35: =高科收款!D59+高科收款!D83+334368-184026 -> 292320 | M35: =I35-L35 -> 0 | N35: =J35*H35-L35 -> 0 | O35: 0 | P35: =P34 -> 0 | Q35: 6.77 | R35: 13044 | S35: 13000 | T35: =R35*G35 -> 2191392 | U35: 600kg吨袋 | V35: EXW | W35: FACTORY | X35: 0 | Y35: 0 | Z35: 0 | AB35: 320 | AC35: 40 | AD35: 20 | AE35: 2560 | AF35: 640
A36: 毛晓翔 | B36: 20/80TT | C36: LSMCHEM GLOBAL PTE. LTD. | D36: CHDW-20260608-031 | E36: 46234 | F36: CH332 | G36: 216 | H36: 1935 | I36: =G36*H36 -> 417960 | J36: 216 | K36: =G36-J36 -> 0 | L36: =184026+高科收款!D106+高科收款!D119 -> 417856 | M36: =I36-L36 -> 104 | N36: =J36*H36-L36 -> 104 | O36: 0 | P36: =P35 -> 0 | Q36: 6.77 | R36: 14535 | S36: 14500 | T36: =R36*G36 -> 3139560 | U36: 600kg吨袋 | V36: EXW | W36: FACTORY | X36: 0 | Y36: 0 | Z36: 0
A37: 张晓敏 | B37: 30/70TT | C37: Garant-PP LTD | D37: CHDW-20260702-032 | E37: 46236 | F37: CH301 | G37: 38.4 | H37: 2009 | I37: =G37*H37 -> 77145.6 | J37: 38.4 | K37: =G37-J37 -> 0 | L37: =23053.12+高科收款!D128 -> 77762.88 | M37: =I37-L37 -> -617.28 | N37: =高科收款!D72 -> 23053.12 | O37: 0 | P37: =P36 -> 0 | Q37: 6.77 | R37: 12057 | S37: 11900 | T37: =R37*G37 -> 462988.8 | U37: 600kg吨袋 | V37: CIF | W37: 保加利亚Burgas | X37: =7090*2 -> 14180 | Y37: =42.3*2 -> 84.6 | Z37: =4000*2 -> 8000 | AB37: 32 | AC37: 4 | AD37: 2 | AE37: 256 | AF37: 64
A38: 杨玉赏 | B38: 100TT | C38: INABATA SINGAPORE (PTE.) LTD. | D38: CHDW-20260708-033 | E38: 46265 | F38: CH520 | G38: 97.92 | H38: 2310 | I38: =G38*H38 -> 226195.2 | J38: =65.28+32.64 -> 97.92 | K38: =G38-J38 -> 0 | L38: =高科收款!D98 -> 226195.2 | M38: =I38-L38 -> 0 | N38: =J38*H38-L38 -> 0 | O38: 0 | P38: =P37 -> 0 | Q38: 6.78 | R38: 13964 | S38: 12500 | T38: =R38*G38 -> 1367354.9 | U38: 小包托盘 | V38: CIF | W38: GEBZE | X38: =6600*6 -> 39600 | Y38: =60*6 -> 360 | Z38: =5500*6 -> 33000 | AB38: 192 | AC38: 12 | AD38: 6 | AE38: 384
A39: 张晓敏 | B39: 30/70TT | C39: CHINA UNICHEM HOLDINGS PTE LTD | D39: CHDW-20260708-034 | E39: 46241 | F39: CH520 | G39: 16.32 | H39: 1725 | I39: =G39*H39 -> 28152 | J39: =高科出库!E330 -> 16.32 | K39: =G39-J39 -> 0 | L39: =高科收款!D84+高科收款!D132 -> 28102 | M39: =I39-L39 -> 50 | N39: =J39*H39-L39 -> 50 | O39: 0 | P39: =P38 -> 0 | Q39: 6.78 | R39: 12638 | S39: 12600 | T39: =R39*G39 -> 206252.16 | U39: 15kg小包带托盘 | V39: FOB | W39: NINGBO | X39: =0 -> 0 | Y39: 0 | Z39: 5500 | AB39: 32 | AC39: 2 | AD39: 1 | AE39: 128
A40: 张晓敏 | B40: 30/70TT | C40: CHINA UNICHEM HOLDINGS PTE LTD | D40: CHDW-20260714-035 | E40: 46248 | F40: CH520 | G40: 37.5 | H40: 1760 | I40: =G40*H40 -> 66000 | J40: 37.5 | K40: =G40-J40 -> 0 | L40: =高科收款!D89+高科收款!D148 -> 65950 | M40: =I40-L40 -> 50 | N40: =J40*H40-L40 -> 50 | O40: 0 | P40: =P39 -> 0 | Q40: 6.77 | R40: 13197 | S40: 13100 | T40: =R40*G40 -> 494887.5 | U40: 15kg小包散装 | V40: FOB | W40: NINGBO | X40: =0 -> 0 | Y40: 0 | Z40: =5000*2 -> 10000
A41: 杨玉赏 | B41: 100TT | C41: IDB DO BRASIL TRADING LTDA | D41: CHDW-20260719-036 | E41: 46265 | F41: CH301 | G41: 19 | H41: 2060 | I41: =G41*H41 -> 39140 | J41: 0 | K41: =G41-J41 -> 19 | L41: 0 | M41: =I41-L41 -> 39140 | N41: =J41*H41-L41 -> 0 | O41: 0 | P41: =P40 -> 0 | Q41: 6.75 | R41: 13024 | S41: 13000 | T41: =R41*G41 -> 247456 | U41: 20kg/包散装 | V41: CFR | W41: Navegantes | X41: 5900 | Y41: =30*G41 -> 570 | Z41: 5500
A42: 杨玉赏 | B42: 30/70TT | C42: INABATA SINGAPORE (PTE.) LTD. | D42: CHDW-20260729-037 | E42: 46295 | F42: CH520 | G42: 131.25 | H42: 2550 | I42: =G42*H42 -> 334687.5 | J42: 37.5 | K42: =G42-J42 -> 93.75 | L42: =高科收款!D109+高科收款!D130 -> 167343.75 | M42: =I42-L42 -> 167343.75 | N42: =J42*H42-L42 -> -71718.75 | O42: 0 | P42: =P41 -> 0 | Q42: 6.76 | R42: 16518 | S42: 14200 | T42: =R42*G42 -> 2167987.5 | U42: 散货包装 | V42: CIF | W42: IZMIR | X42: =6500*7 -> 45500 | Y42: =50*7 -> 350 | Z42: =5000*7 -> 35000
A43: 陶莹 | B43: 100TT | C43: Rare International Corp. | D43: CHDW-20260807-038 | E43: 46272 | F43: CH269 | G43: 36.6 | H43: 1600 | I43: =G43*H43 -> 58560 | J43: 36.6 | K43: =G43-J43 -> 0 | L43: =高科收款!D102+高科收款!D108 -> 58560 | M43: =I43-L43 -> 0 | N43: =J43*H43-L43 -> 0 | O43: 0 | P43: =P42 -> 0 | Q43: 6.7355 | R43: 11800 | S43: 14201 | T43: =R43*G43 -> 431880 | U43: 30KG小包散装 | V43: CIF | W43: Ho Chi Minh | X43: =200*2 -> 400 | Y43: =32*2 -> 64 | Z43: =4500*2 -> 9000
A44: 杨玉赏 | B44: 100TT | C44: INABATA SINGAPORE (PTE.) LTD. | D44: CHDW-20260809-039 | E44: 46295 | F44: CH520 | G44: 65.28 | H44: 2270 | I44: =G44*H44 -> 148185.6 | J44: =32.64+32.64 -> 65.28 | K44: =G44-J44 -> 0 | L44: 148185.6 | M44: =I44-L44 -> 0 | N44: =J44*H44-L44 -> 0 | O44: 0 | P44: =P43 -> 0 | Q44: 6.74 | R44: 14169 | S44: 13700 | T44: =R44*G44 -> 924952.32 | U44: 15KG小包托盘 | V44: CIF | W44: GEBZE | X44: =4*5400 -> 21600 | Y44: =4*50 -> 200 | Z44: =4*5000 -> 20000 | AB44: 128 | AC44: 8 | AD44: 4 | AE44: 256
A45: 毛晓翔 | B45: 20/80TT | C45: LSMCHEM GLOBAL PTE. LTD. | D45: CHDW-20260812-040 | E45: 46295 | F45: CH301 | G45: 76.8 | H45: 1670 | I45: =G45*H45 -> 128256 | J45: 76.8 | K45: =G45-J45 -> 0 | L45: =高科收款!D107+高科收款!D116 -> 128230 | M45: =I45-L45 -> 26 | N45: =J45*H45-L45 -> 26 | O45: 0 | P45: =P44 -> 0 | Q45: 6.7345 | R45: 12463 | S45: 12300 | T45: =R45*G45 -> 957158.4 | U45: 600kg吨袋 | V45: EXW | W45: FACTORY | X45: 0 | Y45: 0 | Z45: 0 | AB45: 64 | AD45: 4 | AE45: 256
A46: 张晓敏 | B46: 100TT | C46: ISOCHEMICALS KIMYA ANONIM SIRKETI | D46: CHDW-20260814-041 | E46: 46279 | F46: CH520 | G46: 56.25 | H46: 1975 | I46: =G46*H46 -> 111093.75 | J46: 0 | K46: =G46-J46 -> 56.25 | L46: 0 | M46: =I46-L46 -> 111093.75 | N46: =J46*H46-L46 -> 0 | O46: 0 | P46: =P45 -> 0 | Q46: 6.73 | R46: 14779 | S46: 14700 | T46: =R46*G46 -> 831318.75 | U46: 15kg小包散装 | V46: FOB | W46: NINGBO | X46: =0 -> 0 | Y46: 0 | Z46: =3*4500 -> 13500
A47: 杨玉赏 | B47: 100TT | C47: INABATA SINGAPORE (PTE.) LTD. | D47: CHDW-20260819-042 | E47: 46284 | F47: CH301 | G47: 17.92 | H47: 1825 | I47: =G47*H47 -> 32704 | J47: 17.92 | K47: =G47-J47 -> 0 | L47: 32704 | M47: =I47-L47 -> 0 | N47: =J47*H47-L47 -> 0 | O47: 0 | P47: =P46 -> 0 | Q47: 6.72 | R47: 12871 | S47: 12800 | T47: =R47*G47 -> 230648.32 | U47: 20kg小包带托盘 | V47: CIF | W47: SINGAPORE | X47: 1000 | Y47: 40 | Z47: 5000
A48: 毛晓翔 | B48: 15%TT 75%LC120 | C48: OCEAN THERMOPLASTIC ELASTOMERS PVT LTD | D48: CHDW-20260831-043 | E48: 46295 | F48: CH520 | G48: 36 | H48: 2100 | I48: =G48*H48 -> 75600 | J48: 36 | K48: =G48-J48 -> 0 | L48: =高科收款!D118 -> 11302 | M48: =I48-L48 -> 64298 | N48: =J48*H48-L48 -> 64298 | O48: 0 | P48: =P47 -> 0 | Q48: 6.71 | R48: 15589 | T48: =R48*G48 -> 561204 | U48: 15kg小包散装 | V48: FOB | W48: NINGBO | X48: =0 -> 0 | Y48: 0 | Z48: =6000*2 -> 12000
A49: 杨玉赏 | B49: 100TT | C49: SAMTEC Co., Ltd. | D49: CHDW-20260902-044 | E49: 46297 | F49: CH520 | G49: 1.92 | H49: 2325 | I49: =G49*H49 -> 4464 | J49: 1.92 | K49: =G49-J49 -> 0 | L49: =高科收款!D121 -> 4444 | M49: =I49-L49 -> 20 | N49: =J49*H49-L49 -> 20 | O49: 0 | P49: =P48 -> 0 | Q49: 6.71 | R49: 16272 | S49: 16200 | T49: =R49*G49 -> 31242.24 | U49: 15KG小包托盘 | V49: CIF | W49: 仁川 | X49: 0 | Y49: 10 | Z49: 2000 | AB49: 4 | AC49: 50元 | AD49: 50元 | AE49: 8
A50: 毛晓翔 | B50: 20/80TT | C50: LSMCHEM GLOBAL PTE. LTD. | D50: CHDW-20260902-045 | E50: 46297 | F50: CH510 | G50: 15.36 | H50: 2230 | I50: =G50*H50 -> 34252.8 | J50: 15.36 | K50: =G50-J50 -> 0 | L50: =高科收款!D133+高科收款!D150 -> 9204.56 | M50: =I50-L50 -> 25048.24 | N50: =J50*H50-L50 -> 25048.24 | O50: 0 | P50: =P49 -> 0 | Q50: 6.71 | R50: 16527 | S50: 15550 | T50: =R50*G50 -> 253854.72 | U50: 2个吨袋1个托盘包装，480公斤一包 | V50: EXW | W50: FACTORY | X50: 0 | Y50: 0 | Z50: 0 | AB50: 16 | AD50: 1 | AE50: 64 | AF50: 32
A51: 陶莹 | B51: 100TT | C51: WWRC Korea Co.,Ltd | D51: CHDW-20260904-046 | E51: 46299 | F51: CH520 | G51: 0.48 | H51: 2780 | I51: =G51*H51 -> 1334.4 | J51: 0.48 | K51: =G51-J51 -> 0 | L51: =高科收款!D123 -> 1334.4 | M51: =I51-L51 -> 0 | N51: =J51*H51-L51 -> 0 | O51: 0 | P51: =P50 -> 0 | Q51: 6.71 | R51: 17520 | S51: 16500 | T51: =R51*G51 -> 8409.6 | U51: 15KG小包托盘 | V51: CIF | W51: 釜山 | X51: 0 | Y51: 10 | Z51: 1500 | AB51: 1 | AC51: 20元 | AD51: 20元 | AE51: 2
A52: 杨玉赏 | B52: 100TT | C52: INABATA SINGAPORE (PTE.) LTD. | D52: CHDW-20260904-047 | E52: 46299 | F52: CH520 | G52: 16.32 | H52: 2550 | I52: =G52*H52 -> 41616 | J52: 16.32 | K52: =G52-J52 -> 0 | L52: 41616 | M52: =I52-L52 -> 0 | N52: =J52*H52-L52 -> 0 | O52: 0 | P52: =P53 -> 0 | Q52: 6.7 | R52: 16417 | T52: =R52*G52 -> 267925.44 | U52: 15KG小包托盘 | V52: CIF | W52: GEBZE | X52: 4500 | Y52: 50 | Z52: 5000 | AB52: 32 | AC52: 2.5 | AD52: 1 | AE52: 64
A53: 杨玉赏 | B53: 100TT | C53: INABATA SINGAPORE (PTE.) LTD. | D53: CHDW-20260904-048 | E53: 46299 | F53: CH520 | G53: 32.64 | H53: 2540 | I53: =G53*H53 -> 82905.6 | J53: 16.32 | K53: =G53-J53 -> 16.32 | L53: 0 | M53: =I53-L53 -> 82905.6 | N53: =J53*H53-L53 -> 41452.8 | O53: 0 | P53: =P51 -> 0 | Q53: 6.7 | R53: 16509 | T53: =R53*G53 -> 538853.76 | U53: 15KG小包托盘 | V53: CIF | W53: GEBZE | X53: =4500*2 -> 9000 | Y53: =50*2 -> 100 | Z53: =5000*2 -> 10000 | AB53: 64 | AC53: 5 | AD53: 2 | AE53: 132
A54: 毛晓翔 | B54: 20/80TT | C54: LSMCHEM GLOBAL PTE. LTD. | D54: CHDW-20260914-049 | E54: 46326 | F54: CH301 | G54: 286.72 | H54: 1900 | I54: =G54*H54 -> 544768 | J54: 286.72 | K54: =G54-J54 -> 0 | L54: 544768 | M54: =I54-L54 -> 0 | N54: =J54*H54-L54 -> 0 | O54: 0 | P54: =P52 -> 0 | Q54: 6.7012 | R54: 14035 | T54: =R54*G54 -> 4024115.2 | U54: 2个吨袋1个托盘包装，必须600公斤一包 | V54: EXW | W54: FACTORY | X54: 0 | Y54: 0 | Z54: 0 | AB54: 480 | AC54: 30 | AD54: 30 | AE54: 1920 | AF54: 960 | AH54: 报关费约100元/票,包装成本265元/吨，物产库换包人工费160元/吨（预计换288吨）
A55: 毛晓翔 | B55: 20/80TT | C55: LSMCHEM GLOBAL PTE. LTD. | D55: CHDW-20260914-049 | E55: 46326 | F55: CH332 | G55: 288 | H55: 1900 | I55: =G55*H55 -> 547200 | J55: 288 | K55: =G55-J55 -> 0 | L55: 547200 | M55: =I55-L55 -> 0 | N55: =J55*H55-L55 -> 0 | O55: 0 | P55: =P53 -> 0 | Q55: 6.7012 | R55: 14035 | T55: =R55*G55 -> 4042080 | U55: 2个吨袋1个托盘包装，必须600公斤一包 | V55: EXW | W55: FACTORY | X55: 0 | Y55: 0 | Z55: 0
A56: 张晓敏 | B56: 30/70TT | C56: MIDDLE EAST PLASTIC MARKETING FZE | D56: CHDW-20260923-050 | E56: 46318 | F56: CH520 | G56: 16.32 | H56: 2280 | I56: =G56*H56 -> 37209.6 | J56: 16.32 | K56: =G56-J56 -> 0 | L56: =高科收款!D147 -> 11127.87 | M56: =I56-L56 -> 26081.73 | N56: =J56*H56-L56 -> 26081.73 | O56: 0 | P56: =P54 -> 0 | Q56: 6.69 | R56: 16659 | T56: =R56*G56 -> 271874.88 | U56: 15KG小包托盘 | V56: FOB | W56: NINGBO | X56: 0 | Y56: 0 | Z56: 5500
A57: 张晓敏 | B57: 30/70TT | C57: CHINA UNICHEM HOLDINGS PTE LTD | D57: CHDW-20261014-051 | E57: 46340 | F57: CH520 | G57: 16.32 | H57: 2265 | I57: =G57*H57 -> 36964.8 | J57: 16.32 | K57: =G57-J57 -> 0 | L57: =高科收款!D151 -> 11064.44 | M57: =I57-L57 -> 25900.36 | N57: =J57*H57-L57 -> 25900.36 | O57: 0 | P57: =P55 -> 0 | Q57: 6.674 | R57: 16505 | S57: 16500 | T57: =R57*G57 -> 269361.6 | U57: 15KG小包托盘 | V57: FOB | W57: NINGBO | X57: 0 | Y57: 0 | Z57: 5500 | AB57: 32 | AC57: 2 | AD57: 1 | AE57: 128
A58: 杨玉赏 | B58: 100TT | C58: INABATA SINGAPORE (PTE.) LTD. | D58: CHDW-20261014-052 | E58: 46356 | F58: CH520 | G58: 65.28 | H58: 2595 | I58: =G58*H58 -> 169401.6 | J58: 0 | K58: =G58-J58 -> 65.28 | L58: 0 | M58: =I58-L58 -> 169401.6 | N58: =J58*H58-L58 -> 0 | O58: 0 | P58: =P56 -> 0 | Q58: 6.674 | R58: 16667 | S58: 16500 | T58: =R58*G58 -> 1088021.8 | U58: 15KG小包托盘 | V58: CIF | W58: GEBZE | X58: =4*4500 -> 18000 | Y58: =4*50 -> 200 | Z58: =4*5000 -> 20000 | AB58: 106 | AC58: 8 | AD58: 4 | AE58: 256

Sheet 高科收款
A1: 日期 | B1: 客户 | C1: 合同号 | D1: 收款金额 | E1: 付款方式 | F1: 备注
A2: 46029 | B2: EMAAR SQUARE GENERAL TRADING & CONT.CO | C2: CHDW-20260105-001 | D2: 10320 | E2: TT | F2: 001 预付
A3: 46029 | B3: LSMCHEM GLOBAL PTE. LTD. | C3: CHDW-20260108-002 | D3: 148236.4 | E3: TT | F3: 002 20%预付
A4: 46085 | B4: LSMCHEM GLOBAL PTE. LTD. | C4: CHDW-20260108-002 | D4: 593049.6 | E4: TT | F4: 002 尾款
A5: 46094 | B5: EMAAR SQUARE GENERAL TRADING & CONT.CO | C5: CHDW-20260105-001 | D5: 22664 | E5: TT | F5: 001 尾款
A6: 46094 | B6: 浙江五合进出口有限公司 | C6: CHDN-20260312-106 | D6: 4402944 | E6: TT | F6: 106 货款
A7: 46097 | B7: Garant-PP LTD | C7: CHDW-20260305-005 | D7: 79273.83 | E7: TT | F7: 005 货款 | G7: 69835
A8: 46100 | B8: CHINA UNICHEM HOLDINGS PTE LTD | C8: CHDW-20260316-009 | D8: 35666 | E8: TT | F8: 009 预付
A9: 46100 | B9: 上海穗广贸易有限公司 | C9: CHDN-20260313-111 | D9: 289800 | E9: TT | F9: 111 货款
A10: 46100 | B10: 浙江五合进出口有限公司 | C10: CHDN-20260312-106 | D10: 5660928 | E10: TT | F10: 106 货款
A11: 46100 | B11: 浙江五合进出口有限公司 | C11: CHDN-20260319-133 | D11: 160000 | E11: TT | F11: 133 货款
A12: 46104 | B12: 苏州名创新材料有限公司 | C12: CHDN-20260323-160 | D12: 208800 | E12: TT | F12: 160 货款
A13: 46106 | B13: 昆山九子莲汽车隔音材料有限公司 | C13: CHDN-20260324-177 | D13: 199824 | E13: TT | F13: 177 货款
A14: 46107 | B14: Rare International Corp. | C14: CHDW-20260320-011 | D14: 63612 | E14: TT | F14: 011 全款
A15: 46107 | B15: Rare International Corp. | C15: CHDW-20260323-012 | D15: 33003 | E15: TT | F15: 012 全款
A16: 46111 | B16: PALMETTO ADHESIVES COMPANY | C16: CHDW-20260330-014 | D16: 4660.4 | E16: TT | F16: 014 全款
A17: 46111 | B17: 浙江五合进出口有限公司 | C17: CHDN-20260312-106 | D17: 2515968 | E17: TT | F17: 106 货款
A18: 46113 | B18: WWRC Korea Co.,Ltd | C18: CHDW-20260326-013 | D18: 77414.4 | E18: TT | F18: 013 全款
A19: 46122 | B19: 宁波方觉科技有限公司 | C19: CHDN-20260408-214 | D19: 787500 | E19: TT | F19: 214 货款
... A23: 46128 | B23: Rare International Corp. | C23: CHDW-20260414-020 | D23: 24336 | E23: TT | F23: 020 全款
A24: 46128 | B24: Rare International Corp. | D24: 80 | E24: TT | F24: 样品费
A25: 46132 | B25: INABATA SINGAPORE (PTE.) LTD. | C25: CHDW-20260306-007 | D25: 298982.4 | E25: TT | F25: 007 全款
A26: 46132 | B26: INABATA SINGAPORE (PTE.) LTD. | C26: CHDW-20260312-008 | D26: 117748.8 | E26: TT | F26: 008 全款
A27: 46132 | B27: INABATA SINGAPORE (PTE.) LTD. | C27: CHDW-20260414-019 | D27: =109687.5/2 -> 54843.75 | E27: TT | F27: 019 50%预付款
A28: 46139 | B28: SOPREMA LTDA | C28: CHDW-20260407-016 | D28: 14734.5 | E28: TT | F28: 016 30%预付款
A29: 46139 | B29: 宁波方觉科技有限公司 | C29: CHDN-20260408-214 | D29: 1575000 | E29: TT | F29: 214 货款
A30: 46141 | B30: 浙江五合进出口有限公司 | C30: CHDN-20260401-201 | D30: 787696 | E30: TT | F30: 201 货款
A31: 46141 | B31: 浙江五合进出口有限公司 | C31: CHDN-20260601-273 | D31: 85904 | E31: TT | F31: 273 货款
A32: 46148 | B32: INABATA SINGAPORE (PTE.) LTD. | C32: CHDW-20260318-010 | D32: 179250 | E32: TT | F32: 010 全款
A33: 46148 | B33: INABATA SINGAPORE (PTE.) LTD. | C33: CHDW-20260402-015 | D33: 147614.4 | E33: TT | F33: 015 50%尾款
A34: 46150 | B34: 浙江五合进出口有限公司 | C34: CHDN-20260325-180 | D34: 3595600 | E34: TT | F34: 180 货款
A35: 46151 | B35: 浙江五合进出口有限公司 | C35: CHDN-20260325-180 | D35: 3000000 | E35: TT | F35: 180 货款
A36: 46153 | B36: 浙江五合进出口有限公司 | C36: CHDN-20260511-234 | D36: 562400 | E36: TT | F36: 234 全款
A37: 46155 | B37: 宁波澜塑新材料有限公司 | C37: CHDN-20260513-237 | D37: 99900 | E37: TT | F37: 237 全款
A38: 46161 | B38: 金华穗广 | C38: CHDN-20260517-243 | D38: 1585000 | E38: TT | F38: 243 全款
A39: 46162 | B39: LSMCHEM GLOBAL PTE. LTD. | C39: CHDW-20260519-024 | D39: 13521.52 | E39: TT | F39: 024 预付
A40: 46162 | B40: Garant-PP LTD | C40: CHDW-20260305-005 | D40: 169922.68 | E40: TT | F40: 005 货款 | G40: 147352.08
A41: 46162 | B41: DONGJU M&TCORPORATION | C41: CHDW-20260519-023 | D41: 94060 | E41: TT | F41: 023 货款
A42: 46167 | B42: CHINA UNICHEM HOLDINGS PTE LTD | C42: CHDW-20260316-009 | D42: 83253 | E42: TT | F42: 009 70%尾款
A43: 46167 | B43: INABATA SINGAPORE (PTE.) LTD. | C43: CHDW-20260414-019 | D43: 54843.75 | E43: TT | F43: 019 50%尾款
A44: 46168 | B44: LSMCHEM GLOBAL PTE. LTD. | C44: CHDW-20260519-024 | D44: 39334 | E44: TT | F44: 024 货款
A45: 46174 | B45: 浙江五合进出口有限公司 | C45: CHDN-20260601-273 | D45: 288624 | E45: TT | F45: 273 货款
A46: 46174 | B46: Garant-PP LTD | D46: 20125.2 | E46: TT
A47: 46174 | B47: 金华穗广 | C47: CHDN-20260601-274 | D47: 1482000 | E47: TT | F47: 274 全款
A48: 46175 | B48: SOPREMA LTDA | C48: CHDW-20260407-016 | D48: 34380.5 | E48: TT | F48: 016 70%尾款
A49: 46176 | B49: W CHEM KOREA | C49: CHDW-20260528-025 | D49: 33671.6 | E49: TT | F49: 025 全款
A50: 46178 | B50: Inabata | C50: CHDW-20260509-022 | D50: 180172.8 | E50: TT | F50: 022 货款
A51: 46178 | B51: 浙江五合进出口有限公司 | C51: CHDN-20260325-180 | D51: 3000000 | E51: TT | F51: 180 货款
A52: 46181 | B52: De Monchy International B.V | C52: CHDW-20260605-028 | D52: 2464 | E52: TT | F52: 028 全款
A53: 46182 | B53: LSMCHEM GLOBAL PTE. LTD. | C53: CHDW-20260519-024 | D53: 34337.64 | E53: TT | F53: 024 预付
A54: 46182 | B54: PALMETTO ADHESIVES COMPANY | C54: CHDW-20260604-027 | D54: 12730.12 | E54: TT | F54: 027 30%预付
A55: 46183 | B55: RIYING INTERNATIONAL TRADING COMPANY LIMITED | C55: CHDW-20260113-003 | D55: 23960.99 | E55: TT | F55: 003部分
A56: 46183 | B56: RIYING INTERNATIONAL TRADING COMPANY LIMITED | C56: CHDW-20260116-004 | D56: 50936.99 | E56: TT | F56: 004+003
A57: 46184 | B57: 苏州名创新材料有限公司 | C57: CHDN-20260610-293 | D57: 81663 | E57: TT | F57: 293 全款
A58: 46184 | B58: RIYING INTERNATIONAL TRADING COMPANY LIMITED | C58: CHDW-20260116-004 | D58: 44990.21 | E58: TT | F58: 004+006
... A72: 46211 | B72: Garant-PP LTD | C72: CHDW-20260702-032 | D72: 23053.12 | E72: TT | F72: 032 全款
A73: 46211 | D73: 1750 | E73: TT | F73: 100公斤301的样品费+快递费
A74: 46213 | B74: 浙江五合进出口有限公司 | C74: CHDN-20260325-180 | D74: 3281970.6 | E74: TT | F74: 180 货款
A75: 46216 | B75: 浙江五合进出口有限公司 | C75: CHDN-20260708-371 | D75: 300000 | E75: TT | F75: 371 货款
A76: 46216 | B76: 浙江五合进出口有限公司 | C76: CHDN-20260708-371 | D76: 771840 | E76: TT | F76: 371 货款
A77: 46217 | B77: 浙江五合进出口有限公司 | C77: CHDN-20260325-180 | D77: 40000 | E77: TT | F77: 180 货款
A78: 46217 | B78: 青岛玖盈化工有限公司 | C78: CHDN-20260709-382 | D78: 900 | E78: TT | F78: 382 全款
A79: 46218 | B79: 浙江五合进出口有限公司 | C79: CHDN-20260714-403 | D79: 234432 | E79: TT | F79: 403 货款
A80: 46218 | B80: 金华穗广 | C80: CHDN-20260713-398 | D80: 1797728 | E80: TT | F80: 398 货款
A81: 46219 | B81: LSMCHEM GLOBAL PTE. LTD. | C81: CHDW-20260519-024 | D81: 198832.24 | E81: TT | F81: 024 货款
A82: 46219 | B82: 金华穗广 | C82: CHDN-20260713-398 | D82: 100000 | E82: TT | F82: 398 货款
A83: 46219 | B83: LSMCHEM GLOBAL PTE. LTD. | C83: CHDW-20260608-031 | D83: 33382 | E83: TT | F83: 031 预付
A84: 46219 | B84: CHINA UNICHEM HOLDINGS PTE LTD | C84: CHDW-20260708-034 | D84: 8420.6 | E84: TT | F84: 30% 预付
A85: 46220 | B85: INABATA SINGAPORE (PTE.) LTD. | C85: CHDW-20260608-029 | D85: 33510.4 | E85: TT | F85: 029 全款
... A127: 46275 | B127: 上海穗广贸易有限公司 | C127: CHDN-20260904-612 | D127: 1500000 | E127: 承兑 | F127: 612 货款
A128: 46276 | B128: Garant-PP LTD | C128: CHDW-20260702-032 | D128: 54709.76 | E128: TT | F128: 70% 尾款 | G128: 欧元47443.2
A129: 46280 | B129: 苏州名创新材料有限公司 | C129: CHDN-20260914-641 | D129: 103800 | E129: TT | F129: 641 全款
A130: 46281 | B130: INABATA SINGAPORE (PTE.) LTD. | C130: CHDW-20260729-037 | D130: 66937.5 | E130: TT | F130: 037 部分尾款
A131: 46281 | B131: LSMCHEM GLOBAL PTE. LTD. | C131: CHDW-20260914-049 | D131: 218854 | E131: TT | F131: 049 预付
A132: 46285 | B132: CHINA UNICHEM HOLDINGS PTE LTD | C132: CHDW-20260708-034 | D132: 19681.4 | E132: TT | F132: 70% 尾款( 25 美金手续费)
A133: 46285 | B133: LSMCHEM GLOBAL PTE. LTD. | C133: CHDW-20260902-045 | D133: 6824.56 | E133: TT | F133: 20%预付
A134: 46286 | B134: 苏州名创新材料有限公司 | C134: CHDN-20260921-664 | D134: 103800 | E134: TT | F134: 664 全款
A135: 46287 | B135: 浙江五合进出口有限公司 | C135: CHDN-20260904-613 | D135: 2188800 | E135: TT | F135: 613 全款
A136: 46288 | B136: 昆山九子莲汽车隔音材料有限公司 | C136: CHDN-20260922-666 | D136: 70875 | E136: TT | F136: 666 全款
A137: 46293 | B137: 上海穗广贸易有限公司 | C137: CHDN-20260928-674 | D137: 269760 | E137: TT | F137: 674 全款
A138: 46293 | B138: 金华烯谷新材料有限公司 | C138: CHDN-20260928-675 | D138: 315562.5 | E138: TT | F138: 675 全款
A139: 46293 | B139: 苏州名创新材料有限公司 | C139: CHDN-20260928-671 | D139: 103800 | E139: TT | F139: 671 全款
A140: 46293 | B140: 金华烯谷新材料有限公司 | C140: CHDN-20260910-633 | D140: 175200 | E140: TT | F140: 633 全款
... A148: 46310 | B148: CHINA UNICHEM HOLDINGS PTE LTD | C148: CHDW-20260714-035 | D148: 46175 | E148: TT | F148: 035 70%尾款
A149: 46310 | B149: LSMCHEM GLOBAL PTE. LTD. | C149: CHDW-20260914-049 | D149: =875494-2380 -> 873114 | E149: TT | F149: 049 尾款
A150: 46310 | B150: LSMCHEM GLOBAL PTE. LTD. | C150: CHDW-20260902-045 | D150: 2380 | E150: TT | F150: 045 货款
A151: 46310 | B151: CHINA UNICHEM HOLDINGS PTE LTD | C151: CHDW-20261014-051 | D151: 11064.44 | E151: TT | F151: 051 预付
A152: 46314 | B152: 苏州名创新材料有限公司 | C152: CHDN-20261019-746 | D152: 105600 | E152: TT | F152: 746 全款
A153: 46315 | B153: 金华烯谷新材料有限公司 | C153: CHDN-20261019-747 | D153: 181200 | E153: TT | F153: 747 全款
A154: 46315 | B154: 金华烯谷新材料有限公司 | C154: CHDN-20261010-708 | D154: =481200-D153 -> 300000 | E154: TT | F154: 708 货款
A155: 46316 | B155: 苏州名创新材料有限公司 | C155: CHDN-20261021-769 | D155: 184800 | E155: TT | F155: 769 全款
B176: a

Sheet 高科出库
A1: 发货日期 | B1: 客户 | C1: 产品型号 | D1: 合同号 | E1: 数量 | F1: 包装 | G1: 柜型 | H1: 提单号 | I1: 箱封号 | J1: 司机信息 | K1: 货代
A2: 46033 | B2: EMAAR SQUARE GENERAL TRADING & CONT.CO | C2: CH332 | D2: CHDW-20260105-001 | E2: 19.2 | F2: 20kg带托盘 | J2: 浙B3Y505
A3: 46037 | B3: LSMCHEM | C3: CH301 | D3: CHDW-20260108-002 | E3: 28.8 | F3: 600公斤吨袋,其中24包带托盘扎带 | J3: 苏CkB975 刘彬13291931176 320321197002273219
A4: 46038 | B4: LSMCHEM | C4: CH301 | D4: CHDW-20260108-002 | E4: 28.8 | F4: 600公斤吨袋,其中24包带托盘扎带 | J4: 梁俊超： 18868606918 车牌：豫PU1998 身份证 412728198502094916
A5: 46038 | B5: LSMCHEM | C5: CH301 | D5: CHDW-20260108-002 | E5: 28.8 | F5: 600公斤吨袋,其中24包带托盘扎带 | J5: 梁俊超： 18868606918 车牌：豫PU1998 身份证 412728198502094916
A6: 46039 | B6: LSMCHEM | C6: CH301 | D6: CHDW-20260108-002 | E6: 27 | F6: 600公斤吨袋,其中24包带托盘扎带 | J6: 梁俊超： 18868606918 车牌：豫PU1998 身份证 412728198502094916
A7: 46043 | B7: LSMCHEM | C7: CH301 | D7: CHDW-20260108-002 | E7: 30.6 | F7: 600公斤吨袋,其中24包带托盘扎带 | J7: 梁俊超： 18868606918 车牌：豫PU1998 身份证 412728198502094916
A8: 46044 | B8: LSMCHEM | C8: CH301 | D8: CHDW-20260108-002 | E8: 28.8 | F8: 600公斤吨袋,其中24包带托盘扎带 | J8: 梁俊超： 18868606918 车牌：豫PU1998 身份证 412728198502094916
A9: 46045 | B9: LSMCHEM | C9: CH301 | D9: CHDW-20260108-002 | E9: 28.8 | F9: 600公斤吨袋,其中24包带托盘扎带 | J9: 冀E4943W 黄德占 15227707078 132233197501241736
A10: 46046 | B10: LSMCHEM | C10: CH301 | D10: CHDW-20260108-002 | E10: 28.8 | F10: 600公斤吨袋,其中24包带托盘扎带 | J10: 姓名，孙杰 ， 车号 ，皖SB6150， 电话，18067531780 身份证号341223198008071358
A11: 46047 | B11: LSMCHEM | C11: CH301 | D11: CHDW-20260108-002 | E11: 28.8 | F11: 600公斤吨袋,其中24包带托盘扎带 | J11: 姓名，孙杰 ， 车号 ，皖SB6150， 电话，18067531780 身份证号341223198008071358
A12: 46048 | B12: LSMCHEM | C12: CH301 | D12: CHDW-20260108-002 | E12: 28.8 | F12: 600公斤吨袋,其中24包带托盘扎带 | J12: 车号：鲁Q782EX 姓名 孙振华 电话：18315796333 身份证：371322198107084933
A13: 46049 | B13: LSMCHEM | C13: CH301 | D13: CHDW-20260108-002 | E13: 28.8 | F13: 600公斤吨袋,其中24包带托盘扎带 | J13: 车号：鲁Q782EX 姓名 孙振华 电话：18315796333 身份证：371322198107084933
... A21: 46093 | B21: RIYING INTERNATIONAL TRADING COMPANY LIMITED | C21: CH301 | D21: CHDW-20260305-006 | E21: 17.92 | F21: 吨袋带托盘包装，标签 | J21: 浙B6T119 18667867181 鲁坤坤 412728198509150319
A22: 46098 | B22: INABATA SINGAPORE (PTE.) LTD. | C22: CH520 | D22: CHDW-20260306-007-1 | E22: 16.32 | F22: 15KG小包托盘 | G22: 40HQ | J22: 浙B3L100 司机：严定文 驾驶员手机： 15606686179
A23: 46098 | B23: INABATA SINGAPORE (PTE.) LTD. | C23: CH520 | D23: CHDW-20260306-007-1 | E23: 16.32 | F23: 15KG小包托盘 | G23: 40HQ | J23: 浙B6C895 司机：陈正春 驾驶员手机：13285843576
A24: 46099 | B24: INABATA SINGAPORE (PTE.) LTD. | C24: CH520 | D24: CHDW-20260306-007-1 | E24: 16.32 | F24: 15KG小包托盘 | G24: 40HQ | J24: 浙B6C895 司机：陈正春 驾驶员手机：13285843576
A25: 46100 | B25: CHINA UNICHEM HOLDINGS PTE LTD | C25: CH520 | D25: CHDW-20260316-009 | E25: 18.75 | F25: 15kg散装 | J25: 浙B6T119 18667867181 鲁坤坤 412728198509150319
A26: 46100 | B26: CHINA UNICHEM HOLDINGS PTE LTD | C26: CH520 | D26: CHDW-20260316-009 | E26: 18.75 | F26: 15kg散装 | J26: 车牌号：浙B3Q660 电话：15658225828 名字：邵海燕 身份证号码：412702198109106112
A27: 46101 | B27: Garant-PP LTD | C27: CH301 | D27: CHDW-20260305-005 | E27: 17.92 | F27: 600kg吨袋 托盘包装 | J27: 浙B6T119 18667867181 鲁坤坤 412728198509150319
A28: 46101 | B28: 浙江五合进出口有限公司 | C28: CH332 | D28: CHDN-20260319-133 | E28: 10 | F28: 20kg 散货包装 | J28: 车号：沪GE8678 司机:陈昌国 电话:13912555475 身份证：32092419760517027
A29: 46101 | B29: 上海穗广贸易有限公司 | C29: CH520 | D29: CHDN-20260313-111 | E29: 18 | F29: 15kg/包散装，1*40HQ. | J29: 车号： 浙B2G755 挂板： 浙B850U挂 司机： 贾新民 驾驶员手机： 18658223296
A30: 46102 | B30: INABATA SINGAPORE (PTE.) LTD. | C30: CH520 | D30: CHDW-20260306-007-2 | E30: 16.32 | F30: 小包带托盘 | J30: 浙B6C895 司机：陈正春 驾驶员手机：13285843576
A31: 46102 | B31: INABATA SINGAPORE (PTE.) LTD. | C31: CH520 | D31: CHDW-20260306-007-2 | E31: 16.32 | F31: 小包带托盘 | J31: 浙B2L600 司机：徐明 驾驶员手机：13685703550
A32: 46102 | B32: INABATA SINGAPORE (PTE.) LTD. | C32: CH520 | D32: CHDW-20260306-007-2 | E32: 16.32 | F32: 小包带托盘 | J32: 浙B6C895 司机：陈正春 驾驶员手机：13285843576
A33: 46102 | B33: Garant-PP LTD | C33: CH301 | D33: CHDW-20260305-005 | E33: 17.92 | F33: 600kg吨袋 托盘包装 | J33: 浙B5W781 潘宁宁 341221198409041536 18712565866
A34: 46102 | B34: Garant-PP LTD | C34: CH301 | D34: CHDW-20260305-005 | E34: 17.92 | F34: 600kg吨袋 托盘包装 | J34: 浙B6T119 18667867181 鲁坤坤 412728198509150319
A35: 46103 | B35: INABATA SINGAPORE (PTE.) LTD. | C35: CH520 | D35: CHDW-20260306-007-2 | E35: 16.32 | F35: 小包带托盘 | J35: 浙B6C895 司机：陈正春 驾驶员手机：13285843576
A36: 46103 | B36: INABATA SINGAPORE (PTE.) LTD. | C36: CH520 | D36: CHDW-20260306-007-2 | E36: 16.32 | F36: 小包带托盘 | J36: 浙B5Y686 司机：刘传付 驾驶员手机：17606836522
... A52: 46115 | B52: PALMETTO ADHESIVES COMPANY | C52: CH520 | D52: CHDW-20260330-014 | E52: 1.68 | F52: 15KG小包托盘 | J52: 司机：羊平 车牌：浙G28PA0 电话：18248539676 身份证：510722197506132878
A53: 46120 | B53: WWRC Korea Co.,Ltd | C53: CH301 | D53: CHDW-20260326-013 | E53: 17.92 | J53: 车号1：浙B6M365 车挂：浙BOX09挂 司机： 付彬 手机：15726830365 身份证 341226199210052330
A54: 46120 | B54: WWRC Korea Co.,Ltd | C54: CH301 | D54: CHDW-20260326-013 | E54: 17.92 | J54: 车号2:浙B5P332 电话 18856907101 名字 蔡自明 身份证 340121198210155513
A55: 46121 | B55: INABATA SINGAPORE (PTE.) LTD. | C55: CH520 | D55: CHDW-20260318-010 | E55: 18.75 | F55: 15KG小包托盘 | J55: 车号：浙B6M365 车挂：浙BOX09挂 司机：付彬 驾驶员手机：15726830365 身份证: 341226199210052330
A56: 46121 | B56: INABATA SINGAPORE (PTE.) LTD. | C56: CH520 | D56: CHDW-20260318-010 | E56: 18.75 | F56: 15KG小包托盘 | J56: 车号：浙B6M333/浙B0Z67挂/ 司机：陈保超 驾驶员手机：18606877698 身份证：342128197304151793
A57: 46127 | B57: LSMCHEM GLOBAL PTE. LTD. | C57: CH301 | D57: CHDW-20260108-002 | E57: 17.92 | F57: 560公斤一包 | J57: 浙B3D319 15656199969 吴志强 340621198412181219
A58: 46128 | B58: LSMCHEM GLOBAL PTE. LTD. | C58: CH301 | D58: CHDW-20260108-002 | E58: 17.92 | F58: 560公斤一包 | J58: 车号： 浙B31260D 司机： 郭堂发 驾驶员手机： 18755056551 司机身份证号： 342324197109181415
A59: 46128 | B59: 宁波方觉科技有限公司 | C59: CH520 | D59: CHDN-20260408-214 | E59: 18.75 | F59: 15kg/包散装 | J59: 司机：侯可喜 电话：17606557345 车号：浙 B7J662 身份证码：370827199508253219
A60: 46128 | B60: 宁波方觉科技有限公司 | C60: CH520 | D60: CHDN-20260408-214 | E60: 18.75 | F60: 15kg/包散装 | J60: 司机：侯可喜 电话：17606557345 车号：浙 B7J662 身份证码：370827199508253219
A61: 46128 | B61: 宁波方觉科技有限公司 | C61: CH520 | D61: CHDN-20260408-214 | E61: 18.75 | F61: 15kg/包散装 | J61: 司机：侯可喜 电话：17606557345 车号：浙 B7J662 身份证码：370827199508253219
A62: 46128 | B62: 宁波方觉科技有限公司 | C62: CH520 | D62: CHDN-20260408-214 | E62: 18.75 | F62: 15kg/包散装 | J62: 司机：江传宝 电话：15558257272 车号：浙 B3K535 身份证码：370828197910231613
A63: 46128 | B63: 宁波方觉科技有限公司 | C63: CH520 | D63: CHDN-20260408-214 | E63: 18.75 | F63: 15kg/包散装 | J63: 司机：李坤 电话：15657813826 车号：浙 B6G929 身份证码：37082719700329303
A64: 46129 | B64: INABATA SINGAPORE (PTE) LTD | C64: CH520 | D64: CHDW-20260402-015 | E64: 16.32 | F64: 小包带托盘 | J64: 浙B2X885 浙B991P挂 司机：胡厚军 驾驶员手机：13956287630 身份证：341004197603280037 | K64: 宁波鹏信国际货运代理有限公司
A65: 46129 | B65: INABATA SINGAPORE (PTE) LTD | C65: CH520 | D65: CHDW-20260402-015 | E65: 16.32 | F65: 小包带托盘 | J65: 浙B2L600 司机：徐明 驾驶员手机： 13685703550 身份证：411526199002021630 | K65: 宁波鹏信国际货运代理有限公司
A66: 46130 | B66: INABATA SINGAPORE (PTE.) LTD. | C66: CH520 | D66: CHDW-20260318-010 | E66: 18.75 | F66: 15KG小包散装 | J66: 浙B2H029 浙B168R挂 司机：黄发水 驾驶员手机：13955004691 身份证：341124197812246039
A67: 46130 | B67: INABATA SINGAPORE (PTE.) LTD. | C67: CH520 | D67: CHDW-20260318-010 | E67: 18.75 | F67: 15KG小包散装 | J67: 浙 B6C895 浙 B911W挂 司机：陈正春 驾驶员手机：13285843576 身份证号：341226197902182313
A68: 46130 | B68: INABATA SINGAPORE (PTE) LTD | C68: CH520 | D68: CHDW-20260402-015 | E68: 16.32 | F68: 15KG小包托盘 | J68: 浙B6M333 浙B0Z67挂 司机：陈保超 驾驶员手机：18606877698 身份证：342128197304151793
A69: 46130 | B69: INABATA SINGAPORE (PTE) LTD | C69: CH520 | D69: CHDW-20260402-015 | E69: 16.32 | F69: 15KG小包托盘 | J69: 浙B6V880 浙B1620挂 司机：李奎伍 驾驶员手机：13221935198 身份证号：341126197301116032
A70: 46131 | B70: INABATA SINGAPORE (PTE) LTD | C70: CH520 | D70: CHDW-20260402-015 | E70: 16.32 | F70: 15KG小包托盘 | J70: 浙B81F88浙B88VU挂 司机： 付兴海 驾驶员手机：15968926588 身份证号：341226197712252333
A71: 46131 | B71: INABATA SINGAPORE (PTE) LTD | C71: CH520 | D71: CHDW-20260402-015 | E71: 16.32 | F71: 15KG小包托盘 | J71: 浙B6M365 浙BOX09挂 司机： 付彬 驾驶员手机：15726830365 身份证号：341226199210052330
A72: 46134 | B72: LSMCHEM | C72: CH301 | D72: CHDW-20260108-002 | E72: 17.92 | F72: 560公斤一包 | J72: 车号： 浙B7V936 司机： 胡志立 身份证：420684199211061057 驾驶员手机： 18871079034
A73: 46134 | B73: LSMCHEM | C73: CH301 | D73: CHDW-20260108-002 | E73: 17.92 | F73: 560公斤一包 | J73: 车号： 浙B7V055 司机： 宋兵 驾驶员手机： 18772119281 身份证：420684198602224533
A74: 46134 | B74: LSMCHEM | C74: CH301 | D74: CHDW-20260108-002 | E74: 17.92 | F74: 560公斤一包 | J74: 车号： 浙B7V936 司机： 胡志立 身份证：420684199211061057 驾驶员手机： 18871079034
A75: 46135 | B75: LSMCHEM | C75: CH301 | D75: CHDW-20260108-002 | E75: 1.12 | F75: 560公斤一包 | J75: 陕ACE151 驾驶员：桑晓号15674812694。 身份证号320722199406205113
A76: 46135 | B76: Rare International Corp. | C76: CH406 | D76: CHDW-20260414-020 | E76: 9.6 | F76: 20kg/包 托盘包装 | J76: 车号: 浙B3U367 司机: 祝国峰 驾驶员手机: 18856881859 托架号: 浙B26X0挂 身份证：341226198112106978
A77: 46139 | B77: 宁波方觉科技有限公司 | C77: CH520 | D77: CHDN-20260408-214 | E77: 18.75 | F77: 15kg/包散装 | J77: 司机信息：张飞 176 8198 0222 车牌号：浙B87D68 浙B81H1挂 身份证号码：341124198609016232
... A123: 46155 | B123: 宁波澜塑新材料有限公司 | C123: CH301 | D123: CHDN-20260513-237 | E123: 4 | F123: 小包散货包装 | J123: 姓名:沈小军 电话:13291581198 车号:浙B2Ⅹ627 身份证号：34112519810727721X
A124: 46155 | B124: 宁波澜塑新材料有限公司 | C124: CH608 | D124: CHDN-20260513-237 | E124: 2.5 | F124: 小包散货包装
A125: 46155 | B125: 浙江五合进出口有限公司 | C125: CH301 | D125: CHDN-20260312-106 | E125: 17.92 | F125: 560kg/包，吨袋包装。 | J125: 车号: 浙B6J960 司机: 刘登峰 驾驶员手机:19059868788 司机身份证号412723199207280815
A126: 46155 | B126: 浙江五合进出口有限公司 | C126: CH301 | D126: CHDN-20260312-106 | E126: 17.92 | F126: 560kg/包，吨袋包装。 | J126: 车号:浙B7V936司机:胡志立驾驶员手机:18871079034司机身份证号:420684199211061057
A127: 46155 | B127: 浙江五合进出口有限公司 | C127: CH301 | D127: CHDN-20260312-106 | E127: 17.92 | F127: 560kg/包，吨袋包装。 | J127: 车号：浙B33162D 司机：曹明明 驾驶员手机：18658207016 司机身份证号：342501198604076015
A128: 46157 | B128: INABATA SINGAPORE (PTE) LTD | C128: CH520 | D128: CHDW-20260509-022 | E128: 16.32 | F128: 小包带托盘 | J128: 车号： 浙B5Q132 司机： 谢正华 托架号： 浙B150M挂 驾驶员手机： 13296828339 身份证号码341124197801027017
A129: 46157 | B129: INABATA SINGAPORE (PTE) LTD | C129: CH520 | D129: CHDW-20260509-022 | E129: 16.32 | F129: 小包带托盘 | J129: 车号： 浙B6M365 司机： 付彬 托架号： 浙BOX09挂 驾驶员手机： 15726830365 身份证 341226199210052330
A130: 46158 | B130: SOPREMA LTDA | C130: CH301 | D130: CHDW-20260420-021 | E130: 19 | F130: 小包散装 | J130: 车号： 浙B6C895 司机： 陈正春 托架号： 浙B911W挂 驾驶员手机： 13285843576 身份证号码：341226197902182313
A131: 46158 | B131: INABATA SINGAPORE (PTE) LTD | C131: CH520 | D131: CHDW-20260509-022 | E131: 16.32 | F131: 小包带托盘 | J131: 车号： 浙B6V880 司机： 李奎伍 托架号： 浙B1620挂 驾驶员手机： 13221935198 身份证号码341126197301116032
A132: 46158 | B132: INABATA SINGAPORE (PTE) LTD | C132: CH520 | D132: CHDW-20260509-022 | E132: 16.32 | F132: 小包带托盘 | J132: 车号： 浙B81F88 司机： 付兴海 托架号： 浙B88VU挂 驾驶员手机： 15968926588 身份证 341226197712252333
A133: 46163 | B133: LSMCHEM GLOBAL PTE. LTD. | C133: CH301 | D133: CHDW-20260519-024 | E133: 17.92 | F133: 560kg吨袋 | J133: 浙B2S116 15557079966 杜海军 412728198611153452
A134: 46163 | B134: LSMCHEM GLOBAL PTE. LTD. | C134: CH301 | D134: CHDW-20260519-024 | E134: 17.92 | F134: 560kg吨袋 | J134: 浙B3Q660 15658225828 邵海燕 412702198109106112
A135: 46164 | B135: 金华穗广 | C135: CH332 | D135: CHDN-20260517-243 | E135: 17.92 | F135: 20kg带托盘 | J135: 车号: 浙B0Z279 司机: 岳兵力 驾驶员手机: 13598410546 身份证：412822197306125896
A136: 46164 | B136: 金华穗广 | C136: CH332 | D136: CHDN-20260517-243 | E136: 17.92 | F136: 20kg带托盘 | J136: 车号：浙B3M687 司机：崔海赵 驾驶员手机：18969401024
... A173: 46173 | B173: 浙江五合进出口有限公司 | C173: CH332 | D173: CHDN-20260325-180 | E173: 19.2 | F173: 600kg/包，19.2吨/柜 | J173: 车号： 浙B7V055 司机： 宋兵 驾驶员手机： 18772119281 司机身份证号： 420684198602224533
A174: 46174 | B174: 浙江五合进出口有限公司 | C174: CH332 | D174: CHDN-20260601-273 | E174: 24.4 | F174: 220kg/袋 | J174: 车号: 鲁EH8823 姓名:来延鹏 身份证：370523198610094617 手机: 13589438123 | K174: 宁波富邦物流股份有限公司
A175: 46174 | B175: 金华穗广 | C175: CH332 | D175: CHDN-20260517-243 | E175: 4.88 | F175: 小包托盘包装 | J175: 浙B6T119 18667867181 鲁坤坤 412728198509150319
A176: 46174 | B176: 金华穗广 | C176: CH332 | D176: CHDN-20260601-274 | E176: 16.52 | F176: 小包托盘包装
A177: 46174 | B177: 金华穗广 | C177: CH332 | D177: CHDN-20260601-274 | E177: 21.48 | F177: 小包托盘包装 | J177: 浙B5W781 潘宁宁 341221198409041536 18712565866
A178: 46175 | B178: 金华穗广 | C178: CH332 | D178: CHDN-20260601-274 | E178: 20.88 | F178: 小包托盘包装 | J178: 车牌号：浙B3Q660 电话：15658225828 名字：邵海燕 身份证号码：412702198109106112
A179: 46175 | B179: LSMCHEM GLOBAL PTE. LTD. | C179: CH301 | D179: CHDW-20260519-024 | E179: 17.92 | F179: 560kg吨袋 | J179: 浙B6T119 18667867181 鲁坤坤 412728198509150319
A180: 46177 | B180: LSMCHEM GLOBAL PTE. LTD. | C180: CH302 | D180: CHDW-20260519-024 | E180: 19.2 | F180: 560kg吨袋 | J180: 浙B6T119 18667867181 鲁坤坤 412728198509150319
A181: 46177 | B181: LSMCHEM GLOBAL PTE. LTD. | C181: CH302 | D181: CHDW-20260519-024 | E181: 19.2 | F181: 560kg吨袋 | J181: 浙B6T119 18667867181 鲁坤坤 412728198509150319
A182: 46178 | B182: LSMCHEM GLOBAL PTE. LTD. | C182: CH302 | D182: CHDW-20260519-024 | E182: 19.2 | F182: 560kg吨袋 | J182: 浙B6T119 18667867181 鲁坤坤 412728198509150319
A183: 46178 | B183: LSMCHEM GLOBAL PTE. LTD. | C183: CH302 | D183: CHDW-20260519-024 | E183: 19.2 | F183: 560kg吨袋 | J183: 浙B3U039 13461360321 程文坡 412728199105173439
A184: 46179 | B184: 金华穗广 | C184: CH332 | D184: CHDN-20260601-274 | E184: 20.56 | J184: 浙B2R529 18601668582 时敬 412702197201206058
A185: 46179 | B185: 金华穗广 | C185: CH332 | D185: CHDN-20260601-274 | E185: 20.56 | J185: 浙B2R529 18601668582 时敬 412702197201206058
A186: 46180 | B186: LSMCHEM GLOBAL PTE. LTD. | C186: CH301 | D186: CHDW-20260519-024 | E186: 19.2 | F186: 560kg吨袋 | J186: 浙B5W781 潘宁宁 341221198409041536 18712565866
A187: 46180 | B187: LSMCHEM GLOBAL PTE. LTD. | C187: CH301 | D187: CHDW-20260519-024 | E187: 19.2 | F187: 560kg吨袋 | J187: 浙B5W781 潘宁宁 341221198409041536 18712565866
A188: 46154 | B188: 浙江五合进出口有限公司 | C188: CH301 | D188: CHDN-20260511-234 | E188: 19 | J188: 司机：潘正伟 车牌号：浙B0E956 驾驶员手机：13136326389 370882198801156119
A189: 46154 | B189: 浙江五合进出口有限公司 | C189: CH301 | D189: CHDN-20260511-234 | E189: 19 | J189: 司机：姜开亮 车牌号：浙B3T918 驾驶员手机：13355163788 37082719820116281X
A190: 46155 | B190: 宁波澜塑新材料有限公司 | C190: CH301 | D190: CHDN-20260513-237 | E190: 4 | J190: 姓名:沈小军 电话:13291581198 车号:浙B2Ⅹ627 身份证号：34112519810727721X
A191: 46155 | B191: 宁波澜塑新材料有限公司 | C191: CH608 | D191: CHDN-20260513-237 | E191: 2.5
A192: 46157 | B192: INABATA SINGAPORE (PTE) LTD | C192: CH520 | D192: CHDW-20260509-022 | E192: 16.32 | J192: 车号： 浙B5Q132 司机： 谢正华 托架号： 浙B150M挂 驾驶员手机： 13296828339 身份证号码341124197801027017
A193: 46157 | B193: INABATA SINGAPORE (PTE) LTD | C193: CH520 | D193: CHDW-20260509-022 | E193: 16.32 | J193: 车号： 浙B6M365 司机： 付彬 托架号： 浙BOX09挂 驾驶员手机： 15726830365 身份证 341226199210052330
A194: 46158 | B194: SOPREMA LTDA | C194: CH301 | D194: CHDW-20260420-021 | E194: 19 | J194: 车号： 浙B6C895 司机： 陈正春 托架号： 浙B911W挂 驾驶员手机： 13285843576 身份证号码：341226197902182313
A195: 46158 | B195: INABATA SINGAPORE (PTE) LTD | C195: CH520 | D195: CHDW-20260509-022 | E195: 16.32 | J195: 车号： 浙B6V880 司机： 李奎伍 托架号： 浙B1620挂 驾驶员手机： 13221935198 身份证号码341126197301116032
A196: 46158 | B196: INABATA SINGAPORE (PTE) LTD | C196: CH520 | D196: CHDW-20260509-022 | E196: 16.32 | J196: 车号： 浙B81F88 司机： 付兴海 托架号： 浙B88VU挂 驾驶员手机： 15968926588 身份证 341226197712252333
A197: 46163 | B197: LSMCHEM GLOBAL PTE. LTD. | C197: CH301 | D197: CHDW-20260519-024 | E197: 17.92 | J197: 浙B2S116 15557079966 杜海军 412728198611153452
A198: 46163 | B198: LSMCHEM GLOBAL PTE. LTD. | C198: CH301 | D198: CHDW-20260519-024 | E198: 17.92 | J198: 浙B3Q660 15658225828 邵海燕 412702198109106112
A199: 46166 | B199: DONGJU M&TCORPORATION | C199: CH406 | D199: CHDW-20260519-023 | E199: 22.4 | J199: 车号： 浙B6M653 司机： 王德保 驾驶员手机： 18658202272 身份证：341126198403235715
A200: 46166 | B200: DONGJU M&TCORPORATION | C200: CH406 | D200: CHDW-20260519-023 | E200: 22.4 | J200: 车号： 浙B3M687 司机： 崔海赵 驾驶员手机： 18969401024 身份证：341126198510036711
A201: 46169 | B201: LSMCHEM GLOBAL PTE. LTD. | C201: CH302 | D201: CHDW-20260519-024 | E201: 19.2 | J201: 浙B6T119 18667867181 鲁坤坤 412728198509150319
A202: 46171 | B202: LSMCHEM GLOBAL PTE. LTD. | C202: CH301 | D202: CHDW-20260519-024 | E202: 19.2 | J202: 浙B3U039 13461360321 程文坡 412728199105173439
A203: 46174 | B203: 浙江五合进出口有限公司 | C203: CH332 | D203: CHDN-20260601-273 | E203: 24.4 | J203: 车号: 鲁EH8823 姓名:来延鹏 身份证：370523198610094617 手机: 13589438123
...

Sheet 生物
A1: 销售员 | B1: 付款方式 | C1: 单位名称 | D1: 合同号 | E1: 合同有效期 | F1: 产品规格 | G1: 合同量 | H1: 销售单价 | I1: 销售金额 | J1: 实际出库 | K1: 未发量 | L1: 到款金额 | M1: 余款 | N1: 应收款 | O1: 佣金单价 | P1: 佣金总金额 | Q1: 审批汇率 | R1: 审批价 | S1: 指导价 | T1: 合同总金额￥ | U1: 包装 | V1: 运输条款 | W1: 目的港 | X1: 审批海运费 | Y1: 审批保费 | Z1: 审批内陆费 | AA1: 实际海运费 | AB1: 托盘数量 | AC1: 缠绕膜 | AD1: 扎带 | AE1: 卡扣 | AF1: 吨袋 | AG1: 绑带
A2: 张晓敏 | B2: 100TT | C2: FIREMAX(CAMBODIA)TIRES CO.. LTD | D2: ZJCHDW-20260121-002 | E2: 46081 | F2: N326 | G2: 478 | H2: 975 | I2: =G2*H2 -> 466050 | J2: 0 | K2: =G2-J2 -> 478 | L2: 0 | M2: =I2-L2 -> 466050 | N2: =J2*H2-L2 -> 0 | O2: 0 | P2: =O2*G2 -> 0 | Q2: 7.066 | R2: 5131 | S2: 7701 | T2: =R2*G2 -> 2452618 | U2: 1000kg 吨袋，22吨1个柜子 | V2: CIF | W2: 胡志明市 | X2: 1000 | Y2: 0 | Z2: 3500
A3: 毛晓翔 | B3: LC90 | C3: Synergy Industriez | D3: ZJCHDW-20260401-016 | E3: 46144 | F3: CH811 | G3: 82.5 | H3: 1400 | I3: =G3*H3 -> 115500 | J3: 0 | K3: =G3-J3 -> 82.5 | L3: 0 | M3: =I3-L3 -> 115500 | N3: =J3*H3-L3 -> 0 | O3: 5 | P3: =O3*G3 -> 412.5 | Q3: 6.8624 | R3: 10233 | S3: 未定指导价 | T3: =R3*G3 -> 844222.5 | U3: 25kg/bag，散装 | V3: CIF | W3: HNHAVA SHEVA | X3: =1400*3 -> 4200 | Y3: =43*3 -> 129 | Z3: =5000*3 -> 15000
A4: 杨玉赏 | B4: 100TT | C4: EUROPEAN PLASTIC JOINT STOCK COMPANY | D4: ZJCHDW-20260119-001 | E4: 46072 | F4: CH810 | G4: 5 | H4: 1035 | I4: =G4*H4 -> 5175 | J4: 5 | K4: =G4-J4 -> 0 | L4: =生物收款!E2 -> 5175 | M4: =I4-L4 -> 0 | N4: =J4*H4-L4 -> 0 | O4: 0 | P4: =O4*G4 -> 0 | Q4: 6.96 | R4: 7704 | S4: 7700 | T4: =R4*G4 -> 38520 | U4: 25kg/bag，托盘包装，1吨1托 | V4: CIF | W4: Hai Phong | X4: 0 | Y4: 10 | Z4: 1800 | AB4: 5
A5: 毛晓翔 | B5: LC90 | C5: RAI INNOTECH POLYMERS PVT. LTD. | D5: ZJCHDW-20260122-003 | E5: 46075 | F5: CH812 | G5: 82.5 | H5: 1020 | I5: =G5*H5 -> 84150 | J5: 82.5 | K5: =G5-J5 -> 0 | L5: =生物收款!E11 -> 84150 | M5: =I5-L5 -> 0 | N5: =J5*H5-L5 -> 0 | O5: 5 | P5: =O5*G5 -> 412.5 | Q5: 6.9473 | R5: 7525 | S5: 未定指导价 | T5: =R5*G5 -> 620812.5 | U5: 25kg/bag，散装 | V5: CIF | W5: MUNDRA | X5: =900*3 -> 2700 | Y5: =31*3 -> 93 | Z5: =5000*3 -> 15000
A6: 毛晓翔 | B6: LC90 | C6: D.R.PLASTO TECH PRIVATE LIMITED | D6: ZJCHDW-20260211-004 | E6: 46078 | F6: CH883 | G6: 110 | H6: 1030 | I6: =G6*H6 -> 113300 | J6: 110 | K6: =G6-J6 -> 0 | L6: =生物收款!E29 -> 113300 | M6: =I6-L6 -> 0 | N6: =J6*H6-L6 -> 0 | O6: 0 | P6: =O6*G6 -> 0 | Q6: 6.91 | R6: 7642 | S6: 未定指导价 | T6: =R6*G6 -> 840620 | U6: 25kg/bag，散装 | V6: CIF | W6: MUNDRA | X6: =800*4 -> 3200 | Y6: =31*4 -> 124 | Z6: =4500*4 -> 18000
A7: 毛晓翔 | B7: LC90 | C7: Synergy Industriez | D7: ZJCHDW-20260211-005 | E7: 46078 | F7: CH811 | G7: 82.5 | H7: 1030 | I7: =G7*H7 -> 84975 | J7: 82.5 | K7: =G7-J7 -> 0 | L7: =生物收款!E32 -> 84975 | M7: =I7-L7 -> 0 | N7: =J7*H7-L7 -> 0 | O7: 0 | P7: =O7*G7 -> 0 | Q7: 6.91 | R7: 7642 | S7: 未定指导价 | T7: =R7*G7 -> 630465 | U7: 25kg/bag，散装 | V7: CIF | W7: NHAVA SHEVA | X7: =800*3 -> 2400 | Y7: =31*3 -> 93 | Z7: =4500*3 -> 13500
A8: 毛晓翔 | B8: LC90 | C8: G P FLEX (INDIA) | D8: ZJCHDW-20260211-006 | E8: 46078 | F8: CH810 | G8: 55 | H8: 1030 | I8: =G8*H8 -> 56650 | J8: 55 | K8: =G8-J8 -> 0 | L8: =生物收款!E27 -> 56650 | M8: =I8-L8 -> 0 | N8: =J8*H8-L8 -> 0 | O8: 0 | P8: =O8*G8 -> 0 | Q8: 6.91 | R8: 7642 | S8: 未定指导价 | T8: =R8*G8 -> 420310 | U8: 25kg/bag，散装 | V8: CIF | W8: NHAVA SHEVA | X8: =800*2 -> 1600 | Y8: =31*2 -> 62 | Z8: =4500*2 -> 9000
A9: 毛晓翔 | B9: LC90 | C9: RAI INNOTECH POLYMERS PVT. LTD. | D9: ZJCHDW-20260211-007 | E9: 46078 | F9: CH812 | G9: 55 | H9: 1030 | I9: =G9*H9 -> 56650 | J9: 55 | K9: =G9-J9 -> 0 | L9: =生物收款!E30 -> 56650 | M9: =I9-L9 -> 0 | N9: =J9*H9-L9 -> 0 | O9: 0 | P9: =O9*G9 -> 0 | Q9: 6.91 | R9: 7642 | S9: 未定指导价 | T9: =R9*G9 -> 420310 | U9: 25kg/bag，散装 | V9: CIF | W9: MUNDRA | X9: =800*2 -> 1600 | Y9: =31*2 -> 62 | Z9: =4500*2 -> 9000
A10: 毛晓翔 | B10: 20/80TT | C10: AMAZON CORPORATE SERVICES PVT. LTD. | D10: ZJCHDW-20260211-008 | E10: 46078 | F10: CH810 | G10: 27.5 | H10: 1025 | I10: =G10*H10 -> 28187.5 | J10: 27.5 | K10: =G10-J10 -> 0 | L10: =生物收款!E3+16832.5 -> 28037.5 | M10: =I10-L10 -> 150 | N10: =J10*H10-L10 -> 150 | O10: 0 | P10: =O10*G10 -> 0 | Q10: 6.91 | R10: 7603 | S10: 未定指导价 | T10: =R10*G10 -> 209082.5 | U10: 25kg/bag，散装 | V10: CIF | W10: MUNDRA, FINAL ICD DADRI | X10: =800 -> 800 | Y10: =31 -> 31 | Z10: =4500 -> 4500
A11: 毛晓翔 | B11: 20/80TT | C11: AMAZON CORPORATE SERVICES PVT. LTD. | D11: ZJCHDW-20260211-008 | E11: 46078 | F11: CH811 | G11: 27.5 | H11: 1025 | I11: =G11*H11 -> 28187.5 | J11: 27.5 | K11: =G11-J11 -> 0 | L11: =生物收款!E12+生物收款!E14-16832.5 -> 28187.5 | M11: =I11-L11 -> 0 | N11: =J11*H11-L11 -> 0 | O11: 0 | P11: =O11*G11 -> 0 | Q11: 6.91 | R11: 7603 | S11: 未定指导价 | T11: =R11*G11 -> 209082.5 | U11: 25kg/bag，散装 | V11: CIF | W11: MUNDRA, FINAL ICD DADRI | X11: =800 -> 800 | Y11: =31 -> 31 | Z11: =4500 -> 4500
A12: 杨玉赏 | B12: 100TT | C12: DARU COMMERCE CO., LTD. | D12: ZJCHDW-20260305-009 | E12: 46117 | F12: CH812 | G12: 20 | H12: 1165 | I12: =G12*H12 -> 23300 | J12: 20 | K12: =G12-J12 -> 0 | L12: =生物收款!E4+生物收款!E5 -> 23300 | M12: =I12-L12 -> 0 | N12: =J12*H12-L12 -> 0 | O12: 0 | P12: =O12*G12 -> 0 | Q12: 6.87 | R12: 8810 | S12: 未定指导价 | T12: =R12*G12 -> 176200 | U12: 1000KG/包，2包共用1个托盘，20吨/20尺小柜 | V12: CFR | W12: BUSAN | X12: 10 | Y12: 0 | Z12: 4000 | AB12: 10
A13: 杨玉赏 | B13: LC90 | C13: ABBEY VIETNAM JOINT STOCK COMPANY | D13: ZJCHDW-20260310-010 | E13: 46122 | F13: N326 | G13: 234 | H13: 1089 | I13: =G13*H13 -> 254826 | J13: 234 | K13: =G13-J13 -> 0 | L13: =生物收款!E13 -> 254227.71 | M13: =I13-L13 -> 598.29 | N13: =J13*H13-L13 -> 598.29 | O13: 0 | P13: =O13*G13 -> 0 | Q13: 6.875 | R13: 7204 | S13: 7050 | T13: =R13*G13 -> 1685736 | U13: 20公斤带托盘 | V13: CIF | W13: Hai Phong | X13: =250*10 -> 2500 | Y13: =30*10 -> 300 | Z13: =4000*10 -> 40000
A14: 张晓敏 | B14: 20/80TT | C14: Valutrans Investment Co., Limited | D14: ZJCHDW-20260312-011 | E14: 46152 | F14: N330 | G14: 80 | H14: 1055 | I14: =G14*H14 -> 84400 | J14: 80 | K14: =G14-J14 -> 0 | L14: =生物收款!E17 -> 84400 | M14: =I14-L14 -> 0 | N14: =J14*H14-L14 -> 0 | O14: 0 | P14: =O14*G14 -> 0 | Q14: 6.875 | R14: 7253 | S14: 7250 | T14: =R14*G14 -> 580240 | U14: 1000kg带托盘 | V14: EXW | W14: FACTORY | X14: 0 | Y14: 0 | Z14: 0 | AA14: 0
A15: 杨玉赏 | B15: 30/70TT | C15: DARU COMMERCE CO., LTD. | D15: ZJCHDW-20260313-012 | E15: 46125 | F15: CH812 | G15: 20 | H15: 1510 | I15: =G15*H15 -> 30200 | J15: 20 | K15: =G15-J15 -> 0 | L15: =生物收款!E6+生物收款!E8 -> 30200 | M15: =I15-L15 -> 0 | N15: =J15*H15-L15 -> 0 | O15: 0 | P15: =O15*G15 -> 0 | Q15: 6.87 | R15: 11488 | S15: 未定指导价 | T15: =R15*G15 -> 229760 | U15: 1000KG/包，2包共用1个托盘，20吨/20尺小柜 | V15: CIF | W15: BUSAN | X15: 10 | Y15: 10 | Z15: 4000 | AB15: 10
A16: 杨玉赏 | B16: 100TT | C16: Polyram Plastic Industries LTD | D16: ZJCHDW-20260316-013 | E16: 46128 | F16: CH875 | G16: 5 | H16: 1560 | I16: =G16*H16 -> 7800 | J16: 5 | K16: =G16-J16 -> 0 | L16: =生物收款!E7-34320 -> 7800 | M16: =I16-L16 -> 0 | N16: =J16*H16-L16 -> 0 | O16: 30 | P16: =O16*G16 -> 150 | Q16: 6.89 | R16: 10616 | S16: 未定指导价 | T16: =R16*G16 -> 53080 | U16: 1000KG吨包带托盘 | V16: CIF | W16: HAIFA | X16: 3850 | Y16: 50 | Z16: 4500
A17: 杨玉赏 | B17: 100TT | C17: Polyram Plastic Industries LTD | D17: ZJCHDW-20260316-013 | E17: 46128 | F17: CH810 | G17: 22 | H17: 1560 | I17: =G17*H17 -> 34320 | J17: 22 | K17: =G17-J17 -> 0 | L17: 34320 | M17: =I17-L17 -> 0 | N17: =J17*H17-L17 -> 0 | O17: 30 | P17: =O17*G17 -> 660 | Q17: 6.89 | R17: 10616 | S17: 未定指导价 | T17: =R17*G17 -> 233552 | U17: 1000KG吨包带托盘 | V17: CIF | W17: HAIFA | X17: 0 | Y17: 0 | Z17: 0
A18: 杨玉赏 | B18: LC60 | C18: ABBEY VIETNAM JOINT STOCK COMPANY | D18: ZJCHDW-20260323-014 | E18: 46173 | F18: N326 | G18: 327.6 | H18: 1110 | I18: =G18*H18 -> 363636 | J18: =117+117+93.6 -> 327.6 | K18: =G18-J18 -> 0 | L18: =生物收款!E19 -> 363636 | M18: =I18-L18 -> 0 | N18: =J18*H18-L18 -> 0 | O18: 0 | P18: =O18*G18 -> 0 | Q18: 6.89 | R18: 7379 | S18: 7150 | T18: =R18*G18 -> 2417360.4 | U18: 20公斤带托盘 | V18: CIF | W18: Hai Phong | X18: =300*14 -> 4200 | Y18: =30*14 -> 420 | Z18: =4000*14 -> 56000
A19: 毛晓翔 | B19: LC90 | C19: D.R.PLASTO TECH PRIVATE LIMITED | D19: ZJCHDW-20260401-015 | E19: 46144 | F19: CH883 | G19: 55 | H19: 1400 | I19: =G19*H19 -> 77000 | J19: 55 | K19: =G19-J19 -> 0 | L19: =生物收款!E28 -> 77000 | M19: =I19-L19 -> 0 | N19: =J19*H19-L19 -> 0 | O19: 5 | P19: =O19*G19 -> 275 | Q19: 6.8624 | R19: 10233 | S19: 未定指导价 | T19: =R19*G19 -> 562815 | U19: 25kg/bag，散装 | V19: CIF | W19: MUNDRA | X19: =1400*2 -> 2800 | Y19: =43*2 -> 86 | Z19: =5000*2 -> 10000
A20: 毛晓翔 | B20: LC90 | C20: G P FLEX (INDIA) | D20: ZJCHDW-20260401-017 | E20: 46144 | F20: CH810 | G20: 55 | H20: 1400 | I20: =G20*H20 -> 77000 | J20: 55 | K20: =G20-J20 -> 0 | L20: =生物收款!E26 -> 77000 | M20: =I20-L20 -> 0 | N20: =J20*H20-L20 -> 0 | O20: 5 | P20: =O20*G20 -> 275 | Q20: 6.8624 | R20: 10233 | S20: 未定指导价 | T20: =R20*G20 -> 562815 | U20: 25kg/bag，散装 | V20: CIF | W20: NHAVA SHEVA | X20: =1400*2 -> 2800 | Y20: =43*2 -> 86 | Z20: =5000*2 -> 10000
A21: 毛晓翔 | B21: LC90 | C21: RAI INNOTECH POLYMERS PVT. LTD. | D21: ZJCHDW-20260401-018 | E21: 46144 | F21: CH812 | G21: 55 | H21: 1400 | I21: =G21*H21 -> 77000 | J21: 55 | K21: =G21-J21 -> 0 | L21: =生物收款!E23 -> 77000 | M21: =I21-L21 -> 0 | N21: =J21*H21-L21 -> 0 | O21: 5 | P21: =O21*G21 -> 275 | Q21: 6.8624 | R21: 10233 | S21: 未定指导价 | T21: =R21*G21 -> 562815 | U21: 25kg/bag，散装 | V21: CIF | W21: MUNDRA | X21: =1400*2 -> 2800 | Y21: =43*2 -> 86 | Z21: =5000*2 -> 10000
A22: 毛晓翔 | B22: LC90 | C22: AMAZON CORPORATE SERVICES PVT. LTD. | D22: ZJCHDW-20260401-019 | E22: 46144 | F22: CH811 | G22: 55 | H22: 1400 | I22: =G22*H22 -> 77000 | J22: 55 | K22: =G22-J22 -> 0 | L22: =生物收款!E20+生物收款!E25 -> 77000 | M22: =I22-L22 -> 0 | N22: =J22*H22-L22 -> 0 | O22: 5 | P22: =O22*G22 -> 275 | Q22: 6.8624 | R22: 10233 | S22: 未定指导价 | T22: =R22*G22 -> 562815 | U22: 25kg/bag，散装 | V22: CIF | W22: MUNDRA, FINAL ICD DADRI | X22: =1400*2 -> 2800 | Y22: =43*2 -> 86 | Z22: =5000*2 -> 10000
A23: 毛晓翔 | B23: LC90 | C23: ARLON INNOVATION BHARAT PRIVATE LIMITED | D23: ZJCHDW-20260408-020 | E23: 46150 | F23: CH811 | G23: 55 | H23: 1480 | I23: =G23*H23 -> 81400 | J23: 55 | K23: =G23-J23 -> 0 | L23: =生物收款!E33 -> 81400 | M23: =I23-L23 -> 0 | N23: =J23*H23-L23 -> 0 | O23: 10 | P23: =O23*G23 -> 550 | Q23: 6.816 | R23: 10730 | S23: 未定指导价 | T23: =R23*G23 -> 590150 | U23: 25kg/bag，散装 | V23: CIF | W23: MUNDRA | X23: =2*1450 -> 2900 | Y23: =2*45 -> 90 | Z23: =2*5000 -> 10000
A24: 毛晓翔 | B24: LC90 | C24: BOMBAY PLASTIC UDYOG | D24: ZJCHDW-20260408-021 | E24: 46150 | F24: CH883 | G24: 27.5 | H24: 1470 | I24: =G24*H24 -> 40425 | J24: 27.5 | K24: =G24-J24 -> 0 | L24: =生物收款!E21 -> 40425 | M24: =I24-L24 -> 0 | N24: =J24*H24-L24 -> 0 | O24: 10 | P24: =O24*G24 -> 275 | Q24: 6.816 | R24: 10653 | S24: 未定指导价 | T24: =R24*G24 -> 292957.5 | U24: 25kg/bag，散装 | V24: CIF | W24: MUNDRA | X24: =1450 -> 1450 | Y24: =45 -> 45 | Z24: =5000 -> 5000
A25: 杨玉赏 | B25: 100TT | C25: Polyram Plastic Industries LTD | D25: ZJCHDW-20260428-022 | E25: 46203 | F25: CH810 | G25: 54 | H25: 1495 | I25: =G25*H25 -> 80730 | J25: 54 | K25: =G25-J25 -> 0 | L25: =生物收款!E10 -> 80730 | M25: =I25-L25 -> 0 | N25: =J25*H25-L25 -> 0 | O25: 30 | P25: =O25*G25 -> 1620 | Q25: 6.82 | R25: 10130 | T25: =R25*G25 -> 547020 | U25: 1000KG吨包带托盘 | V25: CIF | W25: HAIFA | X25: =3400*2 -> 6800 | Y25: =50*2 -> 100 | Z25: =4500*2 -> 9000
A26: 毛晓翔 | B26: LC90 | C26: RAI INNOTECH POLYMERS PVT. LTD. | D26: ZJCHDW-20260428-023 | E26: 46178 | F26: CH812 | G26: 55 | H26: 1350 | I26: =G26*H26 -> 74250 | J26: =27.5+27.5 -> 55 | K26: =G26-J26 -> 0 | L26: 74250 | M26: =I26-L26 -> 0 | N26: =J26*H26-L26 -> 0 | O26: 5 | P26: =O26*G26 -> 275 | Q26: 6.8177 | R26: 9844 | T26: =R26*G26 -> 541420 | U26: 25kg/bag，散装 | V26: CIF | W26: MUNDRA | X26: =1200*2 -> 2400 | Y26: =41*2 -> 82 | Z26: =4800*2 -> 9600
A27: 毛晓翔 | B27: LC90 | C27: G.P. FLEX (INDIA) | D27: ZJCHDW-20260428-024 | E27: 46178 | F27: CH810 | G27: 27.5 | H27: 1350 | I27: =G27*H27 -> 37125 | J27: 27.5 | K27: =G27-J27 -> 0 | L27: =37125 -> 37125 | M27: =I27-L27 -> 0 | N27: =J27*H27-L27 -> 0 | O27: 5 | P27: =O27*G27 -> 137.5 | Q27: 6.8177 | R27: 9844 | T27: =R27*G27 -> 270710 | U27: 25kg/bag，散装 | V27: CIF | W27: HNHAVA SHEVA | X27: =1200 -> 1200 | Y27: =41 -> 41 | Z27: =4800 -> 4800
A28: 毛晓翔 | B28: LC90 | C28: G.P. FLEX (INDIA) | D28: ZJCHDW-20260428-024 | E28: 46178 | F28: CH811 | G28: 27.5 | H28: 1350 | I28: =G28*H28 -> 37125 | J28: 27.5 | K28: =G28-J28 -> 0 | L28: 37125 | M28: =I28-L28 -> 0 | N28: =J28*H28-L28 -> 0 | O28: 5 | P28: =O28*G28 -> 137.5 | Q28: 6.8177 | R28: 9844 | T28: =R28*G28 -> 270710 | U28: 25kg/bag，散装 | V28: CIF | W28: HNHAVA SHEVA | X28: =1200 -> 1200 | Y28: =41 -> 41 | Z28: =4800 -> 4800
A29: 陶莹 | B29: 30/70TT | C29: KALAY DO BRASIL LTDA | D29: ZJCHDW-20260428-025 | E29: 46170 | F29: CH810 | G29: 27 | H29: 1330 | I29: =G29*H29 -> 35910 | J29: 27 | K29: =G29-J29 -> 0 | L29: =生物收款!E9+生物收款!E16 -> 35910 | M29: =I29-L29 -> 0 | N29: =J29*H29-L29 -> 0 | O29: 0 | P29: =O29*G29 -> 0 | Q29: 6.81 | R29: 10000 | S29: 9850 | T29: =R29*G29 -> 270000 | U29: 1000kg带托盘 | V29: FOB | W29: NINGBO | X29: 0 | Y29: 0 | Z29: 5500
A30: 陶莹 | B30: 100TT | C30: RIGHT GLOBAL ADVANCED CO., LIMITED | D30: ZJCHDW-20260428-026 | E30: 46170 | F30: CH883 | G30: 10 | H30: 1370 | I30: =G30*H30 -> 13700 | J30: 10 | K30: =G30-J30 -> 0 | L30: =生物收款!E15 -> 13700 | M30: =I30-L30 -> 0 | N30: =J30*H30-L30 -> 0 | O30: 0 | P30: =O30*G30 -> 0 | Q30: 6.81 | R30: 9971 | S30: 9850 | T30: =R30*G30 -> 99710 | U30: 1000kg带托盘 | V30: CIF | W30: BUSAN | X30: =0 -> 0 | Y30: 15 | Z30: 5000
A31: 毛晓翔 | B31: LC90 | C31: BOMBAY PLASTIC UDYOG | D31: ZJCHDW-20260511-027 | E31: 46184 | F31: CH810 | G31: 27.5 | H31: 1400 | I31: =G31*H31 -> 38500 | J31: 27.5 | K31: =G31-J31 -> 0 | L31: 38500 | M31: =I31-L31 -> 0 | N31: =J31*H31-L31 -> 0 | O31: 10 | P31: =O31*G31 -> 275 | Q31: 6.7826 | R31: 10092 | T31: =R31*G31 -> 277530 | U31: 25kg/bag，散装 | V31: CIF | W31: MUNDRA | X31: 1350 | Y31: 45 | Z31: 5000
A32: 毛晓翔 | B32: LC90 | C32: BOMBAY PLASTIC UDYOG | D32: ZJCHDW-20260511-027 | E32: 46184 | F32: CH811 | G32: 27.5 | H32: 1400 | I32: =G32*H32 -> 38500 | J32: 27.5 | K32: =G32-J32 -> 0 | L32: 38500 | M32: =I32-L32 -> 0 | N32: =J32*H32-L32 -> 0 | O32: 10 | P32: =O32*G32 -> 275 | Q32: 6.7826 | R32: 10092 | T32: =R32*G32 -> 277530 | U32: 25kg/bag，散装 | V32: CIF | W32: MUNDRA | X32: 1350 | Y32: 45 | Z32: 5000
A33: 毛晓翔 | B33: LC90 | C33: SKB INDUSTRIES | D33: ZJCHDW-20260513-028 | E33: 46186 | F33: CH810 | G33: 13.5 | H33: 1350 | I33: =G33*H33 -> 18225 | J33: 13.5 | K33: =G33-J33 -> 0 | L33: 18225 | M33: =I33-L33 -> 0 | N33: =J33*H33-L33 -> 0 | O33: 0 | P33: =O33*G33 -> 0 | Q33: 6.7826 | R33: 9735 | T33: =R33*G33 -> 131422.5 | U33: 25kg/bag，散装 | V33: CIF | W33: MUNDRA | X33: 1500 | Y33: 41 | Z33: 5000
A34: 毛晓翔 | B34: LC90 | C34: SKB INDUSTRIES | D34: ZJCHDW-20260513-028 | E34: 46186 | F34: CH811 | G34: 14 | H34: 1350 | I34: =G34*H34 -> 18900 | J34: 14 | K34: =G34-J34 -> 0 | L34: 18900 | M34: =I34-L34 -> 0 | N34: =J34*H34-L34 -> 0 | O34: 0 | P34: =O34*G34 -> 0 | Q34: 6.7826 | R34: 9735 | T34: =R34*G34 -> 136290 | U34: 25kg/bag，散装 | V34: CIF | W34: MUNDRA | Y34: 42 | Z34: 5001
A35: 毛晓翔 | B35: LC90 | C35: RAI INNOTECH POLYMERS PVT. LTD. | D35: ZJCHDW-20260602-029 | E35: 46205 | F35: CH812 | G35: 110 | H35: 1400 | I35: =G35*H35 -> 154000 | J35: 110 | K35: =G35-J35 -> 0 | L35: =生物收款!E39 -> 154000 | M35: =I35-L35 -> 0 | N35: =J35*H35-L35 -> 0 | O35: 10 | P35: =O35*G35 -> 1100 | Q35: 6.75 | R35: 9606 | T35: =R35*G35 -> 1056660 | U35: 25kg/bag，散装 | V35: CIF | W35: MUNDRA | X35: =2950*4 -> 11800 | Y35: =43*4 -> 172 | Z35: =4800*4 -> 19200
A36: 毛晓翔 | B36: LC90 | C36: Polynomous Industries Private Limited | D36: ZJCHDW-20260706-030 | E36: 46240 | F36: CH883 | G36: 55 | H36: 1400 | I36: =G36*H36 -> 77000 | J36: 55 | K36: =G36-J36 -> 0 | L36: 0 | M36: =I36-L36 -> 77000 | N36: =J36*H36-L36 -> 77000 | O36: 200 | P36: =O36*G36 -> 11000 | Q36: 6.75 | R36: 8601 | T36: =R36*G36 -> 473055 | U36: 25kg/bag，散装 | V36: CIF | W36: NHAVA SHEVA | X36: =1950*2 -> 3900 | Y36: =43*2 -> 86 | Z36: =4800*2 -> 9600
A37: 毛晓翔 | B37: LC90 | C37: Polynomous Industries Private Limited | D37: ZJCHDW-20260706-030 | E37: 46240 | F37: CH811 | G37: 27.5 | H37: 1400 | I37: =G37*H37 -> 38500 | J37: 27.5 | K37: =G37-J37 -> 0 | L37: 0 | M37: =I37-L37 -> 38500 | N37: =J37*H37-L37 -> 38500 | O37: 200 | P37: =O37*G37 -> 5500 | Q37: 6.75 | R37: 8601 | T37: =R37*G37 -> 236527.5 | U37: 25kg/bag，散装 | V37: CIF | W37: NHAVA SHEVA | X37: =1950 -> 1950 | Y37: =43 -> 43 | Z37: 4800
A38: 杨玉赏 | B38: 100TT | C38: DARU COMMERCE CO., LTD. | D38: ZJCHDW-20260710-031 | E38: 46244 | F38: CH883 | G38: 1 | H38: 1340 | I38: =G38*H38 -> 1340 | J38: 1 | K38: =G38-J38 -> 0 | L38: =生物收款!E18 -> 1340 | M38: =I38-L38 -> 0 | N38: =J38*H38-L38 -> 0 | O38: 0 | P38: =O38*G38 -> 0 | Q38: 6.78 | R38: 8729 | S38: 8602 | T38: =R38*G38 -> 8729 | U38: 25kg/bag，带托盘 | V38: CIF | W38: BUSAN | X38: =0 -> 0 | Y38: 10 | Z38: 1400
A39: 杨玉赏 | B39: LC60 | C39: ABBEY VIETNAM JOINT STOCK COMPANY | D39: ZJCHDW-20260710-032 | E39: 46265 | F39: N326 | G39: 93.6 | H39: 1085 | I39: =G39*H39 -> 101556 | J39: 93.6 | K39: =G39-J39 -> 0 | L39: 0 | M39: =I39-L39 -> 101556 | N39: =J39*H39-L39 -> 101556 | O39: 0 | P39: =O39*G39 -> 0 | Q39: 6.78 | R39: 6957 | S39: 6600 | T39: =R39*G39 -> 651175.2 | U39: 20公斤带托盘 | V39: CIF | W39: Hai Phong | X39: =4*600 -> 2400 | Y39: =4*40 -> 160 | Z39: =4*5000 -> 20000
A40: 毛晓翔 | B40: LC90 | C40: BOMBAY PLASTIC UDYOG | D40: ZJCHDW-20260722-033 | E40: 46256 | F40: CH883 | G40: 27.5 | H40: 1240 | I40: =G40*H40 -> 34100 | J40: 27.5 | K40: =G40-J40 -> 0 | L40: 0 | M40: =I40-L40 -> 34100 | N40: =J40*H40-L40 -> 34100 | O40: 10 | P40: =O40*G40 -> 275 | Q40: 6.7537 | R40: 8648 | T40: =R40*G40 -> 237820 | U40: 25kg/bag，散装 | V40: CIF | W40: MUNDRA | X40: 2000 | Y40: 37 | Z40: 5000
A41: 毛晓翔 | B41: 20/80TT | C41: AMAZON CORPORATE SERVICES PVT. LTD. | D41: ZJCHDW-20260722-034 | E41: 46256 | F41: CH811 | G41: 27.5 | H41: 1230 | I41: =G41*H41 -> 33825 | J41: 27.5 | K41: =G41-J41 -> 0 | L41: =生物收款!E22+20335 -> 33825 | M41: =I41-L41 -> 0 | N41: =J41*H41-L41 -> 0 | O41: 0 | P41: =O41*G41 -> 0 | Q41: 6.7537 | R41: 8639 | T41: =R41*G41 -> 237572.5 | U41: 25kg/bag，散装 | V41: CIF | W41: MUNDRA, FINAL ICD DADRI | X41: 2000 | Y41: 37 | Z41: 5000
A42: 毛晓翔 | B42: 20/80TT | C42: AMAZON CORPORATE SERVICES PVT. LTD. | D42: ZJCHDW-20260722-034 | E42: 46256 | F42: CH810 | G42: 27.5 | H42: 1230 | I42: =G42*H42 -> 33825 | J42: 27.5 | K42: =G42-J42 -> 0 | L42: =54075-20335 -> 33740 | M42: =I42-L42 -> 85 | N42: =J42*H42-L42 -> 85 | O42: 0 | P42: =O42*G42 -> 0 | Q42: 6.7537 | R42: 8639 | T42: =R42*G42 -> 237572.5 | U42: 25kg/bag，散装 | V42: CIF | W42: MUNDRA, FINAL ICD DADRI | X42: 2000 | Y42: 37 | Z42: 5000
A43: 毛晓翔 | B43: LC90 | C43: SKB INDUSTRIES | D43: ZJCHDW-20260723-035 | E43: 46257 | F43: CH810 | G43: 27.5 | H43: 1240 | I43: =G43*H43 -> 34100 | J43: 27.5 | K43: =G43-J43 -> 0 | L43: 0 | M43: =I43-L43 -> 34100 | N43: =J43*H43-L43 -> 34100 | O43: 10 | P43: =O43*G43 -> 275 | Q43: 6.7537 | R43: 8648 | T43: =R43*G43 -> 237820 | U43: 25kg/bag，散装 | V43: CIF | W43: MUNDRA | X43: =2000 -> 2000 | Y43: 37 | Z43: 5000
A44: 毛晓翔 | B44: LC90 | C44: SKB INDUSTRIES | D44: ZJCHDW-20260723-035 | E44: 46257 | F44: CH811 | G44: 27.5 | H44: 1240 | I44: =G44*H44 -> 34100 | J44: 27.5 | K44: =G44-J44 -> 0 | L44: 0 | M44: =I44-L44 -> 34100 | N44: =J44*H44-L44 -> 34100 | O44: 10 | P44: =O44*G44 -> 275 | Q44: 6.7537 | R44: 8648 | T44: =R44*G44 -> 237820 | U44: 25kg/bag，散装 | V44: CIF | W44: MUNDRA | X44: =2000 -> 2000 | Y44: 37 | Z44: 5000
A45: 毛晓翔 | B45: LC90 | C45: G.P. FLEX (INDIA) | D45: ZJCHDW-20260723-036 | E45: 46257 | F45: CH810 | G45: 55 | H45: 1240 | I45: =G45*H45 -> 68200 | J45: 55 | K45: =G45-J45 -> 0 | L45: 0 | M45: =I45-L45 -> 68200 | N45: =J45*H45-L45 -> 68200 | O45: 10 | P45: =O45*G45 -> 550 | Q45: 6.7537 | R45: 8648 | T45: =R45*G45 -> 475640 | U45: 25kg/bag，散装 | V45: CIF | W45: MUNDRA | X45: =2000 -> 2000 | Y45: 37 | Z45: 5000
A46: 毛晓翔 | B46: LC90 | C46: RAI INNOTECH POLYMERS PVT. LTD. | D46: ZJCHDW-20260723-037 | E46: 46257 | F46: CH812 | G46: 55 | H46: 1240 | I46: =G46*H46 -> 68200 | J46: 55 | K46: =G46-J46 -> 0 | L46: 0 | M46: =I46-L46 -> 68200 | N46: =J46*H46-L46 -> 68200 | O46: 10 | P46: =O46*G46 -> 550 | Q46: 6.7537 | R46: 8648 | T46: =R46*G46 -> 475640 | U46: 25kg/bag，散装 | V46: CIF | W46: MUNDRA | X46: =2000 -> 2000 | Y46: 37 | Z46: 5000
A47: 毛晓翔 | B47: LC90 | C47: Synergy Industriez | D47: ZJCHDW-20260723-038 | E47: 46295 | F47: CH811 | G47: 55 | H47: 1240 | I47: =G47*H47 -> 68200 | J47: 55 | K47: =G47-J47 -> 0 | L47: 0 | M47: =I47-L47 -> 68200 | N47: =J47*H47-L47 -> 68200 | O47: 10 | P47: =O47*G47 -> 550 | Q47: 6.7537 | R47: 8648 | T47: =R47*G47 -> 475640 | U47: 25kg/bag，散装 | V47: CIF | W47: NHAVA SHEVA | X47: =2000 -> 2000 | Y47: 37 | Z47: 5000
A48: 毛晓翔 | B48: 20/80TT | C48: AMAZON CORPORATE SERVICES PVT. LTD. | D48: ZJCHDW-20260731-039 | E48: 46265 | F48: CH811 | G48: 27.5 | H48: 1240 | I48: =G48*H48 -> 34100 | J48: 27.5 | K48: =G48-J48 -> 0 | L48: =生物收款!E24+16895 -> 29615 | M48: =I48-L48 -> 4485 | N48: =J48*H48-L48 -> 4485 | O48: 本合同申请抵扣前面闭环合同，佣金共计4400美元，生物25年外销合同尾号（050.051.053.056.057.058.059.060.062），抵扣后本合同总金额63800美金。 | Q48: 6.7397 | R48: 8637 | T48: =R48*G48 -> 237517.5 | U48: 25kg/bag，散装 | V48: CIF | W48: MUNDRA, FINAL ICD DADRI | X48: =2215*2 -> 4430 | Y48: =38*2 -> 76 | Z48: =5000*2 -> 10000
A49: 毛晓翔 | B49: 20/80TT | C49: AMAZON CORPORATE SERVICES PVT. LTD. | D49: ZJCHDW-20260731-039 | E49: 46265 | F49: CH810 | G49: 27.5 | H49: 1240 | I49: =G49*H49 -> 34100 | J49: 27.5 | K49: =G49-J49 -> 0 | L49: =生物收款!E40-16895 -> 34100 | M49: =I49-L49 -> 0 | N49: =J49*H49-L49 -> 0 | Q49: 6.7397 | R49: 8637 | T49: =R49*G49 -> 237517.5 | U49: 25kg/bag，散装 | V49: CIF | W49: MUNDRA, FINAL ICD DADRI
A50: 毛晓翔 | B50: LC90 | C50: SPECTRUM IMPEX | D50: ZJCHDW-20260806-040 | E50: 46295 | F50: CH811 | G50: 27.5 | H50: 1260 | I50: =G50*H50 -> 34650 | J50: 27.5 | K50: =G50-J50 -> 0 | L50: 0 | M50: =I50-L50 -> 34650 | N50: =J50*H50-L50 -> 34650 | O50: 10 | P50: =O50*G50 -> 275 | Q50: 6.7345 | R50: 8650 | T50: =R50*G50 -> 237875 | U50: 25kg/bag，散装 | V50: CIF | W50: NHAVA SHEVA | X50: 2450 | Y50: 38 | Z50: 5000
A51: 杨玉赏 | B51: 100TT | C51: Polyram Plastic Industries LTD | D51: ZJCHDW-20260811-041 | E51: 46276 | F51: CH810 | G51: 54 | H51: 1390 | I51: =G51*H51 -> 75060 | J51: 54 | K51: =G51-J51 -> 0 | L51: =生物收款!E31 -> 75060 | M51: =I51-L51 -> 0 | N51: =J51*H51-L51 -> 0 | O51: 30 | P51: =O51*G51 -> 1620 | Q51: 6.73 | R51: 8726 | T51: =R51*G51 -> 471204 | U51: 1000KG吨包带托盘 | V51: CIF | W51: HAIFA | X51: =2*5000 -> 10000 | Y51: =2*50 -> 100 | Z51: =2*5000 -> 10000
A52: 毛晓翔 | B52: LC90 | C52: Polynomous Industries Private Limited | D52: ZJCHDW-20260811-042 | E52: 46295 | F52: CH883 | G52: 55 | H52: 1260 | I52: =G52*H52 -> 69300 | J52: 55 | K52: =G52-J52 -> 0 | L52: 0 | M52: =I52-L52 -> 69300 | N52: =J52*H52-L52 -> 69300 | O52: 5 | P52: =O52*G52 -> 275 | Q52: 6.7345 | R52: 8661 | T52: =R52*G52 -> 476355 | U52: 25kg/bag，散装 | V52: CIF | W52: NHAVA SHEVA | X52: =3*2600 -> 7800 | Y52: =3*38 -> 114 | Z52: =3*4500 -> 13500
A53: 毛晓翔 | B53: LC90 | C53: Polynomous Industries Private Limited | D53: ZJCHDW-20260811-042 | E53: 46295 | F53: CH811 | G53: 27.5 | H53: 1260 | I53: =G53*H53 -> 34650 | J53: 27.5 | K53: =G53-J53 -> 0 | L53: 0 | M53: =I53-L53 -> 34650 | N53: =J53*H53-L53 -> 34650 | O53: 5 | P53: =O53*G53 -> 137.5 | Q53: 6.7345 | R53: 8661 | T53: =R53*G53 -> 238177.5 | U53: 25kg/bag，散装 | V53: CIF | W53: NHAVA SHEVA
A54: 杨玉赏 | B54: LC90 | C54: TISAN MUHENDISLIK PLASTIKLERI SAN VE TIC LTD STI | D54: ZJCHDW-20260822-043 | E54: 46319 | F54: CH810 | G54: 18.5 | H54: 1430 | I54: =G54*H54 -> 26455 | J54: 0 | K54: =G54-J54 -> 18.5 | L54: 0 | M54: =I54-L54 -> 26455 | N54: =J54*H54-L54 -> 0 | O54: 0 | P54: =O54*G54 -> 0 | Q54: 6.71 | R54: 9040 | T54: =R54*G54 -> 167240 | U54: 25kg/bag，带托盘 | V54: CIF | W54: IZMIT | X54: 3550 | Y54: 30 | Z54: 5000
A55: 杨玉赏 | B55: LC90 | C55: TISAN MUHENDISLIK PLASTIKLERI SAN VE TIC LTD STI | D55: ZJCHDW-20260822-043 | E55: 46319 | F55: CH890 | G55: 18.5 | H55: 1430 | I55: =G55*H55 -> 26455 | J55: 0 | K55: =G55-J55 -> 18.5 | L55: 0 | M55: =I55-L55 -> 26455 | N55: =J55*H55-L55 -> 0 | O55: 0 | P55: =O55*G55 -> 0 | Q55: 6.71 | R55: 9040 | T55: =R55*G55 -> 167240 | U55: 25kg/bag，带托盘 | V55: CIF | W55: IZMIT | X55: 3550 | Y55: 30 | Z55: 5000
A56: 杨玉赏 | B56: LC90 | C56: TISAN MUHENDISLIK PLASTIKLERI SAN VE TIC LTD STI | D56: ZJCHDW-20260822-043 | E56: 46319 | F56: CH812 | G56: 18.5 | H56: 1445 | I56: =G56*H56 -> 26732.5 | J56: 0 | K56: =G56-J56 -> 18.5 | L56: 0 | M56: =I56-L56 -> 26732.5 | N56: =J56*H56-L56 -> 0 | O56: 0 | P56: =O56*G56 -> 0 | Q56: 6.71 | R56: 9153 | T56: =R56*G56 -> 169330.5 | U56: 25kg/bag，带托盘 | V56: CIF | W56: IZMIT | X56: 3550 | Y56: 30 | Z56: 5000
A57: 毛晓翔 | B57: LC90 | C57: VECTUS POLYMERS PRIVATE LIMITED | D57: ZJCHDW-20260826-044 | E57: 46291 | F57: CH811 | G57: 27.5 | H57: 1380 | I57: =G57*H57 -> 37950 | J57: 27.5 | K57: =G57-J57 -> 0 | L57: 0 | M57: =I57-L57 -> 37950 | N57: =J57*H57-L57 -> 37950 | O57: 5 | P57: =O57*G57 -> 137.5 | Q57: 6.71 | R57: 9141 | T57: =R57*G57 -> 251377.5 | U57: 25kg/bag，散装 | V57: CIF | W57: MUNDRA | X57: 4000 | Y57: 42 | Z57: 4800
A58: 毛晓翔 | B58: LC90 | C58: RAI INNOTECH POLYMERS PVT. LTD. | D58: ZJCHDW-20260911-045 | E58: 46306 | F58: CH812 | G58: 55 | H58: 1640 | I58: =G58*H58 -> 90200 | J58: 55 | K58: =G58-J58 -> 0 | L58: 0 | M58: =I58-L58 -> 90200 | N58: =J58*H58-L58 -> 90200 | O58: 10 | P58: =O58*G58 -> 550 | Q58: 6.698 | R58: 10884 | T58: =R58*G58 -> 598620 | U58: 25kg/bag，散装 | V58: CIF | W58: MUNDRA | X58: =2*4600 -> 9200 | Y58: =2*50 -> 100 | Z58: =5000*2 -> 10000
A59: 杨玉赏 | B59: 100TT | C59: Polyram Plastic Industries LTD | D59: ZJCHDW-20260911-046 | E59: 46306 | F59: CH810 | G59: 27 | H59: 1570 | I59: =G59*H59 -> 42390 | J59: 0 | K59: =G59-J59 -> 27 | L59: =生物收款!E41 -> 42390 | M59: =I59-L59 -> 0 | N59: =J59*H59-L59 -> -42390 | O59: 30 | P59: =O59*G59 -> 810 | Q59: 6.698 | R59: 10102 | T59: =R59*G59 -> 272754 | U59: 1000KG吨包带托盘 | V59: CIF | W59: HAIFA | X59: 4800 | Y59: 50 | Z59: 5000
A60: 杨玉赏 | B60: LC120 | C60: TISAN MUHENDISLIK PLASTIKLERI SAN VE TIC LTD STI | D60: ZJCHDW-20260918-047 | E60: 46356 | F60: CH810 | G60: 18.5 | H60: 1650 | I60: =G60*H60 -> 30525 | J60: 0 | K60: =G60-J60 -> 18.5 | L60: 0 | M60: =I60-L60 -> 30525 | N60: =J60*H60-L60 -> 0 | O60: 0 | P60: =O60*G60 -> 0 | Q60: 6.69 | R60: 10720 | T60: =R60*G60 -> 198320 | U60: 25kg/bag，带托盘 | V60: CIF | W60: IZMIT | X60: 3500 | Y60: 35 | Z60: =4500 -> 4500
A61: 杨玉赏 | B61: LC120 | C61: TISAN MUHENDISLIK PLASTIKLERI SAN VE TIC LTD STI | D61: ZJCHDW-20260918-047 | E61: 46356 | F61: CH812 | G61: 55.5 | H61: 1650 | I61: =G61*H61 -> 91575 | J61: 0 | K61: =G61-J61 -> 55.5 | L61: 0 | M61: =I61-L61 -> 91575 | N61: =J61*H61-L61 -> 0 | O61: 0 | P61: =O61*G61 -> 0 | Q61: 6.69 | R61: 10720 | T61: =R61*G61 -> 594960 | U61: 25kg/bag，带托盘 | V61: CIF | W61: IZMIT | X61: =3*3500 -> 10500 | Y61: =3*35 -> 105 | Z61: =4500*3 -> 13500
A62: 杨玉赏 | B62: 100TT | C62: Polyram Plastic Industries LTD | D62: ZJCHDW-20260930-048 | E62: 46325 | F62: CH810 | G62: 27 | H62: 1640 | I62: =G62*H62 -> 44280 | J62: 0 | K62: =G62-J62 -> 27 | L62: 0 | M62: =I62-L62 -> 44280 | N62: =J62*H62-L62 -> 0 | O62: 30 | P62: =O62*G62 -> 810 | Q62: 6.695 | R62: 10925 | T62: =R62*G62 -> 294975 | U62: 1000KG吨包带托盘 | V62: CIF | W62: HAIFA | X62: 3800 | Y62: 50 | Z62: 4500
A63: 杨玉赏 | B63: 30/70TT | C63: DARU COMMERCE CO., LTD. | D63: ZJCHDW-20261012-049 | E63: 46338 | F63: CH812 | G63: 48 | H63: 1640 | I63: =G63*H63 -> 78720 | J63: 24 | K63: =G63-J63 -> 24 | L63: 51168 | M63: =I63-L63 -> 27552 | N63: =J63*H63-L63 -> -11808 | O63: 0 | P63: =O63*G63 -> 0 | Q63: 6.68 | R63: 11933 | T63: =R63*G63 -> 572784 | U63: 1000KG吨包带托盘 | V63: CIF | W63: BUSAN | X63: =600*2 -> 1200 | Y63: =45*2 -> 90 | Z63: =5000*2 -> 10000
A64: 杨玉赏 | B64: 30/70TT | C64: DARU COMMERCE CO., LTD. | D64: ZJCHDW-20261020-050 | E64: 46346 | F64: CH812 | G64: 24 | H64: 1630 | I64: =G64*H64 -> 39120 | J64: 0 | K64: =G64-J64 -> 24 | L64: 0 | M64: =I64-L64 -> 39120 | N64: =J64*H64-L64 -> 0 | O64: 0 | Q64: 6.667 | R64: 11766

Sheet 生物收款
A1: 日期 | B1: 客户 | C1: 合同号 | D1: 付款方式 | E1: 收款金额 | F1: 备注
A2: 46048 | B2: EUROPEAN PLASTIC JOINT STOCK COMPANY | C2: ZJCHDW-20260119-001 | D2: TT | E2: 5175 | F2: 001 全款
A3: 46092 | B3: AMAZON CORPORATE SERVICES PVT LTD | C3: ZJCHDW-20260211-008 | D3: TT | E3: 11205 | F3: 008 预付款
A4: 46092 | B4: DARU COMMERCE CO., LTD. | C4: ZJCHDW-20260305-009 | D4: TT | E4: 2330 | F4: 009 货款
A5: 46094 | B5: DARU COMMERCE CO., LTD. | C5: ZJCHDW-20260305-009 | D5: TT | E5: 20970 | F5: 009 尾款
A6: 46100 | B6: DARU COMMERCE CO., LTD. | C6: ZJCHDW-20260313-012 | D6: TT | E6: 9060 | F6: 012 30%定金
A7: 46100 | B7: Polyram Plastic Industries LTD | C7: ZJCHDW-20260316-013 | D7: TT | E7: 42120 | F7: 013 全款
A8: 46106 | B8: DARU COMMERCE CO., LTD. | C8: ZJCHDW-20260313-012 | D8: TT | E8: 21140 | F8: 012 70%尾款
A9: 46149 | B9: KALAY DO BRASIL LTDA | C9: ZJCHDW-20260428-025 | D9: TT | E9: 10773 | F9: 025 30%预付款
A10: 46151 | B10: POLYRAM PLASTIC INDUSTRIES LTD | C10: ZJCHDW-20260428-022 | D10: TT | E10: 80730 | F10: 022 全款
A11: 46165 | B11: RAI INNOTECH POLYMERS PVTLTD | C11: ZJCHDW-20260122-003 | D11: LC | E11: 84150 | F11: 信用证全款
A12: 46171 | B12: AMAZON CORPORATE SERVICES PVT LTD | C12: ZJCHDW-20260211-008-1 | D12: TT | E12: 22510 | F12: 008-1 80%尾款
A13: 46176 | B13: ABBEY VIETNAM JOINT STOCK COMPANY | C13: ZJCHDW-20260310-010 | D13: LC | E13: 254227.71 | F13: 010 信用证
... A43: 46316 | B43: DARU COMMERCE CO., LTD. | C43: ZJCHDW-20261012-049 | D43: TT | E43: 27552 | F43: 部分尾款

Sheet 生物出库
A1: 发货日期 | B1: 客户 | C1: 合同号 | D1: 产品型号 | E1: 数量 | F1: 包装 | G1: 柜型 | H1: 提单号 | I1: 箱封号 | J1: 司机信息 | K1: 货代
A2: 46045 | B2: EUROPEAN PLASTIC JOINT STOCK COMPANY | C2: ZJCHDW-20260119-001 | D2: CH810 | E2: 5 | F2: 25kg/bag，托盘包装，1吨1托 | G2: 4.2米高栏车 | J2: 车号：豫JN5518 姓名：陈保生 电话：19939306728 身份证号：410928197001061299 | K2: 快源物流
A3: 46066 | B3: RAI INNOTECH POLYMERS PRIVATE LIMITED | C3: ZJCHDW-20260122-003 | D3: CH812 | E3: 27.5 | F3: 25kg/bag，散装 | G3: 40HQ | H3: TRLPENNGBMUN02121 | I3: INLU4240159 /40HC / T46168 | J3: 车号： 浙B3Q131 司机： 张涛 驾驶员手机： 17634967958 司机身份证号： 341281198806202491 | K3: 宁波鹏信国际货运代理有限公司
A4: 46066 | B4: RAI INNOTECH POLYMERS PRIVATE LIMITED | C4: ZJCHDW-20260122-003 | D4: CH812 | E4: 27.5 | F4: 25kg/bag，散装 | G4: 40HQ | H4: TRLPENNGBMUN02121 | I4: BEAU4497504/40HC/T46195 | J4: 车号： 浙B2G292 司机： 周忠良 驾驶员手机： 13056757383 司机身份证号： 320722197907146052 | K4: 宁波鹏信国际货运代理有限公司
A5: 46066 | B5: RAI INNOTECH POLYMERS PRIVATE LIMITED | C5: ZJCHDW-20260122-003 | D5: CH812 | E5: 27.5 | F5: 25kg/bag，散装 | G5: 40HQ | H5: TRLPENNGBMUN02121 | I5: BEAU4294596 /40HC/T46162 | J5: 车号： 浙B3U615 司机： 吴飞 驾驶员手机： 15605841525 司机身份证号： 342622198901203217 | K5: 宁波鹏信国际货运代理有限公司
A6: 46098 | B6: DARU COMMERCE CO., LTD. | C6: ZJCHDW-20260305-009 | D6: CH812 | E6: 20 | F6: 1000公斤吨包带托盘 | G6: 20GP | J6: 浙B5C217挂车：浙B51A7挂 司机： 吴佳豪 驾驶员手机： 18352905969 身份证：500240199508260534 | K6: 宁波腾辉国际物流有限公司
A7: 46102 | B7: Polyram Plastic Industries LTD | C7: ZJCHDW-20260316-013 | D7: CH875 | E7: 5 | F7: 1000公斤吨包带托盘 | G7: 40HQ | J7: 浙B81F88 司机： 付兴海 驾驶员手机：15968926588 | K7: 宁波鹏信国际货运代理有限公司
A8: 46102 | B8: Polyram Plastic Industries LTD | C8: ZJCHDW-20260316-013 | D8: CH810 | E8: 22 | F8: 1000公斤吨包带托盘
A9: 46105 | B9: DARU COMMERCE CO., LTD. | C9: ZJCHDW-20260313-012 | D9: CH812 | E9: 20 | F9: 1000公斤吨包带托盘 | G9: 20GP | J9: 浙B1T565 司机： 王辉 驾驶员手机： 13250939801 身份证：34122619751013673X | K9: 宁波腾辉国际物流有限公司
A10: 46109 | B10: ABBEY VIETNAM JOINT STOCK COMPANY | C10: ZJCHDW-20260310-010 | D10: N326 | E10: 23.4 | F10: 20公斤小包带托盘，1.3吨/托 | G10: 40HQ | J10: 车号：浙B2X885 司机：胡厚军 驾驶员手机：13956287630 | K10: 宁波鹏信国际货运代理有限公司
A11: 46109 | B11: ABBEY VIETNAM JOINT STOCK COMPANY | C11: ZJCHDW-20260310-010 | D11: N326 | E11: 23.4 | F11: 20公斤小包带托盘，1.3吨/托 | G11: 40HQ | J11: 车号：浙B2H029 司机：黄发水 驾驶员手机：13955004691 | K11: 宁波鹏信国际货运代理有限公司
A12: 46109 | B12: ABBEY VIETNAM JOINT STOCK COMPANY | C12: ZJCHDW-20260310-010 | D12: N326 | E12: 23.4 | F12: 20公斤小包带托盘，1.3吨/托 | G12: 40HQ | J12: 车号：浙B6V880 司机：李奎伍 驾驶员手机：13221935198 | K12: 宁波鹏信国际货运代理有限公司
A13: 46109 | B13: ABBEY VIETNAM JOINT STOCK COMPANY | C13: ZJCHDW-20260310-010 | D13: N326 | E13: 23.4 | F13: 20公斤小包带托盘，1.3吨/托 | G13: 40HQ | J13: 车号：浙B5Q132 司机 ：谢正华 驾驶员手机：13296828339 | K13: 宁波鹏信国际货运代理有限公司
A14: 46109 | B14: ABBEY VIETNAM JOINT STOCK COMPANY | C14: ZJCHDW-20260310-010 | D14: N326 | E14: 23.4 | F14: 20公斤小包带托盘，1.3吨/托 | G14: 40HQ | J14: 车号：浙B81F88 司机 ：付兴海 驾驶员手机：15968926588 | K14: 宁波鹏信国际货运代理有限公司
A15: 46110 | B15: ABBEY VIETNAM JOINT STOCK COMPANY | C15: ZJCHDW-20260310-010 | D15: N326 | E15: 23.4 | F15: 20公斤小包带托盘，1.3吨/托 | G15: 40HQ | J15: 车号：浙B6C895 司机：陈正春 驾驶员手机：13285843576 | K15: 宁波鹏信国际货运代理有限公司
A16: 46110 | B16: ABBEY VIETNAM JOINT STOCK COMPANY | C16: ZJCHDW-20260310-010 | D16: N326 | E16: 23.4 | F16: 20公斤小包带托盘，1.3吨/托 | G16: 40HQ | J16: 车号：浙B6M333 司机：陈保超 驾驶员手机：18606877698 | K16: 宁波鹏信国际货运代理有限公司
A17: 46110 | B17: ABBEY VIETNAM JOINT STOCK COMPANY | C17: ZJCHDW-20260310-010 | D17: N326 | E17: 23.4 | F17: 20公斤小包带托盘，1.3吨/托 | G17: 40HQ | J17: 车号：浙B6M365 司机：付彬 驾驶员手机：15726830365 | K17: 宁波鹏信国际货运代理有限公司
A18: 46110 | B18: ABBEY VIETNAM JOINT STOCK COMPANY | C18: ZJCHDW-20260310-010 | D18: N326 | E18: 23.4 | F18: 20公斤小包带托盘，1.3吨/托 | G18: 40HQ | J18: 车号：浙B2L600 司机 ：徐明 驾驶员手机：13685703550 | K18: 宁波鹏信国际货运代理有限公司
A19: 46110 | B19: ABBEY VIETNAM JOINT STOCK COMPANY | C19: ZJCHDW-20260310-010 | D19: N326 | E19: 23.4 | F19: 20公斤小包带托盘，1.3吨/托 | G19: 40HQ | J19: 车号：浙B5P332 司机 ：蔡自明 驾驶员手机：18856907101 | K19: 宁波鹏信国际货运代理有限公司
A20: 46134 | B20: AMAZON | C20: ZJCHDW-20260401-019-1 | D20: CH811 | E20: 27.5 | F20: 25kg/bag，散装 | G20: 40HQ | J20: 司机：鲁坤坤 身份证：412728198509150319 车牌：浙B6T119 电话：18667867181
A21: 46134 | B21: G P FLEX (INDIA) | C21: ZJCHDW-20260401-017 | D21: CH810 | E21: 27.5 | F21: 25kg/bag，散装 | G21: 40HQ | J21: 司机：罗祖明 身份证：433130198709102315 车牌：浙B2M812 电话：17742600034
A22: 46134 | B22: G P FLEX (INDIA) | C22: ZJCHDW-20260401-017 | D22: CH810 | E22: 27.5 | F22: 25kg/bag，散装 | G22: 40HQ | J22: 司机：李兆言 身份证：371322198610223814 车牌：浙B3K597 电话：19057976768
A23: 46135 | B23: BOMBAY PLASTIC UDYOG | C23: ZJCHDW-20260408-021 | D23: CH883 | E23: 27.5 | F23: 25kg/bag，散装 | G23: 40HQ | J23: 车牌号：浙B3Q660 电话：15658225828 名字：邵海燕 身份证号码：412702198109106112
A24: 46136 | B24: RAI INNOTECH POLYMERS PRIVATE LIMITED | C24: ZJCHDW-20260401-018 | D24: CH812 | E24: 27.5 | F24: 25kg/bag，散装 | G24: 40HQ | J24: 司机：潘宁宁 身份证：341221198409041536 车牌：浙B5W781 电话：18712565866
A25: 46136 | B25: RAI INNOTECH POLYMERS PRIVATE LIMITED | C25: ZJCHDW-20260401-018 | D25: CH812 | E25: 27.5 | F25: 25kg/bag，散装 | G25: 40HQ | J25: 司机：鲁坤坤 身份证：412728198509150319 车牌：浙B6T119 电话：18667867181
A26: 46142 | B26: AMAZON | C26: ZJCHDW-20260401-019-2 | D26: CH811 | E26: 27.5 | F26: 25kg/bag，散装 | G26: 40HQ | J26: 车牌号：浙B3Q660 电话：15658225828 名字：邵海燕 身份证号码：412702198109106112
A27: 46144 | B27: Valutrans Investment Co., Limited | C27: ZJCHDW-20260312-011 | D27: N330 | E27: 20 | F27: 1000kg带托盘 | G27: 40HQ | J27: 浙B1M229，13056920288.岳甫明，340122196712180791
A28: 46144 | B28: Valutrans Investment Co., Limited | C28: ZJCHDW-20260312-011 | D28: N330 | E28: 20 | F28: 1000kg带托盘 | G28: 40HQ | J28: 姓名：罗祖明 身份证：433130198709102315 车牌：浙B2M812 电话：17742600034
A29: 46144 | B29: Valutrans Investment Co., Limited | C29: ZJCHDW-20260312-011 | D29: N330 | E29: 20 | F29: 1000kg带托盘 | G29: 40HQ | J29: 浙B1N973 手机13157483206 姓名 ：赵峰理身份证412728197902206898
A30: 46144 | B30: Valutrans Investment Co., Limited | C30: ZJCHDW-20260312-011 | D30: N330 | E30: 20 | F30: 1000kg带托盘 | G30: 40HQ | J30: 郝世兵，浙B6B950，340122197304050773 电话：13095963598
A31: 46149 | B31: AMAZON | C31: ZJCHDW-20260211-008-1 | D31: CH810 | E31: 27.5 | F31: 25kg/bag，散装 | G31: 40HQ | J31: 车号： 浙B81F88 司机： 付兴海 托架号： 浙B88VU挂 驾驶员手机： 15968926588 身份证：341226197712252333
... A63: 46161 | B63: SKB INDUSTRIES | C63: ZJCHDW-20260513-028 | D63: CH810 | E63: 13.5 | F63: 25kg/bag，散装 | G63: 40HQ | J63: 车号： 浙B0Z535 司机： 吴鹏 驾驶员手机： 15726830838 装箱地点： 嵊州剡湖 身份证号码：340823199609162518
A64: 46161 | B64: SKB INDUSTRIES | C64: ZJCHDW-20260513-028 | D64: CH811 | E64: 14 | F64: 25kg/bag，散装 | G64: 40HQ
A65: 46162 | B65: G P FLEX (INDIA) | C65: ZJCHDW-20260428-024 | D65: CH811 | E65: 27.5 | F65: 25kg/bag，散装 | G65: 40HQ | J65: 车号： 浙B6C895 司机： 陈正春 托架号： 浙B911W挂 驾驶员手机： 13285843576 装箱地点： 嵊州剡湖 身份证：341226197902182313
A66: 46162 | B66: G P FLEX (INDIA) | C66: ZJCHDW-20260428-024 | D66: CH810 | E66: 27.5 | F66: 25kg/bag，散装 | G66: 40HQ | J66: 车号： 浙B7K653 司机： 岳福坤 托架号： 浙B9Z87挂 驾驶员手机： 15397736508 装箱地点： 嵊州剡湖 身份证: 513027197708277633
A67: 46162 | B67: ARLON INNOVATION BHARAT PRIVATE LIMITED | C67: ZJCHDW-20260408-020 | D67: CH811 | E67: 27.5 | F67: 25kg/bag，散装 | G67: 40HQ | J67: 车号： 浙B6M365 司机： 付彬 托架号： 浙BOX09挂 驾驶员手机： 15726830365 装箱地点： 嵊州剡湖 身份证 341226199210052330
A68: 46162 | B68: ARLON INNOVATION BHARAT PRIVATE LIMITED | C68: ZJCHDW-20260408-020 | D68: CH811 | E68: 27.5 | F68: 25kg/bag，散装 | G68: 40HQ | J68: 车号： 浙B1T565 司机： 王辉 托架号： 浙B111H挂 驾驶员手机： 13250939801 装箱地点： 嵊州剡湖 身份证号码：34122619751013673
A69: 46164 | B69: BOMBAY PLASTIC UDYOG | C69: ZJCHDW-20260511-027 | D69: CH810 | E69: 27.5 | F69: 25kg/bag，散装 | G69: 40HQ | J69: 车号： 浙B5Q132 司机： 谢正华 托架号： 浙B150M挂 驾驶员手机： 13296828339 装箱地点： 嵊州剡湖 身份证号码34112419780102701
A70: 46164 | B70: BOMBAY PLASTIC UDYOG | C70: ZJCHDW-20260511-027 | D70: CH811 | E70: 27.5 | F70: 25kg/bag，散装 | G70: 40HQ | J70: 车号： 浙B7K653 司机： 岳福坤 托架号： 浙B9Z87挂 驾驶员手机： 15397736508 装箱地点： 嵊州剡湖 身份证: 513027197708277633
A71: 46166 | B71: KALAY DO BRASIL LTDA | C71: ZJCHDW-20260428-025 | D71: CH810 | E71: 27 | F71: 1000kg带托盘 | G71: 40HQ | J71: 车号： 浙B5Q132 挂车号牌： 浙B150M 司机：谢正华 身份证号码341124197801027017
A72: 46167 | B72: Polyram Plastic Industries LTD | C72: ZJCHDW-20260428-022 | D72: CH810 | E72: 27 | F72: 25kg/bag，散装 | G72: 40HQ | J72: 浙B3L100 /浙B599L挂 司机： 严定文 驾驶员手机： 15606686179 身份证：429006196707240334
A73: 46167 | B73: Polyram Plastic Industries LTD | C73: ZJCHDW-20260428-022 | D73: CH810 | E73: 27 | F73: 25kg/bag，散装 | G73: 40HQ | J73: 浙B6V880 浙B1620挂 司机： 李奎伍 驾驶员手机： 13221935198 身份证：341126197301116032
A74: 46184 | B74: RAI INNOTECH POLYMERS PVT. LTD. | C74: ZJCHDW-20260602-029 | D74: CH812 | E74: 27.5 | F74: 25kg/bag，散装 | G74: 40HQ | J74: 车号: 浙B5N529 司机: 赵玉华 驾驶员手机: 15158348477 装箱地点： 嵊州剡湖 身份证号码：511021197110065230
A75: 46184 | B75: RAI INNOTECH POLYMERS PVT. LTD. | C75: ZJCHDW-20260602-029 | D75: CH812 | E75: 27.5 | F75: 25kg/bag，散装 | G75: 40HQ | J75: 车号: 浙B5N165 司机: 杜全新 驾驶员手机: 13598653313 装箱地点： 嵊州剡湖 身份证号码：410782197704243774
A76: 46185 | B76: RAI INNOTECH POLYMERS PVT. LTD. | C76: ZJCHDW-20260602-029 | D76: CH812 | E76: 27.5 | F76: 25kg/bag，散装 | G76: 40HQ | J76: 车号: 浙B5P551 司机: 赵万会 身份证：412932197611223212 驾驶员手机: 13598201667
A77: 46185 | B77: RAI INNOTECH POLYMERS PVT. LTD. | C77: ZJCHDW-20260602-029 | D77: CH812 | E77: 27.5 | F77: 25kg/bag，散装 | G77: 40HQ | J77: 车号: 浙B7J152 司机: 陈行 身份证：412822199109026572 驾驶员手机: 13915243083
A78: 46217 | B78: DARU COMMERCE CO., LTD. | C78: ZJCHDW-20260710-031 | D78: CH883 | E78: 1 | F78: 小包打托 | G78: 40HQ | J78: 车牌：浙FW7R19 司机：郑名明 电话：17306516707 身份证：522127199609272533 | K78: 孙氏物流
A79: 46224 | B79: Polynomous Industries Private Limited | C79: ZJCHDW-20260706-030 | D79: CH883 | E79: 27.5 | F79: 25kg/bag，散装 | G79: 40HQ | J79: 车号： 浙B6X315 司机： 黄华 托架号： 浙B9W72挂 驾驶员手机： 15375021818 身份证：34112419810712601X
A80: 46224 | B80: Polynomous Industries Private Limited | C80: ZJCHDW-20260706-030 | D80: CH883 | E80: 27.5 | F80: 25kg/bag，散装 | G80: 40HQ | J80: 车号： 浙B7K653 司机： 岳福坤 托架号： 浙B9Z87挂 驾驶员手机： 15397736508 身份证：513027197708277633
A81: 46224 | B81: Polynomous Industries Private Limited | C81: ZJCHDW-20260706-030 | D81: CH811 | E81: 27.5 | F81: 25kg/bag，散装 | G81: 40HQ | J81: 车号： 浙B3L100 司机： 严定文 托架号： 浙B599L挂 驾驶员手机： 15606686179 身份证：429006196707240334
A82: 46232 | B82: SKB INDUSTRIES | C82: ZJCHDW-20260723-035-1 | D82: CH810 | E82: 27.5 | F82: 25kg/bag，散装 | G82: 40HQ | J82: 车号： 浙B6M333 司机： 陈保超 托架号： 浙B0Z67挂 驾驶员手机： 18606877698 装箱地点： 嵊州剡湖 身份证：342128197304151793 | K82: 宁波鹏信国际货运代理有限公司
A83: 46232 | B83: G.P. FLEX (INDIA) | C83: ZJCHDW-20260723-036 | D83: CH810 | E83: 27.5 | F83: 25kg/bag，散装 | G83: 40HQ | J83: 车号： 浙B2L600 司机： 徐明 托架号： 浙B579U挂 驾驶员手机： 13685703550 装箱地点： 嵊州剡湖 身份证 411526199002021630 | K83: 宁波鹏信国际货运代理有限公司
A84: 46232 | B84: G.P. FLEX (INDIA) | C84: ZJCHDW-20260723-036 | D84: CH810 | E84: 27.5 | F84: 25kg/bag，散装 | G84: 40HQ | J84: 车号： 浙B1T565 司机： 王辉 托架号： 浙B111H挂 驾驶员手机： 13250939801 装箱地点： 嵊州剡湖 身份证 34122619751013673X | K84: 宁波鹏信国际货运代理有限公司
A85: 46235 | B85: ABBEY VIETNAM JOINT STOCK COMPANY | C85: ZJCHDW-20260710-032 | D85: N326 | E85: 23.4 | F85: 20公斤小包带托盘，1.3吨/托 | G85: 40HQ | J85: 车号：浙B6T119 司机：鲁坤坤 驾驶员手机：18667867181 身份证：412728198509150319
A86: 46235 | B86: ABBEY VIETNAM JOINT STOCK COMPANY | C86: ZJCHDW-20260710-032 | D86: N326 | E86: 23.4 | F86: 20公斤小包带托盘，1.3吨/托 | G86: 40HQ | J86: 车号：浙B2S116 司机：杜海军 驾驶员手机：15557079966 身份证：412728198611153452
A87: 46235 | B87: ABBEY VIETNAM JOINT STOCK COMPANY | C87: ZJCHDW-20260710-032 | D87: N326 | E87: 23.4 | F87: 20公斤小包带托盘，1.3吨/托 | G87: 40HQ | J87: 车号：浙B3Q660 司机：邵海燕 驾驶员手机：15658225828 身份证：412702198109106112
A88: 46235 | B88: ABBEY VIETNAM JOINT STOCK COMPANY | C88: ZJCHDW-20260710-032 | D88: N326 | E88: 23.4 | F88: 20公斤小包带托盘，1.3吨/托 | G88: 40HQ | J88: 车号：浙B2R529 司机 ：时敬 驾驶员手机：18601668582 身份证：412702197201206058
A89: 46246 | B89: SKB INDUSTRIES | C89: ZJCHDW-20260723-035-2 | D89: CH811 | E89: 27.5 | F89: 25kg/bag，散装 | G89: 40HQ | J89: 车号： 浙B5Q132 司机： 谢正华 托架号： 浙B150M挂 驾驶员手机： 13296828339 装箱地点： 嵊州剡湖 身份证号码34112419780102701 | K89: 宁波鹏信国际货运代理有限公司
A90: 46247 | B90: RAI INNOTECH POLYMERS PVT. LTD. | C90: ZJCHDW-20260723-037 | D90: CH812 | E90: 27.5 | F90: 25kg/bag，散装 | G90: 40HQ | J90: 车号： 浙B2H029 司机： 黄发水 托架号： 浙B168R挂 驾驶员手机： 13955004691 装箱地点： 嵊州剡湖 身份证号码： 341124197812246039 | K90: 宁波鹏信国际货运代理有限公司
A91: 46248 | B91: BOMBAY PLASTIC UDYOG | C91: ZJCHDW-20260722-033 | D91: CH883 | E91: 27.5 | F91: 25kg/bag，散装 | G91: 40HQ | J91: 车号： 浙B7K653 司机： 岳福坤 托架号： 浙B9Z87挂 驾驶员手机： 15397736508 装箱地点： 嵊州剡湖 身份证：513027197708277633 | K91: 宁波鹏信国际货运代理有限公司
A92: 46248 | B92: RAI INNOTECH POLYMERS PVT. LTD. | C92: ZJCHDW-20260723-037 | D92: CH812 | E92: 27.5 | F92: 25kg/bag，散装 | G92: 40HQ | J92: 车号： 浙B2X885 司机： 胡厚军 托架号： 浙B991P挂 驾驶员手机： 13956287630 装箱地点： 嵊州剡湖 身份证：341004197603280037 | K92: 宁波鹏信国际货运代理有限公司
A93: 46251 | B93: AMAZON CORPORATE SERVICES PVT. LTD. | C93: ZJCHDW-20260722-034 | D93: CH811 | E93: 27.5 | F93: 25kg/bag，散装 | G93: 40HQ | J93: 车号： 浙B0Z535 司机： 吴鹏 驾驶员手机： 15726830838 装箱地点： 嵊州剡湖 身份证号码：340823199609162518 | K93: 宁波汇盟国际物流有限公司
A94: 46252 | B94: AMAZON CORPORATE SERVICES PVT. LTD. | C94: ZJCHDW-20260722-034 | D94: CH810 | E94: 27.5 | F94: 25kg/bag，散装 | G94: 40HQ | J94: 车号: 浙B3U919 司机: 陈发昌 驾驶员手机: 13035458811 身份证341126198206057331 | K94: 宁波汇盟国际物流有限公司
A95: 46256 | B95: AMAZON CORPORATE SERVICES PVT. LTD. | C95: ZJCHDW-20260731-039 | D95: CH811 | E95: 27.5 | F95: 25kg/bag，散装 | G95: 40HQ | J95: 车号： 浙B3M256 司机： 高桂友 驾驶员手机： 18968397361 身份证：341226196910056718 | K95: 宁波汇盟国际物流有限公司
A96: 46256 | B96: AMAZON CORPORATE SERVICES PVT. LTD. | C96: ZJCHDW-20260731-039 | D96: CH810 | E96: 27.5 | F96: 25kg/bag，散装 | G96: 40HQ | J96: 车号： 浙B0Z535 司机： 吴鹏 驾驶员手机： 15726830838 身份证：340823199609162518 | K96: 宁波汇盟国际物流有限公司
A97: 46264 | B97: Polynomous Industries Private Limited | C97: ZJCHDW-20260811-042-1 | D97: CH811 | E97: 27.5 | F97: 25kg/bag，散装 | G97: 40HQ | J97: 浙B6T119 18667867181 鲁坤坤 412728198509150319 | K97: 宁波博海国际物流公司
A98: 46267 | B98: Polyram Plastic Industries LTD | C98: ZJCHDW-20260811-041 | D98: CH810 | E98: 27 | F98: 1000公斤吨包带托盘 | G98: 40HQ | J98: 车号 浙B5Q132 挂车号牌 浙B150M谢正华 身份证号码341124197801027017 | K98: 宁波鹏信国际货运代理有限公司
A99: 46267 | B99: Polyram Plastic Industries LTD | C99: ZJCHDW-20260811-041 | D99: CH810 | E99: 27 | F99: 1000公斤吨包带托盘 | G99: 40HQ | J99: 浙B6M333/浙B0Z67挂/18606877698 陈保超/ 身份证：342128197304151793 | K99: 宁波鹏信国际货运代理有限公司
A100: 46275 | B100: SPECTRUM IMPEX | C100: ZJCHDW-20260806-040 | D100: CH811 | E100: 27.5 | F100: 25kg/bag，散装 | G100: 40HQ | J100: 车号： 浙B2H029 浙B168R挂 司机： 黄发水 驾驶员手机： 13955004691 身份证号码341124197812246039 | K100: 宁波鹏信国际货运代理有限公司
... A108: 46308 | B108: DARU COMMERCE CO., LTD. | C108: ZJCHDW-20261012-049-1 | D108: CH812 | E108: 24 | F108: 1000公斤吨包带托盘) | G108: 40HQ | J108: 车号 ：浙B5Q132 挂车：浙B150M 挂 司机： 谢正华 驾驶员手机： 13296828339 身份证： 341124197801027017 | K108: 宁波腾辉国际物流有限公司

Sheet 长科
A1: 销售员 | B1: 付款方式 | C1: 单位名称 | D1: 合同号 | E1: 合同有效期 | F1: 产品规格 | G1: 合同量 | H1: 销售单价 | I1: 销售金额 | J1: 实际出库 | K1: 未发量 | L1: 到款金额 | M1: 余款 | N1: 应收款 | O1: 应收款（人民币） | P1: 佣金 | Q1: 佣金总价 | R1: 审批汇率 | S1: 审批价 | T1: 指导价 | U1: 合同总金额￥ | V1: 包装 | W1: 运输条款 | X1: 目的港 | Y1: 审批海运费 | Z1: 审批保费 | AA1: 审批内陆费 | AB1: 实际海运费 | AC1: 托盘数量 | AD1: 缠绕膜 | AE1: 扎带 | AF1: 卡扣 | AG1: 吨袋 | AH1: 绑带
A2: 毛晓翔 | B2: 30/70TT | C2: PREMIUM POLYALLOYS LIMITED | D2: CMTRL-XS-20260428-0002 | E2: 46178 | F2: SAN 2800 | G2: 110 | H2: 1510 | I2: =G2*H2 -> 166100 | J2: 0 | K2: =G2-J2 -> 110 | L2: 0 | M2: =I2-L2 -> 166100 | N2: =H2*J2-L2 -> 0 | O2: =N2*R2 -> 0 | P2: 5 | Q2: =P2*G2 -> 550 | R2: 6.8177 | S2: 11047 | T2: 11000 | U2: =S2*G2 -> 1215170 | V2: 25公斤小包散装 | W2: CIF | X2: NHAVA SHEVA | Y2: =1300*4 -> 5200 | Z2: =46*4 -> 184 | AA2: =4800*4 -> 19200
A3: 毛晓翔 | B3: LC90 | C3: AMAZON CORPORATE SERVICES PVT. LTD. | D3: CMTRL-XS-20260506-0001 | E3: 46179 | F3: SAN 4800 | G3: 27.5 | H3: 1500 | I3: =G3*H3 -> 41250 | J3: 0 | K3: =G3-J3 -> 27.5 | L3: 0 | M3: =I3-L3 -> 41250 | N3: =H3*J3-L3 -> 0 | O3: =N3*R3 -> 0 | P3: 0 | Q3: =P3*G3 -> 0 | R3: 6.8177 | S3: 11104 | T3: 11100 | U3: =S3*G3 -> 305360 | V3: 25公斤小包散装 | W3: CIF | X3: MUNDRA, FINAL ICD DADRI | Y3: 1300 | Z3: 46 | AA3: 4800
A4: 毛晓翔 | B4: LC90 | C4: AMAZON CORPORATE SERVICES PVT. LTD. | D4: CMTRL-XS-20260506-0001 | E4: 46179 | F4: HIPS-CH612 | G4: 0.1 | H4: 1540 | I4: =G4*H4 -> 154 | J4: 0 | K4: =G4-J4 -> 0.1 | L4: 0 | M4: =I4-L4 -> 154 | N4: =H4*J4-L4 -> 0 | O4: =N4*R4 -> 0 | P4: 0 | Q4: =P4*G4 -> 0 | R4: 6.8177 | S4: 11312 | T4: 11100 | U4: =S4*G4 -> 1131.2 | V4: 25公斤小包散装 | W4: CIF | X4: MUNDRA, FINAL ICD DADRI
A5: 毛晓翔 | B5: LC90 | C5: AMAZON CORPORATE SERVICES PVT. LTD. | D5: CMTRL-XS-20260506-0001 | E5: 46179 | F5: MABS CT2010 | G5: 0.1 | H5: 2230 | I5: =G5*H5 -> 223 | J5: 0 | K5: =G5-J5 -> 0.1 | L5: 0 | M5: =I5-L5 -> 223 | N5: =H5*J5-L5 -> 0 | O5: =N5*R5 -> 0 | P5: 0 | Q5: =P5*G5 -> 0 | R5: 6.8177 | S5: 16628 | T5: 15500 | U5: =S5*G5 -> 1662.8 | V5: 25公斤小包散装 | W5: CIF | X5: MUNDRA, FINAL ICD DADRI
A6: 张晓敏 | B6: 30/70TT | C6: VINAYAK AGNIPEAK LLP | D6: CMTRL-XS-20260803-0001 | E6: 46268 | F6: SAN 900 | G6: 28 | H6: 1330 | I6: =G6*H6 -> 37240 | J6: 0 | K6: =G6-J6 -> 28 | L6: 0 | M6: =I6-L6 -> 37240 | N6: =H6*J6-L6 -> 0 | O6: =N6*R6 -> 0 | P6: 0 | Q6: =P6*G6 -> 0 | R6: 6.74 | S6: 9379 | U6: =S6*G6 -> 262612 | V6: 25公斤小包散装 | W6: CFR | X6: NHAVA SHEVA | Y6: 2100 | Z6: 0 | AA6: 5000
A7: 毛晓翔 | B7: LC90 | C7: K.L.J. POLYMERS PRIVATE LIMITED | D7: CMTRL-XS-20260112-0003 | E7: 46065 | F7: SAN 4800 | G7: 55 | H7: 1035 | I7: =G7*H7 -> 56925 | J7: 55 | K7: =G7-J7 -> 0 | L7: =长科收款!E28 -> 56925 | M7: =I7-L7 -> 0 | N7: =H7*J7-L7 -> 0 | O7: =N7*R7 -> 0 | P7: 10 | Q7: =P7*G7 -> 550 | R7: 6.9636 | S7: 7454 | T7: 7450 | U7: =S7*G7 -> 409970 | V7: 25公斤小包散装 | W7: CIF | X7: NHAVA SHEVA | Y7: =1500*2 -> 3000 | Z7: =31*2 -> 62 | AA7: =5000*2 -> 10000
A8: 毛晓翔 | B8: LC90 | C8: AMLON POLYMERS | D8: CMTRL-XS-20260112-0005 | E8: 46065 | F8: SAN 4800 | G8: 55 | H8: 985 | I8: =G8*H8 -> 54175 | J8: 55 | K8: =G8-J8 -> 0 | L8: =长科收款!E32 -> 54175 | M8: =I8-L8 -> 0 | N8: =H8*J8-L8 -> 0 | O8: =N8*R8 -> 0 | P8: 10 | Q8: =P8*G8 -> 550 | R8: 6.9636 | S8: 7463 | T8: 7450 | U8: =S8*G8 -> 410465 | V8: 25公斤小包散装 | W8: FOB | X8: QINZHOU | Y8: 0 | Z8: 0 | AA8: =6000*2 -> 12000
A9: 陶莹 | B9: 30/70TT | C9: ALPEX JOINT STOCK COMPANY | D9: CMTRL-XS-20260113-0002 | E9: 46066 | F9: SAN 900 | G9: 27.5 | H9: 1060 | I9: =G9*H9 -> 29150 | J9: 27.5 | K9: =G9-J9 -> 0 | L9: =长科收款!E2+长科收款!E3 -> 29127 | M9: =I9-L9 -> 23 | N9: =H9*J9-L9 -> 23 | O9: =N9*R9 -> 160.54 | P9: 0 | Q9: =P9*G9 -> 0 | R9: 6.98 | S9: 7978 | T9: 7950 | U9: =S9*G9 -> 219395 | V9: 25公斤小包散装 | W9: CIF | X9: Ho Chi Minh | Y9: 600 | Z9: 31 | AA9: 5000
A10: 张晓敏 | B10: 100TT | C10: TAIWAN TONGZEWANG INDUSTRY CO., LTD. | D10: CMTRL-XS-20260114-0001 | E10: 46067 | F10: 炭黑 N660 | G10: 0.5 | H10: 5400 | I10: =G10*H10 -> 2700 | J10: 0.5 | K10: =G10-J10 -> 0 | L10: 2700 | M10: =I10-L10 -> 0 | N10: =H10*J10-L10 -> 0 | O10: =N10*R10 -> 0 | P10: 0 | Q10: =P10*G10 -> 0 | R10: 1 | S10: 5400 | T10: 5280 | U10: =S10*G10 -> 2700 | V10: 500kg吨包，带托盘 | W10: EXW | X10: FACTORY | Y10: 0 | Z10: 0 | AA10: 0 | AB10: 0
A11: 张晓敏 | B11: 100TT | C11: TAIWAN TONGZEWANG INDUSTRY CO., LTD. | D11: CMTRL-XS-20260114-0001 | E11: 46067 | F11: 炭黑 N220 | G11: 0.5 | H11: 6300 | I11: =G11*H11 -> 3150 | J11: 0.5 | K11: =G11-J11 -> 0 | L11: 3150 | M11: =I11-L11 -> 0 | N11: =H11*J11-L11 -> 0 | O11: =N11*R11 -> 0 | P11: 0 | Q11: =P11*G11 -> 0 | R11: 1 | S11: 6300 | T11: 6180 | U11: =S11*G11 -> 3150 | V11: 500kg吨包，带托盘 | W11: EXW | X11: FACTORY | Y11: 0 | Z11: 0 | AA11: 0 | AB11: 0
A12: 刘希雅 | B12: 100TT | C12: Polyram Plastic Industries LTD | D12: CMTRL-XS-20260116-0001 | E12: 46068 | F12: HIPS-CH612 | G12: 27 | H12: 1230 | I12: =G12*H12 -> 33210 | J12: 27 | K12: =G12-J12 -> 0 | L12: =长科收款!E6 -> 33210 | M12: =I12-L12 -> 0 | N12: =H12*J12-L12 -> 0 | O12: =N12*R12 -> 0 | P12: 30 | Q12: =P12*G12 -> 810 | R12: 6.96 | S12: 7808 | T12: 7600 | U12: =S12*G12 -> 210816 | V12: 25公斤小包带托盘 | W12: CIF | X12: HAIFA | Y12: 4500 | Z12: 37 | AA12: 5000
A13: 陈诺 | B13: 100TT | C13: ZHI YUE XIAN (VIETNAM) CO., LTD | D13: CMTRL-XS-20260305-0011 | E13: 46117 | F13: MABS CT2010 | G13: 27.5 | H13: 1780 | I13: =G13*H13 -> 48950 | J13: 27.5 | K13: =G13-J13 -> 0 | L13: =长科收款!E5 -> 48950 | M13: =I13-L13 -> 0 | N13: =H13*J13-L13 -> 0 | O13: =N13*R13 -> 0 | P13: 0 | Q13: =P13*G13 -> 0 | R13: 6.87 | S13: 13810 | T13: 7601 | U13: =S13*G13 -> 379775 | V13: 25公斤小包散装 | W13: EXW | X13: FACTORY | Y13: 0 | Z13: 0 | AA13: 0 | AB13: 0
A14: 张晓敏 | B14: 20/80TT | C14: Valutrans Investment Co., Limited | D14: CMTRL-XS-20260310-0001 | E14: 46132 | F14: 炭黑 N330 | G14: 600 | H14: 1030 | I14: =G14*H14 -> 618000 | J14: =280+120+160+40 -> 600 | K14: =G14-J14 -> 0 | L14: =长科收款!E11+长科收款!E8-3920+329600 -> 618000 | M14: =I14-L14 -> 0 | N14: =H14*J14-L14 -> 0 | O14: =N14*R14 -> 0 | P14: 0 | Q14: =P14*G14 -> 0 | R14: 6.875 | S14: 7081 | T14: 7050 | U14: =S14*G14 -> 4248600 | V14: 1000kg 吨袋 | W14: EXW | X14: FACTORY | Y14: 0 | Z14: 0 | AA14: 0
A15: 张晓敏 | B15: 20/80TT | C15: Valutrans Investment Co., Limited | D15: CMTRL-XS-20260310-0001 | E15: 46132 | F15: 炭黑 N660 | G15: 20 | H15: 980 | I15: =G15*H15 -> 19600 | J15: 20 | K15: =G15-J15 -> 0 | L15: =3920+15680 -> 19600 | M15: =I15-L15 -> 0 | N15: =H15*J15-L15 -> 0 | O15: =N15*R15 -> 0 | P15: 0 | Q15: =P15*G15 -> 0 | R15: 6.875 | S15: 6737 | T15: 6700 | U15: =S15*G15 -> 134740 | V15: 1000kg 吨袋 | W15: EXW | X15: FACTORY | Y15: 0 | Z15: 0 | AA15: 0
A16: 杨玉赏 | B16: 30/70TT | C16: ABBEY VIETNAM JOINT STOCK COMPANY | D16: CMTRL-XS-20260313-0001 | E16: 46125 | F16: 炭黑 N326 | G16: 9.6 | H16: 1120 | I16: =G16*H16 -> 10752 | J16: 9.6 | K16: =G16-J16 -> 0 | L16: =长科收款!E13+3923.85 -> 10752 | M16: =I16-L16 -> 0 | N16: =H16*J16-L16 -> 0 | O16: =N16*R16 -> 0 | P16: 0 | Q16: =P16*G16 -> 0 | R16: 6.87 | S16: 7417 | T16: 7250 | U16: =S16*G16 -> 71203.2 | V16: 20公斤带托盘 | W16: CIF | X16: Hai Phong | Y16: 4500 | Z16: 150 | AA16: 30
A17: 杨玉赏 | B17: 30/70TT | C17: ABBEY VIETNAM JOINT STOCK COMPANY | D17: CMTRL-XS-20260313-0001 | E17: 46125 | F17: 炭黑 N220 | G17: 2.2 | H17: 1170 | I17: =G17*H17 -> 2574 | J17: 2.2 | K17: =G17-J17 -> 0 | L17: 2574 | M17: =I17-L17 -> 0 | N17: =H17*J17-L17 -> 0 | O17: =N17*R17 -> 0 | P17: 0 | Q17: =P17*G17 -> 0 | R17: 6.87 | S17: 7760 | T17: 7600 | U17: =S17*G17 -> 17072 | V17: 20公斤带托盘 | W17: CIF | X17: Hai Phong
A18: 杨玉赏 | B18: 30/70TT | C18: ABBEY VIETNAM JOINT STOCK COMPANY | D18: CMTRL-XS-20260313-0001 | E18: 46125 | F18: 炭黑 N550 | G18: 4.4 | H18: 1055 | I18: =G18*H18 -> 4642 | J18: 4.4 | K18: =G18-J18 -> 0 | L18: 4642 | M18: =I18-L18 -> 0 | N18: =H18*J18-L18 -> 0 | O18: =N18*R18 -> 0 | P18: 0 | Q18: =P18*G18 -> 0 | R18: 6.87 | S18: 6970 | T18: 6800 | U18: =S18*G18 -> 30668 | V18: 20公斤带托盘 | W18: CIF | X18: Hai Phong
A19: 杨玉赏 | B19: 30/70TT | C19: ABBEY VIETNAM JOINT STOCK COMPANY | D19: CMTRL-XS-20260313-0001 | E19: 46125 | F19: 炭黑 N660 | G19: 2.2 | H19: 1040 | I19: =G19*H19 -> 2288 | J19: 2.2 | K19: =G19-J19 -> 0 | L19: 2288 | M19: =I19-L19 -> 0 | N19: =H19*J19-L19 -> 0 | O19: =N19*R19 -> 0 | P19: 0 | Q19: =P19*G19 -> 0 | R19: 6.87 | S19: 6867 | T19: 6700 | U19: =S19*G19 -> 15107.4 | V19: 20公斤带托盘 | W19: CIF | X19: Hai Phong
A20: 陈诺 | B20: 100TT | C20: 鏵塑股份有限公司ULTRATEC PLASTICS CO.,LTD. | D20: CMTRL-XS-20260318-0002 | E20: 46130 | F20: HIPS-CH612 | G20: 15 | H20: 1575 | I20: =G20*H20 -> 23625 | J20: 15 | K20: =G20-J20 -> 0 | L20: =长科收款!E7 -> 23625 | M20: =I20-L20 -> 0 | N20: =H20*J20-L20 -> 0 | O20: =N20*R20 -> 0 | P20: 0 | Q20: =P20*G20 -> 0 | R20: 6.86 | S20: 11500 | T20: 11300 | U20: =S20*G20 -> 172500 | V20: 25公斤小包带托盘 | W20: CIF | X20: Keelung | Y20: 400 | Z20: 26 | AA20: 5000
A21: 毛晓翔 | B21: LC90 | C21: PT POLYMERS INDIA LLP | D21: CMTRL-XS-20260320-0001 | E21: 46142 | F21: SAN 2800 | G21: 137.5 | H21: 1480 | I21: =G21*H21 -> 203500 | J21: =82.5+27.5+27.5 -> 137.5 | K21: =G21-J21 -> 0 | L21: =长科收款!E9+长科收款!E26+162800 -> 203500 | M21: =I21-L21 -> 0 | N21: =H21*J21-L21 -> 0 | O21: =N21*R21 -> 0 | P21: 15 | Q21: =P21*G21 -> 2062.5 | R21: 6.8825 | S21: 10722 | T21: 10500 | U21: =S21*G21 -> 1474275 | V21: 25公斤小包散装 | W21: CIF | X21: MUNDRA | Y21: =1530*5 -> 7650 | Z21: =41*5 -> 205 | AA21: =6500*5 -> 32500
A22: 毛晓翔 | B22: LC90 | C22: PT POLYMERS INDIA LLP | D22: CMTRL-XS-20260320-0001 | E22: 46142 | F22: SAN 4800 | G22: 55 | H22: 1480 | I22: =G22*H22 -> 81400 | J22: 55 | K22: =G22-J22 -> 0 | L22: 81400 | M22: =I22-L22 -> 0 | N22: =H22*J22-L22 -> 0 | O22: =N22*R22 -> 0 | P22: 15 | Q22: =P22*G22 -> 825 | R22: 6.8825 | S22: 10722 | T22: 10500 | U22: =S22*G22 -> 589710 | V22: 25公斤小包散装 | W22: CIF | X22: MUNDRA | Y22: =1530*2 -> 3060 | Z22: =41*2 -> 82 | AA22: =6500*2 -> 13000
A23: 张晓敏 | B23: 100TT | C23: BILLION ASCENT INDUSTRIAL LIMITED | D23: CMTRL-XS-20260323-0001 | E23: 46142 | F23: SAN 900 | G23: 270 | H23: 1540 | I23: =G23*H23 -> 415800 | J23: =54+54+108+54 -> 270 | K23: =G23-J23 -> 0 | L23: =长科收款!E10+长科收款!E12+长科收款!E15 -> 415800 | M23: =I23-L23 -> 0 | N23: =H23*J23-L23 -> 0 | O23: =N23*R23 -> 0 | P23: 0 | Q23: =P23*G23 -> 0 | R23: 6.89 | S23: 11804 | T23: 10501 | U23: =S23*G23 -> 3187080 | V23: 25公斤小包散装 | W23: FOB | X23: QINZHOU | Y23: 0 | Z23: 0 | AA23: =5000*10 -> 50000
A24: 张晓敏 | B24: LC90 | C24: AYDIN PLASTIK TURIZM INS. SAN. VE TIC. LTD. STI | D24: CMTRL-XS-20260326-0001 | E24: 46138 | F24: MABS CT2010 | G24: 54 | H24: 1920 | I24: =G24*H24 -> 103680 | J24: 54 | K24: =G24-J24 -> 0 | L24: =长科收款!E49 -> 183680 | M24: =I24-L24 -> -80000 | N24: =H24*J24-L24 -> -80000 | O24: =N24*R24 -> -551200 | P24: 0 | Q24: =P24*G24 -> 0 | R24: 6.89 | S24: 14763 | T24: 14500 | U24: =S24*G24 -> 797202 | V24: 25公斤小包散装 | W24: FOB | X24: QINZHOU | Y24: 0 | Z24: 0 | AA24: =5000*2 -> 10000
A25: 张晓敏 | B25: 100TT | C25: BILLION ASCENT INDUSTRIAL LIMITED | D25: CMTRL-XS-20260330-0001 | E25: 46132 | F25: SAN 900 | G25: 81 | H25: 1510 | I25: =G25*H25 -> 122310 | J25: 81 | K25: =G25-J25 -> 0 | L25: =长科收款!E18 -> 122310 | M25: =I25-L25 -> 0 | N25: =H25*J25-L25 -> 0 | O25: =N25*R25 -> 0 | P25: 0 | Q25: =P25*G25 -> 0 | R25: 6.89 | S25: 11570 | T25: 11300 | U25: =S25*G25 -> 937170 | V25: 25公斤小包散装 | W25: FOB | X25: QINZHOU | Y25: 0 | Z25: 0 | AA25: 5000
A26: 张晓敏 | B26: 100TT | C26: BILLION ASCENT INDUSTRIAL LIMITED | D26: CMTRL-XS-20260331-0001 | E26: 46178 | F26: SAN 900 | G26: 999 | H26: 1535 | I26: =G26*H26 -> 1533465 | J26: =297+27+27+27+27 -> 405 | K26: =G26-J26 -> 594 | L26: =414449.5+长科收款!E25+长科收款!E51+长科收款!E64+长科收款!E68+长科收款!E92 -> 750126 | M26: =I26-L26 -> 783339 | N26: =H26*J26-L26 -> -128451 | O26: =N26*R26 -> -886311.9 | P26: 0 | Q26: =P26*G26 -> 0 | R26: 6.9 | S26: 11812 | T26: 11800 | U26: =S26*G26 -> 11800188 | V26: 25公斤小包散装 | W26: FOB | X26: QINZHOU | Y26: 0 | Z26: 0 | AA26: =4200*37 -> 155400
A27: 陶莹 | B27: 30/70TT | C27: ALPEX JOINT STOCK COMPANY | D27: CMTRL-XS-20260331-0002 | E27: 46142 | F27: SAN 900 | G27: 27.5 | H27: 1580 | I27: =G27*H27 -> 43450 | J27: 27.5 | K27: =G27-J27 -> 0 | L27: =长科收款!E14+长科收款!E22 -> 43450 | M27: =I27-L27 -> 0 | N27: =H27*J27-L27 -> 0 | O27: =N27*R27 -> 0 | P27: 0 | Q27: =P27*G27 -> 0 | R27: 6.8931 | S27: 11955 | T27: 11800 | U27: =S27*G27 -> 328762.5 | V27: 25公斤小包散装 | W27: CIF | X27: Ho Chi Minh | Y27: 550 | Z27: 48 | AA27: 5000
A28: 杨玉赏 | B28: LC90 | C28: AYDIN PLASTIK TURIZM INS. SAN. VE TIC. LTD. STI | D28: CMTRL-XS-20260408-0001 | E28: 46150 | F28: MABS CT2010 | G28: 81 | H28: 2155 | I28: =G28*H28 -> 174555 | J28: 81 | K28: =G28-J28 -> 0 | L28: =长科收款!E70 -> 174555 | M28: =I28-L28 -> 0 | N28: =H28*J28-L28 -> 0 | O28: =N28*R28 -> 0 | P28: 0 | Q28: =P28*G28 -> 0 | R28: 6.82 | S28: 16441 | U28: =S28*G28 -> 1331721 | V28: 25公斤小包散装 | W28: FOB | X28: QINZHOU | Y28: 0 | Z28: 0 | AA28: =3*4500 -> 13500
A29: 杨玉赏 | B29: 100TT | C29: Polyram Plastic Industries LTD | D29: CMTRL-XS-20260409-0001 | E29: 46151 | F29: HIPS-CH612 | G29: 27 | H29: 1790 | I29: =G29*H29 -> 48330 | J29: 27 | K29: =G29-J29 -> 0 | L29: =长科收款!E20 -> 48283 | M29: =I29-L29 -> 47 | N29: =H29*J29-L29 -> 47 | O29: =N29*R29 -> 320.54 | P29: 30 | Q29: =P29*G29 -> 810 | R29: 6.82 | S29: 12203 | T29: 12200 | U29: =S29*G29 -> 329481 | V29: 25公斤小包带托盘 | W29: CIF | X29: HAIFA | Y29: =3700 -> 3700 | Z29: =50 -> 50 | AA29: 4500
A30: 毛晓翔 | B30: LC30 | C30: PT. Planet Chemicals | D30: CMTRL-XS-20260416-0001 | E30: 46158 | F30: SAN 900 | G30: 55 | H30: 1660 | I30: =G30*H30 -> 91300 | J30: =27.5+27.5 -> 55 | K30: =G30-J30 -> 0 | L30: =长科收款!E37 -> 91300 | M30: =I30-L30 -> 0 | N30: =H30*J30-L30 -> 0 | O30: =N30*R30 -> 0 | P30: 0 | Q30: =P30*G30 -> 0 | R30: 6.8 | S30: 12193 | T30: 11800 | U30: =S30*G30 -> 670615 | V30: 25公斤小包散装 | W30: CIF | X30: Jakarta | Y30: =2*1310 -> 2620 | Z30: =2*50 -> 100 | AA30: =2*5000 -> 10000
A31: 张晓敏 | B31: 100TT | C31: MOZZKULL INTERNATIONAL LIMITED | D31: CMTRL-XS-20260416-0002 | E31: 46158 | F31: MABS CT2010 | G31: 15 | H31: 2060 | I31: =G31*H31 -> 30900 | J31: 0 | K31: =G31-J31 -> 15 | L31: 0 | M31: =I31-L31 -> 30900 | N31: =H31*J31-L31 -> 0 | O31: =N31*R31 -> 0 | P31: 0 | Q31: =P31*G31 -> 0 | R31: 6.8 | S31: 15659 | U31: =S31*G31 -> 234885 | V31: 25公斤小包带托盘 | W31: EXW | X31: FACTORY | Y31: 0 | Z31: 0 | AA31: 0
A32: 毛晓翔 | B32: LC90 | C32: PRIME POLYMART PRIVATE LIMITED | D32: CMTRL-XS-20260429-0001 | E32: 46178 | F32: SAN 900 | G32: 27.5 | H32: 1610 | I32: =G32*H32 -> 44275 | J32: 27.5 | K32: =G32-J32 -> 0 | L32: =长科收款!E73 -> 44275 | M32: =I32-L32 -> 0 | N32: =H32*J32-L32 -> 0 | O32: =N32*R32 -> 0 | P32: 10 | Q32: =P32*G32 -> 275 | R32: 6.8229 | S32: 11794 | T32: 11600 | U32: =S32*G32 -> 324335 | V32: 25公斤小包散装 | W32: CIF | X32: MUNDRA | Y32: 1300 | Z32: 49 | AA32: 5000
A33: 陈诺 | B33: 100TT | C33: ZHI YUE XIAN (VIETNAM) CO., LTD | D33: CMTRL-XS-20260508-0001 | E33: 46181 | F33: MABS CT2010 | G33: 27.5 | H33: 1960 | I33: =G33*H33 -> 53900 | J33: 27.5 | K33: =G33-J33 -> 0 | L33: 53900 | M33: =I33-L33 -> 0 | N33: =H33*J33-L33 -> 0 | O33: =N33*R33 -> 0 | P33: 0 | Q33: =P33*G33 -> 0 | R33: 6.79 | S33: 15038 | T33: 15000 | U33: =S33*G33 -> 413545 | V33: 25公斤小包散装 | W33: EXW | X33: FACTORY | Y33: 0 | Z33: 0 | AA33: 0
A34: 陈诺 | B34: 100TT | C34: 鏵塑股份有限公司ULTRATEC PLASTICS CO.,LTD. | D34: CMTRL-XS-20260511-0001 | E34: 46188 | F34: HIPS-CH612 | G34: 15 | H34: 1540 | I34: =G34*H34 -> 23100 | J34: 15 | K34: =G34-J34 -> 0 | L34: =长科收款!E29 -> 23100 | M34: =I34-L34 -> 0 | N34: =H34*J34-L34 -> 0 | O34: =N34*R34 -> 0 | P34: 1 | Q34: =P34*G34 -> 15 | R34: 6.78 | S34: 11123 | T34: 11000 | U34: =S34*G34 -> 166845 | V34: 25公斤小包带托盘 | W34: CIF | X34: Keelung | Y34: 350 | Z34: 26 | AA34: 5000
A35: 张晓敏 | B35: 100TT | C35: 宁波鹿鸣供应链管理有限公司 | D35: CMTRL-XS-20260514-0004 | E35: 46187 | F35: SAN 900 | G35: 56 | H35: 12150 | I35: =G35*H35 -> 680400 | J35: 56 | K35: =G35-J35 -> 0 | L35: =长科收款!E27 -> 680400 | M35: =I35-L35 -> 0 | N35: =H35*J35-L35 -> 0 | O35: =N35*R35 -> 0 | P35: 0 | Q35: =P35*G35 -> 0 | R35: 1 | S35: 11910 | T35: 11900 | U35: =S35*G35 -> 666960 | V35: 25公斤小包散装 | W35: 送到 | X35: 连云港仓库 | AB35: 240
A36: 杨玉赏 | B36: 100TT | C36: Polyram Plastic Industries LTD | D36: CMTRL-XS-20260518-0001 | E36: 46191 | F36: HIPS-CH612 | G36: 27 | H36: 1700 | I36: =G36*H36 -> 45900 | J36: 27 | K36: =G36-J36 -> 0 | L36: =长科收款!E31 -> 45900 | M36: =I36-L36 -> 0 | N36: =H36*J36-L36 -> 0 | O36: =N36*R36 -> 0 | P36: 30 | Q36: =P36*G36 -> 810 | R36: 6.8 | S36: 11086 | T36: 10800 | U36: =S36*G36 -> 299322 | V36: 25公斤小包带托盘 | W36: CIF | X36: HAIFA | Y36: 5000 | Z36: 50 | AA36: 5000
A37: 张晓敏 | B37: 100TT | C37: Valutrans Investment Co., Limited | D37: CMTRL-XS-20260519-0001 | E37: 46244 | F37: 炭黑 N330 | G37: 540 | H37: 895 | I37: =G37*H37 -> 483300 | J37: =360+80+100 -> 540 | K37: =G37-J37 -> 0 | L37: =长科收款!E38+长科收款!E41+89500 -> 483300 | M37: =I37-L37 -> 0 | N37: =H37*J37-L37 -> 0 | O37: =N37*R37 -> 0 | P37: 0 | Q37: =P37*G37 -> 0 | R37: 6.79 | S37: 6077 | T37: 6000 | U37: =S37*G37 -> 3281580 | V37: 1000kg带托盘 | W37: EXW | X37: FACTORY | Y37: 0 | Z37: 0 | AA37: 0
A38: 张晓敏 | B38: 100TT | C38: Valutrans Investment Co., Limited | D38: CMTRL-XS-20260519-0001 | E38: 46244 | F38: 炭黑 N220 | G38: 0.002 | H38: 1055 | I38: =G38*H38 -> 2.11 | J38: 0.002 | K38: =G38-J38 -> 0 | L38: 2.11 | M38: =I38-L38 -> 0 | N38: =H38*J38-L38 -> 0 | O38: =N38*R38 -> 0 | P38: 0 | Q38: =P38*G38 -> 0 | S38: 7120 | T38: 7100 | U38: =S38*G38 -> 14.24 | W38: EXW | X38: FACTORY | Y38: 0 | Z38: 0 | AA38: 0
A39: 张晓敏 | B39: 100TT | C39: Valutrans Investment Co., Limited | D39: CMTRL-XS-20260520-0006 | E39: 46188 | F39: 炭黑 N330 | G39: 120 | H39: 1055 | I39: =G39*H39 -> 126600 | J39: 120 | K39: =G39-J39 -> 0 | L39: =长科收款!E35 -> 126600 | M39: =I39-L39 -> 0 | N39: =H39*J39-L39 -> 0 | O39: =N39*R39 -> 0 | P39: 0 | Q39: =P39*G39 -> 0 | R39: 6.79 | S39: 7163 | U39: =S39*G39 -> 859560 | V39: 1000kg带托盘 | W39: EXW | X39: FACTORY | Y39: 0 | Z39: 0 | AA39: 0
A40: 张晓敏 | B40: 100TT | C40: 广东探月者航空器材有限公司 | D40: GXCG-XS-20260520-0003 | E40: 46168 | F40: 炭黑 N326 | G40: 30.8 | H40: 6250 | I40: =G40*H40 -> 192500 | J40: 30.8 | K40: =G40-J40 -> 0 | L40: =长科收款!E30 -> 192500 | M40: =I40-L40 -> 0 | N40: =H40*J40-L40 -> 0 | O40: =N40*R40 -> 0 | P40: 0 | Q40: =P40*G40 -> 0 | R40: 1 | S40: 6100 | U40: =S40*G40 -> 187880 | V40: 25公斤小包带托盘 | W40: EXW | X40: FACTORY | Y40: 0 | Z40: 0 | AA40: 0
A41: 陶莹 | B41: 30/70TT | C41: ALPEX JOINT STOCK COMPANY | D41: CMTRL-XS-20260527-0001 | E41: 46200 | F41: SAN 900 | G41: 27.5 | H41: 1500 | I41: =G41*H41 -> 41250 | J41: 27.5 | K41: =G41-J41 -> 0 | L41: =长科收款!E33+长科收款!E36 -> 41250 | M41: =I41-L41 -> 0 | N41: =H41*J41-L41 -> 0 | O41: =N41*R41 -> 0 | P41: 0 | Q41: =P41*G41 -> 0 | R41: 6.77 | S41: 11100 | T41: 11000 | U41: =S41*G41 -> 305250 | V41: 25公斤小包散装 | W41: CIF | X41: Ho Chi Minh | Y41: 650 | Z41: 45 | AA41: 5000
A42: 毛晓翔 | B42: LC90 | C42: AMAZON CORPORATE SERVICES PVT. LTD. | D42: CMTRL-XS-20260629-0002 | E42: 46232 | F42: SAN 900 | G42: 52.5 | H42: 1360 | I42: =G42*H42 -> 71400 | J42: 52.5 | K42: =G42-J42 -> 0 | L42: 0 | M42: =I42-L42 -> 71400 | N42: =H42*J42-L42 -> 71400 | O42: =N42*R42 -> 484092 | P42: 0 | Q42: =P42*G42 -> 0 | R42: 6.78 | S42: 9576 | T42: 9200 | U42: =S42*G42 -> 502740 | V42: 25公斤小包散装 | W42: CIF | X42: MUNDRA, FINAL ICD DADRI | Y42: =2200*2 -> 4400 | Z42: =42*2 -> 84 | AA42: =6000*2 -> 12000
A43: 毛晓翔 | B43: LC90 | C43: AMAZON CORPORATE SERVICES PVT. LTD. | D43: CMTRL-XS-20260629-0002 | E43: 46232 | F43: HIPS-CH310 | G43: 1 | H43: 1340 | I43: =G43*H43 -> 1340 | J43: 1 | K43: =G43-J43 -> 0 | L43: 0 | M43: =I43-L43 -> 1340 | N43: =H43*J43-L43 -> 1340 | O43: =N43*R43 -> 9085.2 | P43: 0 | Q43: =P43*G43 -> 0 | R43: 6.78 | S43: 9423 | U43: =S43*G43 -> 9423 | V43: 25公斤小包散装 | W43: CIF | X43: MUNDRA, FINAL ICD DADRI
A44: 毛晓翔 | B44: LC90 | C44: AMAZON CORPORATE SERVICES PVT. LTD. | D44: CMTRL-XS-20260629-0002 | E44: 46232 | F44: HIPS-CH612 | G44: 1 | H44: 1320 | I44: =G44*H44 -> 1320 | J44: 1 | K44: =G44-J44 -> 0 | L44: 0 | M44: =I44-L44 -> 1320 | N44: =H44*J44-L44 -> 1320 | O44: =N44*R44 -> 8949.6 | P44: 0 | Q44: =P44*G44 -> 0 | R44: 6.78 | S44: 9270 | U44: =S44*G44 -> 9270 | V44: 25公斤小包散装 | W44: CIF | X44: MUNDRA, FINAL ICD DADRI
A45: 毛晓翔 | B45: LC90 | C45: AMAZON CORPORATE SERVICES PVT. LTD. | D45: CMTRL-XS-20260629-0002 | E45: 46232 | F45: MABS CT2010 | G45: 0.5 | H45: 2000 | I45: =G45*H45 -> 1000 | J45: 0.5 | K45: =G45-J45 -> 0 | L45: 0 | M45: =I45-L45 -> 1000 | N45: =H45*J45-L45 -> 1000 | O45: =N45*R45 -> 6780 | P45: 0 | Q45: =P45*G45 -> 0 | R45: 6.78 | S45: 14480 | U45: =S45*G45 -> 7240 | V45: 25公斤小包散装 | W45: CIF | X45: MUNDRA, FINAL ICD DADRI
A46: 陈诺 | B46: 100TT | C46: ZHI YUE XIAN (VIETNAM) CO., LTD | D46: CMTRL-XS-20260630-0003 | E46: 46233 | F46: MABS CT2010 | G46: 27.5 | H46: 1710 | I46: =G46*H46 -> 47025 | J46: 27.5 | K46: =G46-J46 -> 0 | L46: =长科收款!E42 -> 47025 | M46: =I46-L46 -> 0 | N46: =H46*J46-L46 -> 0 | O46: =N46*R46 -> 0 | P46: 0 | Q46: =P46*G46 -> 0 | R46: 6.77 | S46: 13081 | T46: 13000 | U46: =S46*G46 -> 359727.5 | V46: 25公斤小包散装 | W46: EXW | X46: FACTORY | Y46: 0 | Z46: 0 | AA46: 0
A47: 杨玉赏 | B47: 100TT | C47: PENTAPLAST SRL | D47: CMTRL-XS-20260630-0005 | E47: 46233 | F47: MABS CT2010 | G47: 15 | H47: 1800 | I47: =G47*H47 -> 27000 | J47: 15 | K47: =G47-J47 -> 0 | L47: =长科收款!E43 -> 27000 | M47: =I47-L47 -> 0 | N47: =H47*J47-L47 -> 0 | O47: =N47*R47 -> 0 | P47: 0 | Q47: =P47*G47 -> 0 | R47: 6.77 | S47: 13220 | T47: 13000 | U47: =S47*G47 -> 198300 | V47: 25公斤小包带托盘 | W47: FOB | X47: QINZHOU | Y47: 0 | Z47: 0 | AA47: 6000
A48: 杨玉赏 | B48: 100TT | C48: Polyram Plastic Industries LTD | D48: CMTRL-XS-20260709-0002 | E48: 46243 | F48: HIPS-CH612 | G48: 27 | H48: 1490 | I48: =G48*H48 -> 40230 | J48: 27 | K48: =G48-J48 -> 0 | L48: =长科收款!E48 -> 40230 | M48: =I48-L48 -> 0 | N48: =H48*J48-L48 -> 0 | O48: =N48*R48 -> 0 | P48: 30 | Q48: =P48*G48 -> 810 | R48: 6.78 | S48: 8687 | T48: 8500 | U48: =S48*G48 -> 234549 | V48: 25公斤小包带托盘 | W48: CIF | X48: HAIFA | Y48: 7600 | Z48: 50 | AA48: 5500
A49: 陶莹 | B49: 30/70TT | C49: ALPEX JOINT STOCK COMPANY | D49: CMTRL-XS-20260714-0010 | E49: 46248 | F49: SAN 900 | G49: 27.5 | H49: 1270 | I49: =G49*H49 -> 34925 | J49: 27.5 | K49: =G49-J49 -> 0 | L49: 34925 | M49: =I49-L49 -> 0 | N49: =H49*J49-L49 -> 0 | O49: =N49*R49 -> 0 | P49: 0 | Q49: =P49*G49 -> 0 | R49: 6.77 | S49: 9330 | U49: =S49*G49 -> 256575 | V49: 25公斤小包散装 | W49: CIF | X49: Ho Chi Minh | Y49: =700 -> 700 | Z49: 38 | AA49: 5000
A50: 张晓敏 | B50: 100TT | C50: BILLION ASCENT INDUSTRIAL LIMITED | D50: CMTRL-XS-20260715-0001 | E50: 46265 | F50: SAN 900 | G50: 108 | H50: 1240 | I50: =G50*H50 -> 133920 | J50: 108 | K50: =G50-J50 -> 0 | L50: =长科收款!E52+长科收款!E56 -> 133920 | M50: =I50-L50 -> 0 | N50: =H50*J50-L50 -> 0 | O50: =N50*R50 -> 0 | P50: 0 | Q50: =P50*G50 -> 0 | R50: 6.77 | S50: 9319 | U50: =S50*G50 -> 1006452 | V50: 25公斤小包散装 | W50: FOB | X50: QINZHOU | Y50: 0 | Z50: 0 | AA50: =4*9319 -> 37276
A51: 张晓敏 | B51: 100TT | C51: 宁波鹿鸣供应链管理有限公司 | D51: CMTRL-XS-20260715-0003 | E51: 46249 | F51: SAN 900 | G51: 42 | H51: 9720 | I51: =G51*H51 -> 408240 | J51: 42 | K51: =G51-J51 -> 0 | L51: =长科收款!E45 -> 408240 | M51: =I51-L51 -> 0 | N51: =H51*J51-L51 -> 0 | O51: =N51*R51 -> 0 | P51: 0 | Q51: =P51*G51 -> 0 | R51: 1 | S51: 9300 | U51: =S51*G51 -> 390600 | V51: 25公斤小包散装 | W51: 送到 | X51: 连云港仓库 | AB51: =420*G51 -> 17640
A52: 张晓敏 | B52: 100TT | C52: BILLION ASCENT INDUSTRIAL LIMITED | D52: CMTRL-XS-20260716-0001 | E52: 46265 | F52: SAN 900 | G52: 27 | H52: 1245 | I52: =G52*H52 -> 33615 | J52: 27 | K52: =G52-J52 -> 0 | L52: =长科收款!E57 -> 33615 | M52: =I52-L52 -> 0 | N52: =H52*J52-L52 -> 0 | O52: =N52*R52 -> 0 | P52: 0 | Q52: =P52*G52 -> 0 | R52: 6.755 | S52: 9336 | U52: =S52*G52 -> 252072 | V52: 25公斤小包散装 | W52: FOB | X52: QINZHOU | Y52: 0 | Z52: 0 | AA52: 4500
A53: 毛晓翔 | B53: LC90 | C53: BOMBAY PLASTIC UDYOG | D53: CMTRL-XS-20260723-0001 | E53: 46257 | F53: SAN 2800 | G53: 14 | H53: 1320 | I53: =G53*H53 -> 18480 | J53: 14 | K53: =G53-J53 -> 0 | L53: 0 | M53: =I53-L53 -> 18480 | N53: =H53*J53-L53 -> 18480 | O53: =N53*R53 -> 124808.38 | P53: 10 | Q53: =P53*G53 -> 140 | R53: 6.7537 | S53: 9299 | U53: =S53*G53 -> 130186 | V53: 25公斤小包散装 | W53: CIF | X53: MUNDRA | Y53: =1850*2 -> 3700 | Z53: =40*2 -> 80 | AA53: =5000*2 -> 10000
A54: 毛晓翔 | B54: LC90 | C54: BOMBAY PLASTIC UDYOG | D54: CMTRL-XS-20260723-0001 | E54: 46257 | F54: SAN 4800 | G54: 13.5 | H54: 1320 | I54: =G54*H54 -> 17820 | J54: 13.5 | K54: =G54-J54 -> 0 | L54: 0 | M54: =I54-L54 -> 17820 | N54: =H54*J54-L54 -> 17820 | O54: =N54*R54 -> 120350.93 | P54: 10 | Q54: =P54*G54 -> 135 | R54: 6.7537 | S54: 9299 | U54: =S54*G54 -> 125536.5 | V54: 25公斤小包散装 | W54: CIF | X54: MUNDRA
A55: 毛晓翔 | B55: LC90 | C55: BOMBAY PLASTIC UDYOG | D55: CMTRL-XS-20260723-0001 | E55: 46257 | F55: HIPS-CH612 | G55: 27.5 | H55: 1350 | I55: =G55*H55 -> 37125 | J55: 27.5 | K55: =G55-J55 -> 0 | L55: 0 | M55: =I55-L55 -> 37125 | N55: =H55*J55-L55 -> 37125 | O55: =N55*R55 -> 250731.11 | P55: 5 | Q55: =P55*G55 -> 137.5 | R55: 6.7537 | S55: 9299 | U55: =S55*G55 -> 255722.5 | V55: 25公斤小包散装 | W55: CIF | X55: MUNDRA
A56: 毛晓翔 | B56: LC90 | C56: Synergy Industriez | D56: CMTRL-XS-20260723-0004 | E56: 46257 | F56: SAN 2800 | G56: 12.5 | H56: 1320 | I56: =G56*H56 -> 16500 | J56: 12.5 | K56: =G56-J56 -> 0 | L56: 0 | M56: =I56-L56 -> 16500 | N56: =H56*J56-L56 -> 16500 | O56: =N56*R56 -> 111436.05 | P56: 10 | Q56: =P56*G56 -> 125 | R56: 6.7537 | S56: 9299 | U56: =S56*G56 -> 116237.5 | V56: 25公斤小包散装 | W56: CIF | X56: NHAVA SHEVA | Y56: =1850*3 -> 5550 | Z56: =40*3 -> 120 | AA56: =5000*3 -> 15000
A57: 毛晓翔 | B57: LC90 | C57: Synergy Industriez | D57: CMTRL-XS-20260723-0004 | E57: 46257 | F57: SAN 4800 | G57: 15 | H57: 1320 | I57: =G57*H57 -> 19800 | J57: 15 | K57: =G57-J57 -> 0 | L57: 0 | M57: =I57-L57 -> 19800 | N57: =H57*J57-L57 -> 19800 | O57: =N57*R57 -> 133723.26 | P57: 10 | Q57: =P57*G57 -> 150 | R57: 6.7537 | S57: 9299 | U57: =S57*G57 -> 139485 | V57: 25公斤小包散装 | W57: CIF | X57: NHAVA SHEVA
A58: 毛晓翔 | B58: LC90 | C58: Synergy Industriez | D58: CMTRL-XS-20260723-0004 | E58: 46257 | F58: HIPS-CH612 | G58: 55 | H58: 1350 | I58: =G58*H58 -> 74250 | J58: 55 | K58: =G58-J58 -> 0 | L58: 0 | M58: =I58-L58 -> 74250 | N58: =H58*J58-L58 -> 74250 | O58: =N58*R58 -> 501462.22 | P58: 5 | Q58: =P58*G58 -> 275 | R58: 6.7537 | S58: 9299 | U58: =S58*G58 -> 511445 | V58: 25公斤小包散装 | W58: CIF | X58: NHAVA SHEVA
A59: 毛晓翔 | B59: LC90 | C59: PRIME POLYMART PRIVATE LIMITED | D59: CMTRL-XS-20260731-0001 | E59: 46265 | F59: SAN 900 | G59: 27.5 | H59: 1350 | I59: =G59*H59 -> 37125 | J59: 27.5 | K59: =G59-J59 -> 0 | L59: 0 | M59: =I59-L59 -> 37125 | N59: =H59*J59-L59 -> 37125 | O59: =N59*R59 -> 250211.36 | P59: 10 | Q59: =P59*G59 -> 275 | R59: 6.7397 | S59: 9508 | U59: =S59*G59 -> 261470 | V59: 25公斤小包散装 | W59: CIF | X59: MUNDRA | Y59: 1850 | Z59: 41 | AA59: 5000
A60: 毛晓翔 | B60: 20/80TT | C60: AMAZON CORPORATE SERVICES PVT. LTD. | D60: CMTRL-XS-20260731-0005 | E60: 46265 | F60: SAN 900 | G60: 27.5 | H60: 1300 | I60: =G60*H60 -> 35750 | J60: 27.5 | K60: =G60-J60 -> 0 | L60: =长科收款!E53+长科收款!E74 -> 35877.5 | M60: =I60-L60 -> -127.5 | N60: =H60*J60-L60 -> -127.5 | O60: =N60*R60 -> -859.31175 | P60: 本合同申请抵扣25年闭环合同，佣金共计1712.5美元，长科25年外销合同尾号（1030-0004，1111-0007，1216-0001），抵扣后本合同总金额107737.50美金。 | R60: 6.7397 | S60: 9153 | U60: =S60*G60 -> 251707.5 | V60: 25公斤小包散装 | W60: CIF | X60: MUNDRA, FINAL ICD DADRI | Y60: =2000*3 -> 6000 | Z60: =40*3 -> 120 | AA60: =5000*3 -> 15000
A61: 毛晓翔 | B61: 20/80TT | C61: AMAZON CORPORATE SERVICES PVT. LTD. | D61: CMTRL-XS-20260731-0005 | E61: 46265 | F61: SAN 4800 | G61: 27.5 | H61: 1340 | I61: =G61*H61 -> 36850 | J61: 27.5 | K61: =G61-J61 -> 0 | L61: =长科收款!E54+长科收款!E75 -> 35877.5 | M61: =I61-L61 -> 972.5 | N61: =H61*J61-L61 -> 972.5 | O61: =N61*R61 -> 6554.3583 | R61: 6.7397 | S61: 9458 | U61: =S61*G61 -> 260095 | V61: 25公斤小包散装 | W61: CIF | X61: MUNDRA, FINAL ICD DADRI
A62: 毛晓翔 | B62: 20/80TT | C62: AMAZON CORPORATE SERVICES PVT. LTD. | D62: CMTRL-XS-20260731-0005 | E62: 46265 | F62: HIPS-CH612 | G62: 27.5 | H62: 1340 | I62: =G62*H62 -> 36850 | J62: 27.5 | K62: =G62-J62 -> 0 | L62: =长科收款!E55+长科收款!E75 -> 35877.5 | M62: =I62-L62 -> 972.5 | N62: =H62*J62-L62 -> 972.5 | O62: =N62*R62 -> 6554.3583 | R62: 6.7397 | S62: 9458 | U62: =S62*G62 -> 260095 | V62: 25公斤小包散装 | W62: CIF | X62: MUNDRA, FINAL ICD DADRI
A63: 刘丝雨 | B63: LC30 | C63: VRIDDHI PETROCHEMICALS | D63: CMTRL-20260804-001 | E63: 46269 | F63: SAN 900 | G63: 27.5 | H63: 1360 | I63: =G63*H63 -> 37400 | J63: =长科出库!E194 -> 27.5 | K63: =G63-J63 -> 0 | L63: 0 | M63: =I63-L63 -> 37400 | N63: =H63*J63-L63 -> 37400 | O63: =N63*R63 -> 252076 | P63: 0 | Q63: =P63*G63 -> 0 | R63: 6.74 | S63: 9329 | U63: =S63*G63 -> 256547.5 | V63: 25公斤小包散装 | W63: CIF | X63: MUNDRA | Y63: 2950 | Z63: 40 | AA63: 5000
A64: 毛晓翔 | B64: LC90 | C64: PRIME POLYMART PRIVATE LIMITED | D64: CMTRL-20260805-002 | E64: 46270 | F64: SAN 900 | G64: 27.5 | H64: 1350 | I64: =G64*H64 -> 37125 | J64: 27.5 | K64: =G64-J64 -> 0 | L64: 0 | M64: =I64-L64 -> 37125 | N64: =H64*J64-L64 -> 37125 | O64: =N64*R64 -> 250211.36 | P64: 10 | Q64: =P64*G64 -> 275 | R64: 6.7397 | S64: 9430 | U64: =S64*G64 -> 259325 | V64: 25公斤小包散装 | W64: CIF | X64: MUNDRA | Y64: 2130 | Z64: 41 | AA64: 5000
A65: 张晓敏 | B65: 100TT | C65: FIREMAX(CAMBODIA) TIRES CO.. LTD | D65: CMTRL-20260806-003 | E65: 46295 | F65: 炭黑 N660 | G65: 420 | H65: 1010 | I65: =G65*H65 -> 424200 | J65: =100+140+180 -> 420 | K65: =G65-J65 -> 0 | L65: =长科收款!E58 -> 424200 | M65: =I65-L65 -> 0 | N65: =H65*J65-L65 -> 0 | O65: =N65*R65 -> 0 | P65: 0 | Q65: =P65*G65 -> 0 | R65: 6.735 | S65: 6407 | U65: =S65*G65 -> 2690940 | V65: 1000kg带托盘 | W65: CFR | X65: PHUOC AN/ HOCHIMINH | Y65: =21*580 -> 12180 | Z65: 0 | AA65: =21*4000 -> 84000
A66: 毛晓翔 | B66: LC90 | C66: D.R.PLASTO TECH PRIVATE LIMITED | D66: CMTRL-20260811-004 | E66: 46276 | F66: HIPS-CH612 | G66: 110 | H66: 1340 | I66: =G66*H66 -> 147400 | J66: 110 | K66: =G66-J66 -> 0 | L66: 0 | M66: =I66-L66 -> 147400 | N66: =H66*J66-L66 -> 147400 | O66: =N66*R66 -> 992665.3 | P66: 5 | Q66: =P66*G66 -> 550 | R66: 6.7345 | S66: 9403 | U66: =S66*G66 -> 1034330 | V66: 25公斤小包散装 | W66: CIF | X66: MUNDRA | Y66: =4*2050 -> 8200 | Z66: =4*41 -> 164 | AA66: =4*5000 -> 20000
A67: 毛晓翔 | B67: LC90 | C67: SUNPLAST ELECTRONICS PVT.LTD | D67: CMTRL-20260811-005 | E67: 46276 | F67: HIPS-CH612 | G67: 55 | H67: 1360 | I67: =G67*H67 -> 74800 | J67: 55 | K67: =G67-J67 -> 0 | L67: 0 | M67: =I67-L67 -> 74800 | N67: =H67*J67-L67 -> 74800 | O67: =N67*R67 -> 503740.6 | P67: 10 | Q67: =P67*G67 -> 550 | R67: 6.7345 | S67: 9521 | U67: =S67*G67 -> 523655 | V67: 25公斤小包散装 | W67: CIF | X67: MUNDRA | Y67: =2*2050 -> 4100 | Z67: =2*41 -> 82 | AA67: =2*5000 -> 10000
A68: 毛晓翔 | B68: 20/80TT | C68: AMAZON CORPORATE SERVICES PVT. LTD. | D68: CMTRL-20260811-006 | E68: 46276 | F68: SAN 900 | G68: 27.5 | H68: 1340 | I68: =G68*H68 -> 36850 | J68: 27.5 | K68: =G68-J68 -> 0 | L68: =长科收款!E59+长科收款!E85 -> 36772 | M68: =I68-L68 -> 78 | N68: =H68*J68-L68 -> 78 | O68: =N68*R68 -> 525.291 | P68: 0 | Q68: =P68*G68 -> 0 | R68: 6.7345 | S68: 9409 | U68: =S68*G68 -> 258747.5 | V68: 25公斤小包散装 | W68: CIF | X68: MUNDRA, FINAL ICD DADRI | Y68: =2150*2 -> 4300 | Z68: =41*2 -> 82 | AA68: =5000*2 -> 10000
A69: 毛晓翔 | B69: 20/80TT | C69: AMAZON CORPORATE SERVICES PVT. LTD. | D69: CMTRL-20260811-006 | E69: 46276 | F69: SAN 4800 | G69: 27.5 | H69: 1290 | I69: =G69*H69 -> 35475 | J69: 27.5 | K69: =G69-J69 -> 0 | L69: =长科收款!E60+长科收款!E84 -> 35397 | M69: =I69-L69 -> 78 | N69: =H69*J69-L69 -> 78 | O69: =N69*R69 -> 525.291 | P69: 0 | Q69: =P69*G69 -> 0 | R69: 6.7345 | S69: 9028 | U69: =S69*G69 -> 248270 | V69: 25公斤小包散装 | W69: CIF | X69: MUNDRA, FINAL ICD DADRI
A70: 张晓敏 | B70: 100TT | C70: BILLION ASCENT INDUSTRIAL LIMITED | D70: CMTRL-20260812-007 | E70: 46277 | F70: SAN 900 | G70: 108 | H70: 1244 | I70: =G70*H70 -> 134352 | J70: 108 | K70: =G70-J70 -> 0 | L70: =长科收款!E63 -> 134352 | M70: =I70-L70 -> 0 | N70: =H70*J70-L70 -> 0 | O70: =N70*R70 -> 0 | P70: 0 | Q70: =P70*G70 -> 0 | R70: 6.7345 | S70: 9300 | U70: =S70*G70 -> 1004400 | V70: 25公斤小包散装 | W70: FOB | X70: QINZHOU | Y70: 0 | Z70: =0 -> 0 | AA70: =4*4500 -> 18000
A71: 张晓敏 | B71: 100TT | C71: BILLION ASCENT INDUSTRIAL LIMITED | D71: CMTRL-20260812-008 | E71: 46277 | F71: SAN 900 | G71: 108 | H71: 1244 | I71: =G71*H71 -> 134352 | J71: 108 | K71: =G71-J71 -> 0 | L71: =长科收款!E67 -> 134352 | M71: =I71-L71 -> 0 | N71: =H71*J71-L71 -> 0 | O71: =N71*R71 -> 0 | P71: 0 | Q71: =P71*G71 -> 0 | R71: 7.7345 | S71: 9301 | U71: =S71*G71 -> 1004508 | V71: 25公斤小包散装 | W71: FOB | X71: QINZHOU | Y71: 0 | Z71: =0 -> 0 | AA71: =4*4500 -> 18000
A72: 刘丝雨 | B72: 30/70TT | C72: NJ POWER LLP | D72: CMTRL-20260812-009 | E72: 46277 | F72: SAN 900 | G72: 27.5 | H72: 1375 | I72: =G72*H72 -> 37812.5 | J72: 27.5 | K72: =G72-J72 -> 0 | L72: =长科收款!E62+长科收款!E80 -> 37812.5 | M72: =I72-L72 -> 0 | N72: =H72*J72-L72 -> 0 | O72: =N72*R72 -> 0 | P72: 0 | Q72: =P72*G72 -> 0 | R72: 6.73 | S72: 9651 | U72: =S72*G72 -> 265402.5 | V72: 25公斤小包散装 | W72: CIF | X72: MUNDRA | Y72: 2200 | Z72: 40 | AA72: 5000
A73: 毛晓翔 | B73: LC90 | C73: PT POLYMERS INDIA LLP | D73: CMTRL-20260814-010 | E73: 46279 | F73: SAN 4800 | G73: 84 | H73: 1325 | I73: =G73*H73 -> 111300 | J73: 84 | K73: =G73-J73 -> 0 | L73: 0 | M73: =I73-L73 -> 111300 | N73: =H73*J73-L73 -> 111300 | O73: =N73*R73 -> 749549.85 | P73: 5 | Q73: =P73*G73 -> 420 | R73: 6.7345 | S73: 9220 | U73: =S73*G73 -> 774480 | V73: 800kg带托盘 | W73: CIF | X73: MUNDRA | Y73: =3*2300 -> 6900 | Z73: =3*40 -> 120 | AA73: =3*5000 -> 15000
A74: 毛晓翔 | B74: 20 TT 80 LC90 | C74: PT POLYMERS INDIA LLP | D74: CMTRL-20260814-011 | E74: 46279 | F74: SAN 4800 | G74: 84 | H74: 1325 | I74: =G74*H74 -> 111300 | J74: 84 | K74: =G74-J74 -> 0 | L74: 0 | M74: =I74-L74 -> 111300 | N74: =H74*J74-L74 -> 111300 | O74: =N74*R74 -> 749549.85 | P74: 5 | Q74: =P74*G74 -> 420 | R74: 6.7345 | S74: 9220 | U74: =S74*G74 -> 774480 | V74: 800kg带托盘 | W74: CIF | X74: MUNDRA | Y74: =3*2300 -> 6900 | Z74: =3*40 -> 120 | AA74: =3*5000 -> 15000
A75: 毛晓翔 | B75: LC90 | C75: DIRCO POLYMERS PRIVATE LIMITD | D75: CMTRL-20260814-012 | E75: 46279 | F75: SAN 4800 | G75: 165 | H75: 1325 | I75: =G75*H75 -> 218625 | J75: =137.5+27.5 -> 165 | K75: =G75-J75 -> 0 | L75: 0 | M75: =I75-L75 -> 218625 | N75: =H75*J75-L75 -> 218625 | O75: =N75*R75 -> 1472330.1 | P75: 5 | Q75: =P75*G75 -> 825 | R75: 6.7345 | S75: 9220 | U75: =S75*G75 -> 1521300 | V75: 25公斤小包散装 | W75: CIF | X75: MUNDRA | Y75: =6*2300 -> 13800 | Z75: =6*40 -> 240 | AA75: =6*5000 -> 30000
A76: 刘丝雨 | B76: 30/70TT | C76: VINAYAK AGNIPEAK LLP | D76: CMTRL-20260819-013 | E76: 46279 | F76: SAN 900 | G76: 27.5 | H76: 1285 | I76: =G76*H76 -> 35337.5 | J76: 27.5 | K76: =G76-J76 -> 0 | L76: =长科收款!E66 -> 10601.25 | M76: =I76-L76 -> 24736.25 | N76: =H76*J76-L76 -> 24736.25 | O76: =N76*R76 -> 166435.38 | P76: 0 | Q76: =P76*G76 -> 0 | R76: 6.7284 | S76: 9566 | U76: =S76*G76 -> 263065 | V76: 25公斤小包散装 | W76: FOB | X76: QINZHOU | Y76: 0 | Z76: =0 -> 0 | AA76: 5500
A77: 张晓敏 | B77: 100TT | C77: FIREMAX(CAMBODIA) TIRES CO.. LTD | D77: CMTRL-20260820-014 | E77: 46295 | F77: 炭黑 N660 | G77: 200 | H77: 1040 | I77: =G77*H77 -> 208000 | J77: 200 | K77: =G77-J77 -> 0 | L77: =长科收款!E69 -> 208000 | M77: =I77-L77 -> 0 | N77: =H77*J77-L77 -> 0 | O77: =N77*R77 -> 0 | P77: 0 | Q77: =P77*G77 -> 0 | R77: 6.725 | S77: 6614 | U77: =S77*G77 -> 1322800 | V77: 1000kg带托盘 | W77: CIF | X77: Ho Chi Minh | Y77: =580*10 -> 5800 | Z77: =0 -> 0 | AA77: =4000*10 -> 40000
A78: 张晓敏 | B78: 100TT | C78: FIREMAX(CAMBODIA) TIRES CO.. LTD | D78: CMTRL-20260825-015 | E78: 46295 | F78: 炭黑 N330 | G78: 500 | H78: 1150 | I78: =G78*H78 -> 575000 | J78: 500 | K78: =G78-J78 -> 0 | L78: =长科收款!E72 -> 1150000 | M78: =I78-L78 -> -575000 | N78: =H78*J78-L78 -> -575000 | O78: =N78*R78 -> -3858250 | P78: 0 | Q78: =P78*G78 -> 0 | R78: 6.71 | S78: 7313 | U78: =S78*G78 -> 3656500 | V78: 1000kg带托盘 | W78: CIF | X78: Ho Chi Minh | Y78: =580*500 -> 290000 | AA78: =4000*500 -> 2000000
A79: 张晓敏 | B79: 100TT | C79: FIREMAX(CAMBODIA) TIRES CO.. LTD | D79: CMTRL-20260825-015 | E79: 46295 | F79: 炭黑 N326 | G79: 500 | H79: 1150 | I79: =G79*H79 -> 575000 | J79: 500 | K79: =G79-J79 -> 0 | L79: =长科收款!E72 -> 1150000 | M79: =I79-L79 -> -575000 | N79: =H79*J79-L79 -> -575000 | O79: =N79*R79 -> -3858250 | P79: 0 | Q79: =P79*G79 -> 0 | R79: 6.71 | S79: 7313 | U79: =S79*G79 -> 3656500 | V79: 1000kg带托盘 | W79: CIF | X79: Ho Chi Minh
A80: 毛晓翔 | B80: LC90 | C80: D.R.PLASTO TECH PRIVATE LIMITED | D80: CMTRL-20260825-016 | E80: 46290 | F80: SAN 2800 | G80: 82.5 | H80: 1380 | I80: =G80*H80 -> 113850 | J80: 82.5 | K80: =G80-J80 -> 0 | L80: 0 | M80: =I80-L80 -> 113850 | N80: =H80*J80-L80 -> 113850 | O80: =N80*R80 -> 763933.5 | P80: 5 | Q80: =P80*G80 -> 412.5 | R80: 6.71 | S80: 9265 | U80: =S80*G80 -> 764362.5 | V80: 25公斤小包散装 | W80: CIF | X80: MUNDRA | Y80: =3550*3 -> 10650 | Z80: =41*3 -> 123 | AA80: =5000*3 -> 15000
A81: 毛晓翔 | B81: LC90 | C81: D.R.PLASTO TECH PRIVATE LIMITED | D81: CMTRL-20260825-016 | E81: 46290 | F81: SAN 4800 | G81: 27.5 | H81: 1380 | I81: =G81*H81 -> 37950 | J81: 27.5 | K81: =G81-J81 -> 0 | L81: 0 | M81: =I81-L81 -> 37950 | N81: =H81*J81-L81 -> 37950 | O81: =N81*R81 -> 254644.5 | P81: 5 | Q81: =P81*G81 -> 137.5 | R81: 6.71 | S81: 9265 | U81: =S81*G81 -> 254787.5 | V81: 25公斤小包散装 | W81: CIF | X81: MUNDRA | Y81: =3550 -> 3550 | Z81: 41 | AA81: 5000
A82: 毛晓翔 | B82: LC90 | C82: Synergy Industries | D82: CMTRL-20260825-017 | E82: 46290 | F82: SAN 2800 | G82: 27.5 | H82: 1380 | I82: =G82*H82 -> 37950 | J82: 27.5 | K82: =G82-J82 -> 0 | L82: 0 | M82: =I82-L82 -> 37950 | N82: =H82*J82-L82 -> 37950 | O82: =N82*R82 -> 254644.5 | P82: 5 | Q82: =P82*G82 -> 137.5 | R82: 6.71 | S82: 9265 | U82: =S82*G82 -> 254787.5 | V82: 25公斤小包散装 | W82: CIF | X82: NHAVA SHEVA | Y82: =3550 -> 3550 | Z82: 41 | AA82: 5000
A83: 毛晓翔 | B83: LC90 | C83: Synergy Industriez | D83: CMTRL-20260825-017 | E83: 46290 | F83: SAN 4800 | G83: 27.5 | H83: 1380 | I83: =G83*H83 -> 37950 | J83: 27.5 | K83: =G83-J83 -> 0 | L83: 0 | M83: =I83-L83 -> 37950 | N83: =H83*J83-L83 -> 37950 | O83: =N83*R83 -> 254644.5 | P83: 5 | Q83: =P83*G83 -> 137.5 | R83: 6.71 | S83: 9265 | U83: =S83*G83 -> 254787.5 | V83: 25公斤小包散装 | W83: CIF | X83: NHAVA SHEVA | Y83: =3550 -> 3550 | Z83: 41 | AA83: 5000
A84: 毛晓翔 | B84: LC90 | C84: JJ PLASTALLOY PRIVATE LIMITED | D84: CMTRL-20260825-018 | E84: 46290 | F84: SAN 2800 | G84: 27 | H84: 1380 | I84: =G84*H84 -> 37260 | J84: 27 | K84: =G84-J84 -> 0 | L84: 0 | M84: =I84-L84 -> 37260 | N84: =H84*J84-L84 -> 37260 | O84: =N84*R84 -> 250014.6 | P84: 5 | Q84: =P84*G84 -> 135 | R84: 6.71 | S84: 9265 | U84: =S84*G84 -> 250155 | V84: 25公斤小包散装 | W84: CIF | X84: NHAVA SHEVA
A85: 张晓敏 | B85: 100TT | C85: 宁波鹿鸣供应链管理有限公司 | D85: CMTRL-XS-20260826-0003 | E85: 46291 | F85: SAN 900 | G85: 64 | H85: 10100 | I85: =G85*H85 -> 646400 | J85: 64 | K85: =G85-J85 -> 0 | L85: =长科收款!E71 -> 646400 | M85: =I85-L85 -> 0 | N85: =H85*J85-L85 -> 0 | O85: =N85*R85 -> 0 | P85: 0 | Q85: =P85*G85 -> 0 | R85: 1 | S85: 9690 | U85: =S85*G85 -> 620160 | V85: 25公斤小包散装 | W85: 送到 | X85: 连云港仓库 | Y85: 410 | Z85: 0 | AA85: 0
A86: 刘丝雨 | B86: 30/70TT | C86: NJ POWER LLP | D86: CMTRL-20260828-019 | E86: 46293 | F86: SAN 900 | G86: 27.5 | H86: 1350 | I86: =G86*H86 -> 37125 | J86: 27.5 | K86: =G86-J86 -> 0 | L86: =长科收款!E76+长科收款!E89 -> 37087 | M86: =I86-L86 -> 38 | N86: =H86*J86-L86 -> 38 | O86: =N86*R86 -> 254.98 | P86: 10 | Q86: =P86*G86 -> 275 | R86: 6.71 | S86: 9950 | U86: =S86*G86 -> 273625 | V86: 25公斤小包散装 | W86: FOB | X86: QINZHOU | Y86: 0 | Z86: 0 | AA86: 6000
A87: 刘丝雨 | B87: 30/70TT | C87: VINAYAK AGNIPEAK LLP | D87: CMTRL-20260828-020 | E87: 46293 | F87: SAN 900 | G87: 27.5 | H87: 1350 | I87: =G87*H87 -> 37125 | J87: 27.5 | K87: =G87-J87 -> 0 | L87: =长科收款!E78+长科收款!E87 -> 37125 | M87: =I87-L87 -> 0 | N87: =H87*J87-L87 -> 0 | O87: =N87*R87 -> 0 | P87: 10 | Q87: =P87*G87 -> 275 | R87: 6.71 | S87: 9950 | U87: =S87*G87 -> 273625 | V87: 25公斤小包散装 | W87: FOB | X87: QINZHOU | Y87: 0 | Z87: 0 | AA87: 6000
A88: 毛晓翔 | B88: 100TT | C88: 惠州市尹纯环保科技有限公司 | D88: CMTRL-XS-20260907-0001 | E88: 46285 | F88: MABS CT2010 | G88: 1 | H88: 16700 | I88: =G88*H88 -> 16700 | J88: 1 | K88: =G88-J88 -> 0 | L88: =长科收款!E77 -> 16700 | M88: =I88-L88 -> 0 | N88: =H88*J88-L88 -> 0 | O88: =N88*R88 -> 0 | P88: 0 | Q88: =P88*G88 -> 0 | R88: 1 | S88: 16200 | U88: =S88*G88 -> 16200 | V88: 25公斤小包带托盘 | W88: 送到 | X88: 惠州 | Y88: 0 | Z88: 0 | AA88: 500
A89: 刘丝雨 | B89: LC30 | C89: VRIDDHI PETROCHEMICALS | D89: CMTRL-20260922-021 | E89: 46317 | F89: SAN 900 | G89: 27.5 | H89: 1640 | I89: =G89*H89 -> 45100 | J89: 0 | K89: =G89-J89 -> 27.5 | L89: 0 | M89: =I89-L89 -> 45100 | N89: =H89*J89-L89 -> 0 | O89: =N89*R89 -> 0 | P89: 10 | Q89: =P89*G89 -> 275 | R89: 6.6845 | S89: 11147 | T89: 11050 | U89: =S89*G89 -> 306542.5 | V89: 25公斤小包散装 | W89: CIF | X89: MUNDRA | Y89: 3550 | Z89: 60 | AA89: 5000
A90: 毛晓翔 | B90: 20/80TT | C90: Synergy Industriez | D90: CMTRL-20260924-022 | E90: 46319 | F90: SAN 4800 | G90: 55 | H90: 1560 | I90: =G90*H90 -> 85800 | J90: 55 | K90: =G90-J90 -> 0 | L90: =长科收款!E81 -> 51480 | M90: =I90-L90 -> 34320 | N90: =H90*J90-L90 -> 34320 | O90: =N90*R90 -> 229841.04 | P90: 10 | Q90: =P90*G90 -> 550 | R90: 6.697 | S90: 10525 | U90: =S90*G90 -> 578875 | V90: 25公斤小包散装 | W90: CIF | X90: NHAVA SHEVA | Y90: =3700*2 -> 7400 | Z90: =48*2 -> 96 | AA90: =5000*2 -> 10000
A91: 毛晓翔 | B91: 20/80TT | C91: Synergy Industriez | D91: CMTRL-20260924-022 | E91: 46319 | F91: HIPS-CH612 | G91: 110 | H91: 1560 | I91: =G91*H91 -> 171600 | J91: 110 | K91: =G91-J91 -> 0 | L91: 0 | M91: =I91-L91 -> 171600 | N91: =H91*J91-L91 -> 171600 | O91: =N91*R91 -> 1149205.2 | P91: 10 | Q91: =P91*G91 -> 1100 | R91: 6.697 | S91: 10525 | U91: =S91*G91 -> 1157750 | V91: 25公斤小包散装 | W91: CIF | X91: NHAVA SHEVA | Y91: =3700*4 -> 14800 | Z91: =48*4 -> 192 | AA91: =5000*4 -> 20000
A92: 毛晓翔 | B92: 20/80TT | C92: DIRCO POLYMERS PVT LTD | D92: CMTRL-20260930-023 | E92: 46326 | F92: SAN 4800 | G92: 220 | H92: 1540 | I92: =G92*H92 -> 338800 | J92: =110+110 -> 220 | K92: =G92-J92 -> 0 | L92: 135520 | M92: =I92-L92 -> 203280 | N92: =H92*J92-L92 -> 203280 | O92: =N92*R92 -> 1361386.5 | P92: 5 | Q92: =P92*G92 -> 1100 | R92: 6.6971 | S92: 10426 | T92: 10300 | U92: =S92*G92 -> 2293720 | V92: 25公斤小包散装 | W92: CIF | X92: MUNDRA | Y92: =8*3700 -> 29600 | Z92: =8*47 -> 376 | AA92: =8*4500 -> 36000
A93: 毛晓翔 | B93: 20/80TT | C93: DIRCO POLYMERS PVT LTD | D93: CMTRL-20260930-023 | E93: 46326 | F93: HIPS-CH612 | G93: 220 | H93: 1540 | I93: =G93*H93 -> 338800 | J93: =55+82.5+82.5 -> 220 | K93: =G93-J93 -> 0 | L93: 0 | M93: =I93-L93 -> 338800 | N93: =H93*J93-L93 -> 338800 | O93: =N93*R93 -> 2268977.5 | P93: 5 | Q93: =P93*G93 -> 1100 | R93: 6.6971 | S93: 10426 | T93: 10500 | U93: =S93*G93 -> 2293720 | V93: 25公斤小包散装 | W93: CIF | X93: MUNDRA | Y93: =8*3700 -> 29600 | Z93: =8*47 -> 376 | AA93: =8*4500 -> 36000
A94: 毛晓翔 | B94: LC90 | C94: SUNPLAST ELECTRONICS PRIVATE LIMITED | D94: CMTRL-20260930-024 | E94: 46326 | F94: SAN 2800 | G94: 13.5 | H94: 1540 | I94: =G94*H94 -> 20790 | J94: 13.5 | K94: =G94-J94 -> 0 | L94: 0 | M94: =I94-L94 -> 20790 | N94: =H94*J94-L94 -> 20790 | O94: =N94*R94 -> 139232.71 | P94: 5 | Q94: =P94*G94 -> 67.5 | R94: 6.6971 | S94: 10426 | T94: 10300 | U94: =S94*G94 -> 140751 | V94: 25公斤小包散装 | W94: CIF | X94: MUNDRA | Y94: =3700 -> 3700 | Z94: =47 -> 47 | AA94: =4500 -> 4500
A95: 毛晓翔 | B95: LC90 | C95: SUNPLAST ELECTRONICS PRIVATE LIMITED | D95: CMTRL-20260930-024 | E95: 46326 | F95: SAN 4800 | G95: 14 | H95: 1540 | I95: =G95*H95 -> 21560 | J95: 14 | K95: =G95-J95 -> 0 | L95: 0 | M95: =I95-L95 -> 21560 | N95: =H95*J95-L95 -> 21560 | O95: =N95*R95 -> 144389.48 | P95: 5 | Q95: =P95*G95 -> 70 | R95: 6.6971 | S95: 10426 | T95: 10300 | U95: =S95*G95 -> 145964 | V95: 25公斤小包散装 | W95: CIF | X95: MUNDRA
A96: 毛晓翔 | B96: LC90 | C96: SUNPLAST ELECTRONICS PRIVATE LIMITED | D96: CMTRL-20260930-024 | E96: 46326 | F96: HIPS-CH612 | G96: 55 | H96: 1540 | I96: =G96*H96 -> 84700 | J96: 55 | K96: =G96-J96 -> 0 | L96: 0 | M96: =I96-L96 -> 84700 | N96: =H96*J96-L96 -> 84700 | O96: =N96*R96 -> 567244.37 | P96: 5 | Q96: =P96*G96 -> 275 | R96: 6.6971 | S96: 10426 | T96: 10500 | U96: =S96*G96 -> 573430 | V96: 25公斤小包散装 | W96: CIF | X96: MUNDRA | Y96: =2*3700 -> 7400 | Z96: =2*47 -> 94 | AA96: =2*4500 -> 9000
A97: 张晓敏 | B97: 100TT | C97: BILLION ASCENT INDUSTRIAL LIMITED | D97: CMTRL-20260930-025 | E97: 46325 | F97: SAN 900 | G97: 135 | H97: 1440 | I97: =G97*H97 -> 194400 | J97: 81 | K97: =G97-J97 -> 54 | L97: =长科收款!E86+长科收款!E91 -> 194400 | M97: =I97-L97 -> 0 | N97: =H97*J97-L97 -> -77760 | O97: =N97*R97 -> -520603.2 | P97: 0 | Q97: =P97*G97 -> 0 | R97: 6.695 | S97: 10727 | U97: =S97*G97 -> 1448145 | V97: 25公斤小包散装 | W97: FOB | X97: QINZHOU | Y97: 0 | Z97: 0 | AA97: =5*4500 -> 22500
A98: 刘丝雨 | B98: 100TT | C98: BILLION ASCENT INDUSTRIAL LIMITED | D98: CMTRL-20261008-026 | E98: 46334 | F98: MABS CT2010 | G98: 27 | H98: 1920 | I98: =G98*H98 -> 51840 | J98: 27 | K98: =G98-J98 -> 0 | L98: =长科收款!E88 -> 51840 | M98: =I98-L98 -> 0 | N98: =H98*J98-L98 -> 0 | O98: =N98*R98 -> 0 | P98: 0 | Q98: =P98*G98 -> 0 | R98: 6.6914 | S98: 14313 | T98: 14000 | U98: =S98*G98 -> 386451 | W98: FOB | X98: QINZHOU | Y98: 0 | Z98: 0 | AA98: 5500
A99: 何欣润 | B99: 100TT | C99: FIREMAX(CAMBODIA) TIRES CO.. LTD | D99: CMTRL-20261010-027 | E99: 46341 | F99: 炭黑 N330 | G99: 600 | H99: 1385 | I99: =G99*H99 -> 831000 | J99: =80+60+60 -> 200 | K99: =G99-J99 -> 400 | L99: 831000 | M99: =I99-L99 -> 0 | N99: =H99*J99-L99 -> -554000 | O99: =N99*R99 -> -3700720 | P99: 0 | Q99: =P99*G99 -> 0 | R99: 6.68 | S99: 8716 | U99: =S99*G99 -> 5229600 | V99: 1000kg 吨袋 | W99: CIF | X99: Ho Chi Minh | Y99: =900*30 -> 27000 | Z99: =30*30 -> 900 | AA99: =900*30 -> 27000
A100: 何欣润 | B100: 100TT | C100: FIREMAX(CAMBODIA) TIRES CO.. LTD | D100: CMTRL-20261010-027 | E100: 46341 | F100: 炭黑 N326 | G100: 330 | H100: 1385 | I100: =G100*H100 -> 457050 | J100: =60+120+40+80 -> 300 | K100: =G100-J100 -> 30 | L100: 457050 | M100: =I100-L100 -> 0 | N100: =H100*J100-L100 -> -41550 | O100: =N100*R100 -> -277554 | P100: 0 | Q100: =P100*G100 -> 0 | R100: 6.68 | S100: 8765 | U100: =S100*G100 -> 2892450 | V100: 1000kg 吨袋 | W100: CIF | X100: Ho Chi Minh | Y100: =900*30 -> 27000 | Z100: =30*15 -> 450 | AA100: =4500*15 -> 67500
...

Sheet 长科收款
A1: 日期 | B1: 客户 | C1: 合同号 | D1: 付款方式 | E1: 收款金额 | F1: 备注
A2: 46036 | B2: ALPEX JOINT STOCK COMPANY | C2: CMTRL-XS-20260113-0002 | D2: TT | E2: 8722 | F2: 0002 预付款
A3: 46050 | B3: ALPEX JOINT STOCK COMPANY | C3: CMTRL-XS-20260113-0002 | E3: 20405 | F3: 0002 尾款
A4: 46065 | B4: TAIWAN TONGZEWANG INDUSTRY CO., LTD. | C4: CMTRL-XS-20260114-0001 | D4: TT | E4: 5850 | F4: 0001 全款
A5: 46090 | B5: ZHI YUE XIAN (VIETNAM) CO., LTD | C5: CMTRL-XS-20260305-0011 | D5: TT | E5: 48950 | F5: 0011 全款
A6: 46093 | B6: Polyram Plastic Industries LTD | C6: CMTRL-XS-20260116-0001 | D6: TT | E6: 33210 | F6: 0001 全款
A7: 46101 | B7: 鏵塑股份有限公司ULTRATEC PLASTICS CO.,LTD. | C7: CMTRL-XS-20260318-0002 | D7: TT | E7: 23625 | F7: 0002 全款
A8: 46101 | B8: Valutrans Investment Co., Limited | C8: CMTRL-XS-20260310-0001 | D8: TT | E8: 127520 | F8: 0001 预付
A9: 46106 | B9: PT POLYMERS INDIA LLP | C9: CMTRL-XS-20260320-0001 | D9: TT | E9: 20350 | F9: 0001 货款
A10: 46108 | B10: BILLION ASCENT INDUSTRIAL LIMITED | C10: CMTRL-XS-20260323-0001 | D10: TT | E10: 166320 | F10: 0001 货款
A11: 46111 | B11: Valutrans Investment Co., Limited | C11: CMTRL-XS-20260310-0001 | D11: TT | E11: 164800 | F11: 0001 货款
A12: 46111 | B12: BILLION ASCENT INDUSTRIAL LIMITED | C12: CMTRL-XS-20260323-0001 | D12: TT | E12: 83160 | F12: 0001 货款
A13: 46112 | B13: ABBEY VIETNAM JOINT STOCK COMPANY | C13: CMTRL-XS-20260313-0001 | D13: TT | E13: 6828.15 | F13: 0001 30%预付款
A14: 46119 | B14: ALPEX JOINT STOCK COMPANY | C14: CMTRL-XS-20260331-0002 | D14: TT | E14: 13035 | F14: 0002 预付款
A15: 46120 | B15: BILLION ASCENT INDUSTRIAL LIMITED | C15: CMTRL-XS-20260323-0001 | D15: TT | E15: 166320 | F15: 货款
... A38: 46195 | B38: Valutrans Investment Co., Limited | C38: CMTRL-XS-20260519-0001 | D38: TT | E38: 89500 | F38: 货款
A39: 46195 | B39: SAMSUNG CT CORPORATION | D39: TT | E39: 460330 | F39: 货款
A40: 46198 | B40: SAMSUNG CT CORPORATION | D40: TT | E40: 470792.5 | F40: 货款
A41: 46202 | B41: Valutrans Investment Co., Limited | C41: CMTRL-XS-20260519-0001 | D41: TT | E41: 304300 | F41: 340吨货款
A42: 46206 | B42: ZHI YUE XIAN (VIETNAM) CO., LTD | C42: CMTRL-XS-20260630-0003 | D42: TT | E42: 47025 | F42: 全款
A43: 46209 | B43: PENTAPLAST SRL | C43: CMTRL-XS-20260630-0005 | D43: TT | E43: 27000 | F43: 全款
A44: 46212 | B44: SAMSUNG CT CORPORATION | D44: TT | E44: 156937.5 | F44: 货款
A45: 46218 | B45: 宁波鹿鸣供应链管理有限公司 | C45: CMTRL-XS-20260715-0003 | D45: TT | E45: 408240 | F45: 全款
A46: 46219 | B46: PT POLYMERS INDIA LLP | C46: CMTRL-XS-20260320-0001-2 | D46: LC | E46: 122100 | F46: 信用证全款
A47: 46219 | B47: PT POLYMERS INDIA LLP | C47: CMTRL-XS-20260320-0001-3 | D47: LC | E47: 122100 | F47: 信用证全款
A48: 46219 | B48: Polyram Plastic Industries LTD | C48: CMTRL-XS-20260709-0002 | D48: TT | E48: 40230 | F48: 全款
A49: 46220 | B49: AYDIN PLASTIK TURIZM INS. SAN. VE TIC. LTD. STI | C49: CMTRL-XS-20260326-0001 | D49: LC | E49: 183680 | F49: 信用证全款
A50: 46223 | B50: ALPEX JOINT STOCK COMPANY | C50: CMTRL-XS-20260714-0010 | D50: TT | E50: 10477.5 | F50: 30%预付款
A51: 46224 | B51: BILLION ASCENT INDUSTRIAL LIMITED | C51: CMTRL-XS-20260331-0001 | D51: TT | E51: =27*1535*0.9 -> 37300.5 | F51: 27 吨 ，90% 货款
A52: 46224 | B52: BILLION ASCENT INDUSTRIAL LIMITED | C52: CMTRL-XS-20260715-0001 | D52: TT | E52: =54*1240 -> 66960 | F52: 54 吨100% 货款
A53: 46234 | B53: AMAZON CORPORATE SERVICES PVT. LTD. | C53: CMTRL-XS-20260731-0005-1 | D53: TT | E53: 7147.5 | F53: 20%预付
A54: 46237 | B54: AMAZON CORPORATE SERVICES PVT. LTD. | C54: CMTRL-XS-20260731-0005-2 | D54: TT | E54: 7147.5 | F54: 20%预付
A55: 46237 | B55: AMAZON CORPORATE SERVICES PVT. LTD. | C55: CMTRL-XS-20260731-0005-3 | D55: TT | E55: 7147.5 | F55: 20%预付
A56: 46237 | B56: BILLION ASCENT INDUSTRIAL LIMITED | C56: CMTRL-XS-20260715-0001 | D56: TT | E56: =54*长科!H50 -> 66960 | F56: 54 吨货款
A57: 46237 | B57: BILLION ASCENT INDUSTRIAL LIMITED | C57: CMTRL-XS-20260716-0001 | D57: TT | E57: =27*长科!H52 -> 33615 | F57: 27 吨货款
A58: 46246 | B58: FIREMAX(CAMBODIA) TIRES CO.. LTD | C58: CMTRL-20260806-003 | D58: TT | E58: 424200 | F58: 003 全款
A59: 46246 | B59: AMAZON CORPORATE SERVICES PVT. LTD. | C59: CMTRL-20260811-006 | D59: TT | E59: 7335 | F59: 006-1 20%预付
A60: 46246 | B60: AMAZON CORPORATE SERVICES PVT. LTD. | C60: CMTRL-20260811-006 | D60: TT | E60: 7060 | F60: 006-2 20%预付
A61: 46247 | B61: ALPEX JOINT STOCK COMPANY | C61: CMTRL-XS-20260714-0010 | D61: TT | E61: 24447.5 | F61: 30%预付款
A62: 46247 | B62: NJ POWER LLP | C62: CMTRL-20260812-009 | D62: TT | E62: 11343.75 | F62: 30%预付款 (38美金手续费）
A63: 46247 | B63: BILLION ASCENT INDUSTRIAL LIMITED | C63: CMTRL-20260812-007 | D63: TT | E63: 134352 | F63: 全款
A64: 46247 | B64: BILLION ASCENT INDUSTRIAL LIMITED | C64: CMTRL-XS-20260331-0001 | D64: TT | E64: 37300.5 | F64: 27吨，90% 尾款
A65: 46252 | B65: Valutrans Investment Co., Limited | C65: CMTRL-XS-20260519-0001 | D65: TT | E65: 89502.11 | F65: 尾款
A66: 46254 | B66: VINAYAK AGNIPEAK LLP | C66: CMTRL-20260819-013 | D66: TT | E66: 10601.25 | F66: 30%预付 (38美金手续费）
A67: 46254 | B67: BILLION ASCENT INDUSTRIAL LIMITED | C67: CMTRL-20260812-008 | D67: TT | E67: 134352 | F67: 全款
A68: 46254 | B68: BILLION ASCENT INDUSTRIAL LIMITED | C68: CMTRL-XS-20260331-0001 | D68: TT | E68: 37300.5 | F68: 27 吨，90% 尾款
A69: 46259 | B69: FIREMAX(CAMBODIA) TIRES CO.. LTD | C69: CMTRL-20260820-014 | D69: TT | E69: 208000 | F69: 全款
... A90: 46309 | B90: FIREMAX(CAMBODIA) TIRES CO.. LTD | C90: CMTRL-20261010-027 | D90: TT | E90: 1288050 | F90: 全款
A91: 46317 | B91: BILLION ASCENT INDUSTRIAL LIMITED | C91: CMTRL-20260930-025 | D91: TT | E91: =54*长科!H97 -> 77760 | F91: 54吨
A92: 46317 | B92: BILLION ASCENT INDUSTRIAL LIMITED | C92: CMTRL-XS-20260331-0001 | D92: TT | E92: =27*长科!H26*0.9 -> 37300.5 | F92: 27吨，90% 尾款
A93: 46317 | B93: BILLION ASCENT INDUSTRIAL LIMITED | C93: CMTRL-20261015-028 | D93: TT | E93: 32016 | F93: 全款

Sheet 长科出库
A1: 发货日期 | B1: 客户 | C1: 合同号 | D1: 产品型号 | E1: 数量 | F1: 包装 | G1: 柜型 | H1: 提单号 | I1: 箱封号 | J1: 司机信息 | K1: 货代
A2: 46039 | B2: ALPEX JOINT STOCK COMPANY | C2: CMTRL-XS-20260113-0002 | D2: SAN 900 | E2: 27.5 | F2: 小包散装 | G2: 40HQ | J2: 车号，桂P53680 姓名：盘小龙 电话：13558000229 身份证：450923198710306738 | K2: 广西泛航国际物流有限公司
A3: 46043 | B3: TAIWAN TONGZEWANG INDUSTRY CO., LTD | C3: CMTRL-XS-20260114-0001 | D3: 炭黑 N220 | E3: 0.5 | F3: 半吨包带托盘（logo包装） | G3: 4.2米高栏车 | J3: 车牌：桂FQ2796 司机：李成付 电话：13277846690 证件：130427197001010634 | K3: 广西泛航国际物流有限公司
A4: 46043 | B4: TAIWAN TONGZEWANG INDUSTRY CO., LTD | C4: CMTRL-XS-20260114-0001 | D4: 炭黑 N660 | E4: 0.5 | F4: 半吨包带托盘（logo包装）
A5: 46051 | B5: Polyram Plastic Industries LTD | C5: CMTRL-XS-20260116-0001 | D5: HIPS 612 | E5: 27 | F5: 25公斤小包带托盘（1.125吨/托） | G5: 40HQ | J5: 车号：桂NB1612 名字：李树林 电话：17878781612 身份证：450923198506027758 | K5: 广西泛航国际物流有限公司
A6: 46053 | B6: K.L.J. POLYMERS PRIVATE LIMITED | C6: CMTRL-XS-20260112-0003 | D6: SAN 4800 | E6: 27.5 | F6: 小包散装 | G6: 40HQ | J6: 桂P53680 盘小龙 13558000229 身份证：450923198710306738 | K6: 广西泛航国际物流有限公司
A7: 46053 | B7: K.L.J. POLYMERS PRIVATE LIMITED | C7: CMTRL-XS-20260112-0003 | D7: SAN 4800 | E7: 27.5 | F7: 小包散装 | G7: 40HQ | J7: 桂NB1612 名字：李树林 电话：17878781612 身份证：4509231985060277 | K7: 广西泛航国际物流有限公司
A8: 46057 | B8: AMLON POLYMERS | C8: CMTRL-XS-20260112-0005 | D8: SAN 4800 | E8: 27.5 | F8: 小包散装 | G8: 40HQ | H8: 265970201 | I8: 箱号:TCNU2787713 封号:ML-CN5351682 | J8: 车号1：桂NC8668 名字：许富金 电话：13977039933 身份证：450702198410154856 | K8: 广西泛航国际物流有限公司
A9: 46057 | B9: AMLON POLYMERS | C9: CMTRL-XS-20260112-0005 | D9: SAN 4800 | E9: 27.5 | F9: 小包散装 | G9: 40HQ | I9: 箱号:HASU4989226 封号:ML-CN5351681 | J9: 车号 2：桂NC7839 名字：宁国杰 电话：18977701013 身份证:450702198007204817 | K9: 广西泛航国际物流有限公司
A10: 46091 | B10: ZHI YUE XIAN (VIETNAM) CO., LTD | C10: CMTRL-XS-20260305-0011 | D10: MABS CT2010 | E10: 27.5 | F10: 小包散装 | G10: 40HQ | I10: 柜号：SDY09901966 | J10: 车牌：赣DJ8101 车挂：赖DY681挂 司机：丰建斌 电话：13878655950 身份证号：45212319741116581X | K10: 东莞丽林达物流有限公司
A11: 46105 | B11: Valutrans Investment Co., Limited | C11: CMTRL-XS-20260310-0001 | D11: 炭黑 N660 | E11: 20 | F11: 1000kg 吨袋 | H11: 提单号：155600034016 | I11: 箱号：EGSU1648191 封号：EMCSYH0554 | J11: 车号：桂P82205 姓名：黄立保 身份证：450122197011044519 电话：13532697873
A12: 46105 | B12: Valutrans Investment Co., Limited | C12: CMTRL-XS-20260310-0001 | D12: 炭黑 N330 | E12: 20 | F12: 1000kg 吨袋 | H12: 提单号：155600034016 | I12: 箱号：TCLU8898785 封号：EMCSYH0584 | J12: 车号：桂P10238D 司机姓名：王锋 身份证：429003197404210037 电话：15271067939
A13: 46105 | B13: Valutrans Investment Co., Limited | C13: CMTRL-XS-20260310-0001 | D13: 炭黑 N330 | E13: 20 | F13: 1000kg 吨袋 | H13: 提单号：155600034016 | I13: 箱号：EGHU9560098 封号：EMCSYH0614 | J13: 桂P02820D 司机姓名：王家贵 身份证：452824197410185899 电话：18777766299
A14: 46105 | B14: Valutrans Investment Co., Limited | C14: CMTRL-XS-20260310-0001 | D14: 炭黑 N330 | E14: 20 | F14: 1000kg 吨袋 | H14: 提单号：155600034016 | I14: 箱号：GA0U6248510 封号：EMCSYH0694 | J14: 桂N08163D 司机姓名：杨金双 身份证：220322197906182419 电话：13530544375
A15: 46105 | B15: Valutrans Investment Co., Limited | C15: CMTRL-XS-20260310-0001 | D15: 炭黑 N330 | E15: 20 | F15: 1000kg 吨袋 | H15: 提单号：155600034016 | I15: 箱号：EGSU9513417 封号：EMCSYH0604 | J15: 桂P10238D 司机姓名：王锋 身份证：429003197404210037 电话：15271067939
A16: 46105 | B16: Valutrans Investment Co., Limited | C16: CMTRL-XS-20260310-0001 | D16: 炭黑 N330 | E16: 20 | F16: 1000kg 吨袋 | H16: 提单号：155600034016 | I16: 箱号：EGHU9786906 封号：EMCSYH0564 | J16: 桂P80805 司机姓名：刘大邦 身份证：450703199204201237 电话：17877277089
A17: 46105 | B17: Valutrans Investment Co., Limited | C17: CMTRL-XS-20260310-0001 | D17: 炭黑 N330 | E17: 20 | F17: 1000kg 吨袋 | H17: 提单号：155600034016 | I17: 箱号：EGHU9100533 封号：EMCSYH0594 | J17: 桂P02820D 司机姓名：王家贵 身份证：452824197410185899 电话：18777766299
A18: 46105 | B18: Valutrans Investment Co., Limited | C18: CMTRL-XS-20260310-0001 | D18: 炭黑 N330 | E18: 20 | F18: 1000kg 吨袋 | H18: 提单号：155600034016 | I18: 箱号：TGBU4663835 封号：EMCSYH0574 | J18: 桂N08163D 司机姓名：杨金双 身份证：220322197906182419 电话：13530544375
A19: 46106 | B19: Valutrans Investment Co., Limited | C19: CMTRL-XS-20260310-0001 | D19: 炭黑 N330 | E19: 20 | F19: 1000kg 吨袋 | H19: 提单号：155600034016 | I19: 箱号：TRHU7147780 封号：EMCSYH0654 | J19: 车号：桂P02820D 司机姓名：王家贵 身份证：452824197410185899 电话：18777766299
A20: 46106 | B20: Valutrans Investment Co., Limited | C20: CMTRL-XS-20260310-0001 | D20: 炭黑 N330 | E20: 20 | F20: 1000kg 吨袋 | H20: 提单号：155600034016 | I20: 箱号：EMCU8936328 封号：EMCSYH0634 | J20: 车号：桂N05876D 姓名：杨世旺 身份证号：450703198201282110 电话：18877705103
A21: 46106 | B21: Valutrans Investment Co., Limited | C21: CMTRL-XS-20260310-0001 | D21: 炭黑 N330 | E21: 20 | F21: 1000kg 吨袋 | H21: 提单号：155600034016 | I21: 箱号：EGSU1908895 封号：EMCSYH0664 | J21: 车号：桂N08163D 司机姓名：杨金双 身份证：220322197906182419 电话：13530544375
A22: 46106 | B22: Valutrans Investment Co., Limited | C22: CMTRL-XS-20260310-0001 | D22: 炭黑 N330 | E22: 20 | F22: 1000kg 吨袋 | H22: 提单号：155600034016 | I22: 柜号：EMCU1564527 铅封：EMCSYH0624 | J22: 车号：桂N02860D 姓名：黄高伟 身份证：45070219880513661X 电话：18207878199
... A25: 46106 | B25: Valutrans Investment Co., Limited | C25: CMTRL-XS-20260310-0001 | D25: 炭黑 N330 | E25: 20 | F25: 1000kg 吨袋 | H25: 提单号：155600034016 | I25: 箱号：EGSU1776382 封号：EMCSYH0674 | J25: 车号：桂N08163D 司机姓名：杨金双 身份证：220322197906182419 电话：13530544375
A26: 46109 | B26: 鏵塑股份有限公司 ULTRATEC PLASTICS CO.,LTD. | C26: CMTRL-XS-20260318-0002 | D26: HIPS 612 | E26: 15 | F26: 25公斤小包带托盘 | J26: 车号 ：桂NB8181 司机 :唐有明 电话:13667867517 身份证：452323198111191915 | K26: 广西泛航国际物流有限公司
A27: 46112 | B27: PT POLYMERS INDIA LLP | C27: CMTRL-XS-20260320-0001 | D27: SAN 2800 | E27: 27.5 | F27: 25公斤小包散装 | H27: 提单号，155600042183 | I27: 箱号，EGSU9796662 封签，EMCSYN5194 | J27: 桂NC0900 名字：罗尚金 电话：18378871900 身份证：452730198410254774 | K27: 广西泛航国际物流有限公司
A28: 46112 | B28: PT POLYMERS INDIA LLP | C28: CMTRL-XS-20260320-0001 | D28: SAN 2800 | E28: 27.5 | F28: 25公斤小包散装 | H28: 单号.155600042183 | I28: 箱号.EITU9205514 封号:EMCSYN5184 | J28: 沪DT6163 名字： 陈家桩 电话： 15007771145 身份证：450721198211255610 | K28: 广西泛航国际物流有限公司
A29: 46112 | B29: PT POLYMERS INDIA LLP | C29: CMTRL-XS-20260320-0001 | D29: SAN 2800 | E29: 27.5 | F29: 25公斤小包散装 | H29: 提单号:155600042183 | I29: 箱号：GAOU6985841 封铅号:EMCSYN5954 | J29: 桂N92007 名字：唐玺 电话：18323764911 身份证：500234198310076238 | K29: 广西泛航国际物流有限公司
A30: 46112 | B30: BILLION ASCENT INDUSTRIAL LIMITED | C30: CMTRL-XS-20260323-0001 | D30: SAN 900 | E30: 27 | F30: 25公斤小包散装 | H30: 单号:COAU7267804610 | I30: 箱号TEMU6001355 封号SYA1042342 | J30: 车号1:桂NE0200 姓名：李香武 电话：17776002225 身份证:450923198410247756 | K30: 广西泛航国际物流有限公司
A31: 46112 | B31: BILLION ASCENT INDUSTRIAL LIMITED | C31: CMTRL-XS-20260323-0001 | D31: SAN 900 | E31: 27 | F31: 25公斤小包散装 | H31: 单号:COAU7267804610 | I31: 箱号CSNU8493285 封号NF502075 | J31: 车号2：桂ND7880 姓名:张国伟 电话:18877112201 身份证:450702199404035134 | K31: 广西泛航国际物流有限公司
A32: 46112 | B32: Valutrans Investment Co., Limited | C32: CMTRL-XS-20260310-0001 | D32: 炭黑 N330 | E32: 20 | F32: 1000kg 吨袋 | H32: 提单号：155600034024 | I32: 箱号：TGBU6996877 封号：EMCSYN6634 | J32: 车号：桂P10238D 司机姓名：王锋 身份证：429003197404210037 电话：15271067939 提单号：155600034024
A33: 46112 | B33: Valutrans Investment Co., Limited | C33: CMTRL-XS-20260310-0001 | D33: 炭黑 N330 | E33: 20 | F33: 1000kg 吨袋 | H33: 提单号：155600034024 | I33: 箱号：EGHU9293788 封号：EMCSYN6654 | J33: 车号：桂P02820D 司机姓名：王家贵 身份证：452824197410185899 电话：18777766299 提单号：155600034024
A34: 46112 | B34: Valutrans Investment Co., Limited | C34: CMTRL-XS-20260310-0001 | D34: 炭黑 N330 | E34: 20 | F34: 1000kg 吨袋 | H34: 提单号：155600034024 | I34: 箱号：EITU1778340 封号：EMCSYN6624 | J34: 车号：桂N08163D 司机姓名：杨金双 身份证：220322197906182419 电话：13530544375 提单号：155600034024
A35: 46112 | B35: Valutrans Investment Co., Limited | C35: CMTRL-XS-20260310-0001 | D35: 炭黑 N330 | E35: 20 | F35: 1000kg 吨袋 | H35: 提单号：155600034024 | I35: 箱号：EITU9276760 封号：EMCSYN6614 | J35: 车号：桂N08306D 姓名： 梁广友 身份证号：452528198208301036 电话：18277517031
A36: 46112 | B36: Valutrans Investment Co., Limited | C36: CMTRL-XS-20260310-0001 | D36: 炭黑 N330 | E36: 20 | F36: 1000kg 吨袋 | H36: 提单号：155600034024 | I36: 箱号：EGHU9601480 封号：EMCSYN6604 | J36: 车号：桂P12681D 姓名：江华达 身份证：450702199803235117 电话：18777705053
A37: 46112 | B37: Valutrans Investment Co., Limited | C37: CMTRL-XS-20260310-0001 | D37: 炭黑 N330 | E37: 20 | F37: 1000kg 吨袋 | H37: 提单号：155600034024 | I37: 箱号：TRHU7849581 封号：EMCSYN6544 | J37: 姓名：何在锋 身份证：452702198303094773 电话：15307787987 提单号：155600034024
A38: 46112 | B38: Valutrans Investment Co., Limited | C38: CMTRL-XS-20260310-0001 | D38: 炭黑 N330 | E38: 20 | F38: 1000kg 吨袋 | J38: 车号：桂N05876D 姓名：杨世旺 身份证号：450703198201282110 电话：18877705103
A39: 46112 | B39: Valutrans Investment Co., Limited | C39: CMTRL-XS-20260310-0001 | D39: 炭黑 N330 | E39: 20 | F39: 1000kg 吨袋 | J39: 车号：桂P09360D 姓名：蒙生宝 身份证：45272719780424031 电话：13768284099
A40: 46113 | B40: Valutrans Investment Co., Limited | C40: CMTRL-XS-20260310-0001 | D40: 炭黑 N330 | E40: 20 | F40: 1000kg 吨袋 | H40: 提单号：155600034024 | I40: 箱号：TXGU7395533 封号：EMCSYN6554 | J40: 车号：桂P13596D 司机姓名：全大攀 身份证：452802197706148116 电话：13807774428
A41: 46113 | B41: Valutrans Investment Co., Limited | C41: CMTRL-XS-20260310-0001 | D41: 炭黑 N330 | E41: 20 | F41: 1000kg 吨袋 | H41: 提单号：155600034032 | I41: 箱号：MAGU5368659 封号：EMCSYN6564 | J41: 车号：桂P12681D 姓名：江华达 身份证：450702199803235117 电话：18777705053
A42: 46113 | B42: Valutrans Investment Co., Limited | C42: CMTRL-XS-20260310-0001 | D42: 炭黑 N330 | E42: 20 | F42: 1000kg 吨袋 | H42: 提单号：155600034024 | I42: 箱号：EGSU9393610 封号：EMCSYN6584 | J42: 车号：桂P06926D 姓名：陈永平 身份证：452802197506133358 电话：18177164466
A43: 46113 | B43: Valutrans Investment Co., Limited | C43: CMTRL-XS-20260310-0001 | D43: 炭黑 N330 | E43: 20 | F43: 1000kg 吨袋 | H43: 提单号：155600034032 | I43: 箱号：EMCU9949090 封号：EMCSYN6524 | J43: 车号：桂ND1085 姓名：袁智决 身份证：452226198909116635 电话：15278860772
A44: 46113 | B44: Valutrans Investment Co., Limited | C44: CMTRL-XS-20260310-0001 | D44: 炭黑 N330 | E44: 20 | F44: 1000kg 吨袋 | H44: 提单号：155600034032 | I44: 箱号：EGSU9423611 封号：EMCSYN6574 | J44: 车号：桂P12681D 姓名：江华达 身份证：450702199803235117 电话：18777705053
A45: 46113 | B45: Valutrans Investment Co., Limited | C45: CMTRL-XS-20260310-0001 | D45: 炭黑 N330 | E45: 20 | F45: 1000kg 吨袋 | H45: 提单号：155600034032 | I45: 箱号：EITU1670103 封号：EMCSYN6594 | J45: 车号：桂P13596D 司机姓名：全大攀 身份证：452802197706148116 电话：13807774428
A46: 46113 | B46: Valutrans Investment Co., Limited | C46: CMTRL-XS-20260310-0001 | D46: 炭黑 N330 | E46: 20 | F46: 1000kg 吨袋 | H46: 提单号：155600034032 | I46: 箱号：EGSU9263215 封号：EMCSYN6504 | J46: 车号：桂P06926D 姓名：陈永平 身份证：452802197506133358 电话：18177164466
A47: 46113 | B47: Valutrans Investment Co., Limited | C47: CMTRL-XS-20260310-0001 | D47: 炭黑 N330 | E47: 20 | F47: 1000kg 吨袋 | H47: 提单号：155600034032 | I47: 箱号：EGSU6365527 封号：EMCSYN6514 | J47: 车号：桂ND1085 姓名：袁智决 身份证：452226198909116635 电话：15278860772
A48: 46113 | B48: BILLION ASCENT INDUSTRIAL LIMITED | C48: CMTRL-XS-20260323-0001 | D48: SAN 900 | E48: 27 | F48: 25公斤小包散装 | I48: 箱号:UETU5315609 封签号:NE209644 | J48: 车号:桂NC2156 司机:蒋小华 电话:18897665188 身份证号 452323197303172212
A49: 46113 | B49: BILLION ASCENT INDUSTRIAL LIMITED | C49: CMTRL-XS-20260323-0001 | D49: SAN 900 | E49: 27 | F49: 25公斤小包散装 | I49: 箱号：CSNU5949875 封号:SYA1001914 | J49: 车号：桂NB1612 名字：李树林 电话：17878781612 身份证：450923198506027758
A50: 46116 | B50: ABBEY VIETNAM JOINT STOCK COMPANY | C50: CMTRL-XS-20260313-0001 | D50: 炭黑 N326 | E50: 9.6 | F50: 20公斤带托盘 | J50: 车牌：桂NB1539 姓名：谭华运 电话：13502119580 身份证:452728199003202718
A51: 46116 | B51: ABBEY VIETNAM JOINT STOCK COMPANY | C51: CMTRL-XS-20260313-0001 | D51: 炭黑 N220 | E51: 2.2 | F51: 20公斤带托盘
A52: 46116 | B52: ABBEY VIETNAM JOINT STOCK COMPANY | C52: CMTRL-XS-20260313-0001 | D52: 炭黑 N550 | E52: 4.4 | F52: 20公斤带托盘
A53: 46116 | B53: ABBEY VIETNAM JOINT STOCK COMPANY | C53: CMTRL-XS-20260313-0001 | D53: 炭黑 N660 | E53: 2.2 | F53: 20公斤带托盘
A54: 46120 | B54: PT POLYMERS INDIA LLP | C54: CMTRL-XS-20260320-0001 | D54: SAN 2800 | E54: 27.5 | F54: 25公斤小包散装 | J54: 桂NC2156 司机:蒋小华 电话:18897665188 身份证号 452323197303172212
A55: 46120 | B55: PT POLYMERS INDIA LLP | C55: CMTRL-XS-20260320-0001 | D55: SAN 4800 | E55: 27.5 | F55: 25公斤小包散装 | J55: 桂P53680（27.5吨CN-4800） 名字：盘小龙 电话：13558000229 身份证：450923198710306738
A56: 46120 | B56: PT POLYMERS INDIA LLP | C56: CMTRL-XS-20260320-0001 | D56: SAN 4800 | E56: 27.5 | F56: 25公斤小包散装 | J56: 桂P08596（27.5吨CN-4800） 名字：盘宝聪 电话：15807707639 身份证：452528198302066714
A57: 46122 | B57: PT POLYMERS INDIA LLP | C57: CMTRL-XS-20260320-0001 | D57: SAN 2800 | E57: 27.5 | F57: 25公斤小包散装 | J57: 车号：桂P53680 司机：盘小龙 电话：13558000229 身份证：450923198710306738
A58: 46125 | B58: BILLION ASCENT INDUSTRIAL LIMITED | C58: CMTRL-XS-20260323-0001 | D58: SAN 900 | E58: 27 | F58: 25公斤小包散装 | H58: SITGQIHP076237 | I58: 箱号FFAU7430942 封号SITZ257776 | J58: 车号：桂NC8668 姓名：许富金 电话：13977039933 身份证：450702198410154856 | K58: 广西泛航国际物流有限公司
A59: 46125 | B59: BILLION ASCENT INDUSTRIAL LIMITED | C59: CMTRL-XS-20260323-0001 | D59: SAN 900 | E59: 27 | F59: 25公斤小包散装 | H59: SITGQIHP076237 | I59: 箱号：UETU7251355 封号：SITZ754600 | J59: 车号:桂NE0200 姓名：李香武 电话：17776002225 身份证:450923198410247756 | K59: 广西泛航国际物流有限公司
A60: 46125 | B60: ALPEX JOINT STOCK COMPANY | C60: CMTRL-XS-20260331-0002 | D60: SAN 900 | E60: 27.5 | F60: 25公斤小包散装 | H60: SITGQISG076334 | I60: 箱号：SITU9209827 封号：SITZ374584 | J60: 车号：桂N99393 姓名：蓝毅 电话：19902185158 身份证：452731197606126039 | K60: 宁波鹏信国际货运代理有限公司
A61: 46126 | B61: AYDIN PLASTIK TURIZM INSAAT SAN VE | C61: CMTRL-XS-20260326-0001 | D61: MABS CT2010 | E61: 27 | J61: 车号：桂N99393 名字：蓝 毅 电话：19902185158 身份证：452731197606126039
A62: 46126 | B62: AYDIN PLASTIK TURIZM INSAAT SAN VE | C62: CMTRL-XS-20260326-0001 | D62: MABS CT2010 | E62: 27 | J62: 车号：桂NB1139 名字：谭鸿毅 电话：13102108227 身份证：452728198808163619
A63: 46139 | B63: Polyram Plastic Industries LTD | C63: CMTRL-XS-20260409-0001 | D63: HIPS 612 | E63: 27 | F63: 25公斤小包带托盘（1.125吨/托） | J63: 车号：桂ND0169 姓名：黄瑞波 身份证：452802197509202750 电话：18277726326 | K63: 广西泛航国际物流有限公司
A64: 46141 | B64: BILLION ASCENT INDUSTRIAL LIMITED | C64: CMTRL-XS-20260330-0001 | D64: SAN 900 | E64: 27 | J64: 车号：桂NB1612 名字：李树林 电话：17878781612 身份证：450923198506027758
A65: 46147 | B65: BILLION ASCENT INDUSTRIAL LIMITED | C65: CMTRL-XS-20260323-0001 | D65: SAN 900 | E65: 27 | J65: 车号：桂NB1612 名字：李树林 电话：17878781612 身份证：450923198506027758
A66: 46147 | B66: BILLION ASCENT INDUSTRIAL LIMITED | C66: CMTRL-XS-20260323-0001 | D66: SAN 900 | E66: 27 | J66: 车号：桂P53680 盘小龙13558000229 身份证：450923198710306738 提单号：SITGQISG077365
A67: 46147 | B67: BILLION ASCENT INDUSTRIAL LIMITED | C67: CMTRL-XS-20260323-0001 | D67: SAN 900 | E67: 27 | J67: 车号：桂P08596 盘宝聪15807707639 身份证：452528198302066714
A68: 46147 | B68: BILLION ASCENT INDUSTRIAL LIMITED | C68: CMTRL-XS-20260323-0001 | D68: SAN 900 | E68: 27 | J68: 车号:桂NC2156 司机:蒋小华 电话:18897665188 身份证号: 452323197303172212
A69: 46153 | B69: BILLION ASCENT INDUSTRIAL LIMITED | C69: CMTRL-XS-20260330-0001 | D69: SAN 900 | E69: 27 | J69: 车号：桂P53680 盘小龙13558000229 身份证：450923198710306738
A70: 46153 | B70: BILLION ASCENT INDUSTRIAL LIMITED | C70: CMTRL-XS-20260330-0001 | D70: SAN 900 | E70: 27 | J70: 车号：桂P08596 盘宝聪15807707639 身份证：452528198302066714
A71: 46156 | B71: PRIME POLYMART PRIVATE LIMITED | C71: CMTRL-XS-20260429-0001 | D71: SAN 900 | E71: 27.5 | J71: 车牌号：桂N03027D 司机：冯生荣 手机：18877186336 身份证：45012219751103451X
A72: 46156 | B72: PT. Planet Chemicals | C72: CMTRL-XS-20260416-0001 | D72: SAN 900 | E72: 27.5 | J72: 车牌号：桂N11711D 司机：梁立仕 电话：13877796681 身份证号：452802197508206637
A73: 46158 | B73: PT. Planet Chemicals | C73: CMTRL-XS-20260416-0001 | D73: SAN 900 | E73: 27.5 | J73: 车号：桂N08230D 姓名：刘晋奎 电话：19127972967 身份证：452824197102052218
A74: 46158 | B74: BILLION ASCENT INDUSTRIAL LIMITED | C74: CMTRL-XS-20260331-0001 | D74: SAN 900 | E74: 27 | J74: 车号:桂NE5611 名字:韦德权 电话:18977715303 证:452824197101161834
A75: 46158 | B75: AYDIN PLASTIK TURIZM INSAAT SAN VE | C75: CMTRL-XS-20260408-0001 | D75: MABS CT2010 | E75: 27 | J75: 桂N99393 蓝 毅 13502119580 452731197606126039
... A119: 46190 | B119: Valutrans Investment Co., Limited | C119: CMTRL-XS-20260519-0001 | D119: 炭黑 N330 | E119: 20 | J119: 车号:桂P02806D 司机: 宁佳 身份证:450721198202176355 电话:13307874545
A120: 46201 | B120: Valutrans Investment Co., Limited | C120: CMTRL-XS-20260519-0001 | D120: 炭黑 N330 | E120: 20 | I120: 柜号:TCKU6193130 铅封号:SITZ880407 | J120: 车号:桂NC3611 司机:覃志绘 身份证:452724198201092855 电话:15807882685
A121: 46201 | B121: Valutrans Investment Co., Limited | C121: CMTRL-XS-20260519-0001 | D121: 炭黑 N330 | E121: 20 | I121: 柜号:FFAU7696589 铅封:SITZ880404 | J121: 车号:桂NC6582 司机:梁绍锋 身份证:452802197203243031 电话:13877740196
A122: 46201 | B122: Valutrans Investment Co., Limited | C122: CMTRL-XS-20260519-0001 | D122: 炭黑 N330 | E122: 20 | I122: 柜号:HPCU5262652 铅封号:SITZ880408 | J122: 车号:桂N08163D 司机:杨金双 身份证:220322197906182419 电话:13530544375
A123: 46201 | B123: Valutrans Investment Co., Limited | C123: CMTRL-XS-20260519-0001 | D123: 炭黑 N330 | E123: 20 | I123: 柜号:FFU5350067 铅封号:SITZ880405 | J123: 车号:桂P08928D 司机:韦高雄 身份证:452729199602130871 电话:19977848178
A124: 46212 | B124: AMAZON CORPORATE SERVICES PVT. LTD. | C124: CMTRL-XS-20260629-0002 | D124: SAN 900 | E124: 27.5 | J124: 粤H03036D 粤H9698挂 司机：张永华 电话：13457721505 身份证：450521197611082530 | K124: 广西奥利吉国际物流有限公司
A125: 46212 | B125: AMAZON CORPORATE SERVICES PVT. LTD. | C125: CMTRL-XS-20260629-0002 | D125: SAN 900 | E125: 25 | J125: 车号2：桂N11738D，挂：桂NCT36挂 司机：翁松锦 电话：13457704078 身份证：452802196908255177 | K125: 广西奥利吉国际物流有限公司
A126: 46212 | B126: AMAZON CORPORATE SERVICES PVT. LTD. | C126: CMTRL-XS-20260629-0002 | D126: HIPS 310 | E126: 1
A127: 46212 | B127: AMAZON CORPORATE SERVICES PVT. LTD. | C127: CMTRL-XS-20260629-0002 | D127: HIPS 612 | E127: 1
A128: 46212 | B128: AMAZON CORPORATE SERVICES PVT. LTD. | C128: CMTRL-XS-20260629-0002 | D128: MABS CT2010 | E128: 0.5
A129: 46213 | B129: ZHI YUE XIAN (VIETNAM) CO., LTD | C129: CMTRL-XS-20260630-0003 | D129: MABS CT2010 | E129: 27.5 | J129: 车牌：宁E95869 车挂：甘LA989挂 柜号：TGHU9973820 司机：马强 电话：13399339997 身份证号：622701198704053871 | K129: 东莞丽林达物流有限公司
A130: 46219 | B130: 宁波鹿鸣供应链管理有限公司 | C130: CMTRL-XS-20260715-0003 | D130: SAN 900 | E130: 34 | J130: 车号:苏GN9239 姓名/电话：范康/15195722242 身份证号：320723197708286016 | K130: 货之邦物流
A131: 46219 | B131: 宁波鹿鸣供应链管理有限公司 | C131: CMTRL-XS-20260715-0003 | D131: SAN 900 | E131: 8 | J131: 车号:豫KD31029 姓名/电话：肖守峰/19293742083 身份证号：411023198109274514 | K131: 货之邦物流
A132: 46226 | B132: BILLION ASCENT INDUSTRIAL LIMITED | C132: CMTRL-XS-20260715-0001 | D132: SAN 900 | E132: 27 | I132: 柜号: FFAU4301767 封签号: SITZ257183 | J132: 车牌号：桂NB8032 挂车号：桂NR562挂 司机：林斌 电话：13102108227 身份证：45020319710329073X | K132: 宁波鹏信国际货运代理有限公司
A133: 46226 | B133: BILLION ASCENT INDUSTRIAL LIMITED | C133: CMTRL-XS-20260715-0001 | D133: SAN 900 | E133: 27 | I133: 柜号：FFAU7555410 铅封：SITZ756943 | J133: 车牌号：桂NC1793 挂车号：桂AL193挂 司机：蓝冬明 电话：13163060872 身份证：452123198509233133 | K133: 宁波鹏信国际货运代理有限公司
A134: 46227 | B134: Polyram Plastic Industries LTD | C134: CMTRL-XS-20260709-0002 | D134: HIPS 612 | E134: 27 | J134: 车号:桂NC2156 司机:蒋小华 电话:18897665188 身份证号: 452323197303172212 | K134: 广西泛航国际物流有限公司
A135: 46227 | B135: BILLION ASCENT INDUSTRIAL LIMITED | C135: CMTRL-XS-20260331-0001 | D135: SAN 900 | E135: 27 | I135: 柜号FFAU6201793 封号SITZ381927 | J135: 车牌号：桂N97983 司机：李志权 电话：13502119580 身份证：452522197210210835 | K135: 宁波鹏信国际货运代理有限公司
A136: 46228 | B136: Synergy Industriez | C136: CMTRL-XS-20260723-0004 | D136: HIPS 612 | E136: 27.5 | J136: 桂NE7607 桂NCM19挂 姓名：马红波 电话：15296102463 身份证：230105197601261313 | K136: 广西奥利吉国际物流有限公司
A137: 46228 | B137: Synergy Industriez | C137: CMTRL-XS-20260723-0004 | D137: HIPS 612 | E137: 27.5 | J137: 车号:桂NE6208桂NM196挂司机:何雅业电话:18778766478身份证:450721198401254416 | K137: 广西奥利吉国际物流有限公司
A138: 46229 | B138: Synergy Industriez | C138: CMTRL-XS-20260723-0004 | D138: SAN 2800 | E138: 12.5 | J138: 桂NC3373 桂NV220挂 姓名：丁忠平 身份证：450721198701042212 电话：15107801430 | K138: 广西奥利吉国际物流有限公司
A139: 46229 | B139: Synergy Industriez | C139: CMTRL-XS-20260723-0004 | D139: SAN 4800 | E139: 15
A140: 46233 | B140: BOMBAY PLASTIC UDYOG | C140: CMTRL-XS-20260723-0001 | D140: SAN 2800 | E140: 14 | J140: 车牌号2：粤H03036D 挂车号：粤H9698挂 司机：张永华 电话：13457721505 身份证：450521197611082530 | K140: 广西奥利吉国际物流有限公司
A141: 46233 | B141: BOMBAY PLASTIC UDYOG | C141: CMTRL-XS-20260723-0001 | D141: SAN 4800 | E141: 13.5
A142: 46233 | B142: BOMBAY PLASTIC UDYOG | C142: CMTRL-XS-20260723-0001 | D142: HIPS-CH612 | E142: 27.5 | J142: 车牌号1:粤H09957D 挂车号:粤H9539挂 司机：钟厚昌 电话：13647776588 身份证：452802197811153910 | K142: 广西奥利吉国际物流有限公司
A143: 46235 | B143: PENTAPLAST SRL | C143: CMTRL-XS-20260630-0005 | D143: MABS CT2010 | E143: 15 | J143: 车牌号：桂NE5611 司机：韦德权 电话：18977715303 身份证：452824197101161834 | K143: 广西泛航国际物流有限公司
A144: 46235 | B144: ALPEX JOINT STOCK COMPANY | C144: CMTRL-XS-20260714-0010 | D144: SAN 900 | E144: 27.5 | H144: 提单号:SITGQISG080989 | I144: 箱号：FFAU1135343 铅封:SITD766875 | J144: 车号：桂NE1685 司机：谭 旭 电话 13752285222 身份证： 452728198803172735 | K144: 宁波鹏信国际货运代理有限公司
A145: 46239 | B145: PRIME POLYMART PRIVATE LIMITED | C145: CMTRL-XS-20260731-0001 | D145: SAN 900 | E145: 27.5 | J145: 车号：桂ND0169 姓名：黄瑞波 身份证：452802197509202750 电话：18277726326 | K145: 广西泛航国际物流有限公司
...
